Workbook

Sheet FC inventory
A1: Date | B1: Name of FC | C1: Movement | D1: Agemawo 1kg | E1: Boneless Beef 1kg | F1: Cow Hump 1kg | G1: Cow Head & Neck 1kg | H1: Goat Meat 1kg | I1: Chicken 1kg | J1: Titus 1kg (uncleaned) | K1: Titus 1kg (Cleaned) | L1: Hake 1kg (Cleaned) | M1: Hake 1kg (Uncleaned) | N1: Value Pack (Cow Tongue) | O1: Value Pack (Cow Assorted) | P1: Token Pack (Cow Minced Meat) | Q1: Token Pack (Agemawo) | R1: Token pack(boneless beef) | S1: Token Pack (Cow Tail) | T1: Token Pack (Cow Head & Neck) | U1: Token Pack (Cow Hump) | V1: Token Pack (Goat Meat) | W1: Token Pack (Chicken) | X1: Token Pack (Chicken Gizzard) | Y1: Token Pack (Pomo) | Z1: Token Pack (Shaki & Roundabout) | AA1: Token Pack (Cow Assorted) | AB1: Token Pack (Cow Leg) | AC1: Token Pack (Goat Assorted) | AD1: Token Pack (Titus) | AE1: Token Pack (Hake) | AF1: Token (small snail) | AG1: Token (big snail) | AH1: Token (Goat head & leg)
A2: 45317 | B2: BCT | C2: In | D2: 13 | E2: 5 | F2: 2 | G2: 3 | H2: 2 | I2: 60 | N2: 1 | O2: 2 | Q2: 17 | R2: 10 | S2: 2 | W2: 20 | X2: 5 | AA2: 6 | AB2: 5 | AC2: 1
A3: 45317 | B3: Bashorun | C3: In | D3: 13 | E3: 5 | G3: 3 | H3: 2 | I3: 60 | O3: 3 | R3: 10 | S3: 2 | W3: 17 | AA3: 6 | AB3: 5 | AC3: 1
A4: 45317 | B4: Apata | C4: In | D4: 13 | E4: 4 | F4: 1 | G4: 3 | H4: 1 | I4: 60 | N4: 1 | O4: 2 | Q4: 17 | R4: 10 | S4: 2 | W4: 20 | X4: 5 | AA4: 6 | AB4: 4 | AC4: 1
A5: 45317 | B5: BCT | C5: Out | D5: 4 | W5: 2
A6: 45318 | B6: Bashorun | C6: In | Q6: 17 | W6: 3 | X6: 5
A7: 45318 | B7: Felele | C7: In | D7: 11 | E7: 4 | F7: 2 | G7: 3 | H7: 2 | I7: 45 | N7: 1 | O7: 2 | Q7: 17 | R7: 10 | S7: 2 | W7: 20 | X7: 5 | AA7: 6 | AB7: 5 | AC7: 1
A8: 45318 | B8: Apata | C8: Out | D8: 1 | I8: 2 | R8: 1 | AA8: 1 | AB8: 1
A9: 45318 | B9: BCT | C9: Out | D9: 3 | E9: 1 | I9: 1 | O9: 1 | Q9: 2 | R9: 1 | S9: 1 | W9: 1 | X9: 1 | AA9: 2 | AB9: 1
A10: 45318 | B10: Bashorun | C10: Out | D10: 3 | I10: 3 | O10: 3 | R10: 1 | S10: 1 | W10: 3 | AA10: 1 | AB10: 1
A11: 45320 | B11: Alakia | C11: In | D11: 10 | E11: 4 | F11: 1 | G11: 1 | I11: 35 | N11: 1 | O11: 2 | Q11: 15 | R11: 8 | S11: 2 | W11: 14 | X11: 4 | AA11: 5 | AB11: 4 | AC11: 1
A12: 45320 | B12: Apata | C12: Out | D12: 1
A13: 45320 | B13: Bashorun | C13: Out | Q13: 1 | R13: 1 | S13: 1 | W13: 1 | X13: 3 | AC13: 1
A14: 45320 | B14: Alakia | C14: Out | I14: 1 | AA14: 1
A15: 45321 | B15: Alakia | C15: Out | F15: 1 | Q15: 1 | W15: 1 | AB15: 1
A16: 45321 | B16: Bashorun | C16: Out | I16: 2 | Q16: 1 | W16: 1
A17: 45321 | B17: Apata | C17: Out | E17: 1 | Q17: 2 | AB17: 3
A18: 45321 | B18: BCT | C18: Out | D18: 3 | AA18: 1
A19: 45321 | B19: Felele | C19: Out | D19: 1 | I19: 1 | Q19: 1 | S19: 2 | X19: 3 | AA19: 1
A20: 45322 | B20: Bashorun | C20: In | F20: 2
A21: 45322 | B21: Alakia | C21: Out | D21: 2 | I21: 3 | R21: 1 | X21: 1 | AA21: 1
A22: 45322 | B22: Bashorun | C22: Out | D22: 4 | E22: 1 | H22: 2 | I22: 1 | Q22: 1 | R22: 1 | W22: 1 | X22: 2 | AA22: 2 | AB22: 2
A23: 45322 | B23: Apata | C23: Out | D23: 2 | E23: 1 | Q23: 2 | R23: 1
A24: 45322 | B24: BCT | C24: Out | I24: 1 | Q24: 1
A25: 45322 | B25: Felele | C25: Out | D25: 2 | I25: 1
A26: 45323 | B26: Alakia | C26: Out | D26: 1 | G26: 1 | N26: 1 | S26: 1 | AB26: 1
A27: 45323 | B27: Bashorun | C27: Out | D27: 2 | I27: 3 | Q27: 1
A28: 45323 | B28: Apata | C28: Out | D28: 1
A29: 45323 | B29: BCT | C29: Out | D29: 1 | F29: 1 | I29: 1 | O29: 3 | X29: 1 | AA29: 1
A30: 45323 | B30: Felele | C30: Out | G30: 1 | I30: 5
A31: 45323 | B31: BCT | C31: In | O31: 2
A32: 45324 | B32: Alakia | C32: Out | I32: 1
A33: 45324 | B33: Bashorun | C33: Out | D33: 1 | I33: 2 | W33: 2 | AA33: 2
A34: 45324 | B34: Apata | C34: Out | X34: 2
A35: 45324 | B35: BCT | C35: Out | D35: 2 | G35: 2 | I35: 4 | Q35: 1 | X35: 2 | AA35: 1
A36: 45324 | B36: Felele | C36: Out | D36: 3 | F36: 1 | G36: 2 | O36: 1 | AB36: 1
A37: 45325 | B37: BCT | C37: In | D37: 7 | O37: 3 | X37: 4
A38: 45325 | B38: Bashorun | C38: In | D38: 7 | F38: 1 | I38: 5 | Q38: 10 | R38: 5 | W38: 8 | X38: 3 | AA38: 3 | AB38: 2
A39: 45325 | B39: Alakia | C39: Out | D39: 3 | Q39: 2 | S39: 1 | AA39: 2
A40: 45325 | B40: Bashorun | C40: Out | D40: 1 | I40: 2 | Q40: 4 | W40: 1
A41: 45325 | B41: Apata | C41: Out | E41: 1
A42: 45325 | B42: BCT | C42: Out | D42: 6 | E42: 1 | Q42: 1 | AA42: 1 | AB42: 1
A43: 45325 | B43: Felele | C43: Out | D43: 4 | E43: 4 | I43: 3 | Q43: 1 | X43: 2
A44: 45327 | B44: BCT | C44: In | D44: 4
A45: 45327 | B45: Alakia | C45: Out | I45: 1
A46: 45327 | B46: Bashorun | C46: Out
A47: 45327 | B47: Apata | C47: Out
A48: 45327 | B48: BCT | C48: Out | D48: 2 | E48: 3 | F48: 1 | G48: 1 | I48: 5 | O48: 1 | Q48: 1 | R48: 1 | W48: 1
A49: 45327 | B49: Felele | C49: Out | H49: 2 | AA49: 2 | AC49: 1
A50: 45328 | B50: Alakia | C50: Out | D50: 1 | I50: 1
A51: 45328 | B51: Bashorun | C51: Out | D51: 5 | E51: 2 | I51: 1
A52: 45328 | B52: BCT | C52: Out | D52: 1 | I52: 5 | O52: 1 | Q52: 1 | R52: 2 | AB52: 1 | AC52: 1
A53: 45328 | B53: Felele | C53: Out | D53: 1 | F53: 1 | I53: 2 | Q53: 2
A54: 45329 | B54: Alakia | C54: Out | D54: 2 | O54: 1 | Q54: 1 | X54: 2 | AC54: 1
A55: 45329 | B55: Bashorun | C55: Out | D55: 4 | E55: 2 | G55: 2 | I55: 3 | O55: 4 | Q55: 1 | X55: 3 | AA55: 4
A56: 45329 | B56: Apata | C56: Out | E56: 1 | H56: 1 | I56: 1
A57: 45329 | B57: BCT | C57: Out | I57: 2 | Q57: 3
A58: 45329 | B58: Felele | C58: Out | I58: 1 | O58: 1 | AA58: 2 | AB58: 4
A59: 45329 | B59: Bashorun | C59: In | O59: 7
A60: 45330 | B60: BCT | C60: In | O60: 4 | AA60: 3
A61: 45330 | B61: Apata | C61: In | AH61: 3
A62: 45330 | B62: Alakia | C62: Out | D62: 1 | I62: 2 | W62: 1
A63: 45330 | B63: Bashorun | C63: Out | I63: 2 | O63: 2 | Q63: 2
A64: 45330 | B64: Apata | C64: Out | S64: 1 | AA64: 1 | AH64: 3
A65: 45330 | B65: BCT | C65: Out | N65: 1 | O65: 2 | Q65: 1 | AA65: 1
A66: 45330 | B66: Felele | C66: Out | G66: 3 | AB66: 2
A67: 45330 | B67: Felele | C67: In | G67: 3 | AB67: 4
A68: 45331 | B68: Alakia | C68: Out | E68: 1 | I68: 1 | R68: 1 | X68: 1
A69: 45331 | B69: Bashorun | C69: Out | F69: 2 | G69: 1 | I69: 4 | O69: 1 | Q69: 7
A70: 45331 | B70: Apata | C70: Out | D70: 2 | I70: 1 | Q70: 2 | S70: 1
A71: 45331 | B71: BCT | C71: Out | D71: 4 | G71: 1 | H71: 2 | I71: 6 | O71: 4 | Q71: 4 | W71: 1 | X71: 1 | AA71: 1
A72: 45331 | B72: Felele | C72: Out | I72: 6 | N72: 1 | Q72: 5 | R72: 2 | AA72: 1 | AB72: 1

Sheet Apata
A1: =TODAY() -> 45889 | B1: Agemawo 1kg | C1: Boneless Beef 1kg | D1: Cow Hump 1kg | E1: Cow Head & Neck 1kg | F1: Goat Meat 1kg | G1: Chicken 1kg | H1: Titus 1kg (uncleaned) | I1: Titus 1kg (Cleaned) | J1: Hake 1kg (Cleaned) | K1: Hake 1kg (Uncleaned) | L1: Value Pack (Cow Tongue) | M1: Value Pack (Cow Assorted) | N1: Token Pack (Cow Minced Meat) | O1: Token Pack (Agemawo) | P1: Token pack(boneless beef) | Q1: Token Pack (Cow Tail) | R1: Token Pack (Cow Head & Neck) | S1: Token Pack (Cow Hump) | T1: Token Pack (Goat Meat) | U1: Token Pack (Chicken) | V1: Token Pack (Chicken Gizzard) | W1: Token Pack (Pomo) | X1: Token Pack (Shaki & Roundabout) | Y1: Token Pack (Cow Assorted) | Z1: Token Pack (Cow Leg) | AA1: Token Pack (Goat Assorted) | AB1: Token Pack (Titus) | AC1: Token Pack (Hake) | AD1: Token (small snail) | AE1: Token (big snail) | AF1: Token (Goat head & leg)
A2: Stock Count | B2: 0 | C2: 0 | D2: 0 | E2: 0 | F2: 0 | G2: 0 | H2: 0 | I2: 0 | J2: 0 | K2: 0 | L2: 0 | M2: 0 | N2: 0 | O2: 0 | P2: 0 | Q2: 0 | R2: 0 | S2: 0 | T2: 0 | U2: 0 | V2: 0 | W2: 0 | X2: 0 | Y2: 0 | Z2: 0 | AA2: 0 | AB2: 0 | AC2: 0 | AD2: 0 | AE2: 0 | AF2: 0
A3: Opening Stock | B3: =sumifs('FC inventory'!D2:D999,'FC inventory'!$A$2:$A999,"<"&$A$1,'FC inventory'!$B$2:$B999,"Apata",'FC inventory'!$C$2:$C999,"In")-sumifs('FC inventory'!D2:D999,'FC inventory'!$A$2:$A999,"<"&$A$1,'FC inventory'!$B$2:$B999,"Apata",'FC inventory'!$C$2:$C999,"Out")+SUMIFS('FC inventory'!D2:D999,'FC inventory'!$A$2:$A999,"<"&$A$1,'FC inventory'!$B$2:$B999,"Apata",'FC inventory'!$C$2:$C999,"Returned") -> 6 | C3: =sumifs('FC inventory'!E2:E999,'FC inventory'!$A$2:$A999,"<"&$A$1,'FC inventory'!$B$2:$B999,"Apata",'FC inventory'!$C$2:$C999,"In")-sumifs('FC inventory'!E2:E999,'FC inventory'!$A$2:$A999,"<"&$A$1,'FC inventory'!$B$2:$B999,"Apata",'FC inventory'!$C$2:$C999,"Out")+SUMIFS('FC inventory'!E2:E999,'FC inventory'!$A$2:$A999,"<"&$A$1,'FC inventory'!$B$2:$B999,"Apata",'FC inventory'!$C$2:$C999,"Returned") -> 0 | D3: =sumifs('FC inventory'!F2:F999,'FC inventory'!$A$2:$A999,"<"&$A$1,'FC inventory'!$B$2:$B999,"Apata",'FC inventory'!$C$2:$C999,"In")-sumifs('FC inventory'!F2:F999,'FC inventory'!$A$2:$A999,"<"&$A$1,'FC inventory'!$B$2:$B999,"Apata",'FC inventory'!$C$2:$C999,"Out")+SUMIFS('FC inventory'!F2:F999,'FC inventory'!$A$2:$A999,"<"&$A$1,'FC inventory'!$B$2:$B999,"Apata",'FC inventory'!$C$2:$C999,"Returned") -> 1 | E3: =sumifs('FC inventory'!G2:G999,'FC inventory'!$A$2:$A999,"<"&$A$1,'FC inventory'!$B$2:$B999,"Apata",'FC inventory'!$C$2:$C999,"In")-sumifs('FC inventory'!G2:G999,'FC inventory'!$A$2:$A999,"<"&$A$1,'FC inventory'!$B$2:$B999,"Apata",'FC inventory'!$C$2:$C999,"Out")+SUMIFS('FC inventory'!G2:G999,'FC inventory'!$A$2:$A999,"<"&$A$1,'FC inventory'!$B$2:$B999,"Apata",'FC inventory'!$C$2:$C999,"Returned") -> 3 | F3: =sumifs('FC inventory'!H2:H999,'FC inventory'!$A$2:$A999,"<"&$A$1,'FC inventory'!$B$2:$B999,"Apata",'FC inventory'!$C$2:$C999,"In")-sumifs('FC inventory'!H2:H999,'FC inventory'!$A$2:$A999,"<"&$A$1,'FC inventory'!$B$2:$B999,"Apata",'FC inventory'!$C$2:$C999,"Out")+SUMIFS('FC inventory'!H2:H999,'FC inventory'!$A$2:$A999,"<"&$A$1,'FC inventory'!$B$2:$B999,"Apata",'FC inventory'!$C$2:$C999,"Returned") -> 0 | G3: =sumifs('FC inventory'!I2:I999,'FC inventory'!$A$2:$A999,"<"&$A$1,'FC inventory'!$B$2:$B999,"Apata",'FC inventory'!$C$2:$C999,"In")-sumifs('FC inventory'!I2:I999,'FC inventory'!$A$2:$A999,"<"&$A$1,'FC inventory'!$B$2:$B999,"Apata",'FC inventory'!$C$2:$C999,"Out")+SUMIFS('FC inventory'!I2:I999,'FC inventory'!$A$2:$A999,"<"&$A$1,'FC inventory'!$B$2:$B999,"Apata",'FC inventory'!$C$2:$C999,"Returned") -> 56 | H3: =sumifs('FC inventory'!J2:J999,'FC inventory'!$A$2:$A999,"<"&$A$1,'FC inventory'!$B$2:$B999,"Apata",'FC inventory'!$C$2:$C999,"In")-sumifs('FC inventory'!J2:J999,'FC inventory'!$A$2:$A999,"<"&$A$1,'FC inventory'!$B$2:$B999,"Apata",'FC inventory'!$C$2:$C999,"Out")+SUMIFS('FC inventory'!J2:J999,'FC inventory'!$A$2:$A999,"<"&$A$1,'FC inventory'!$B$2:$B999,"Apata",'FC inventory'!$C$2:$C999,"Returned") -> 0 | I3: =sumifs('FC inventory'!K2:K999,'FC inventory'!$A$2:$A999,"<"&$A$1,'FC inventory'!$B$2:$B999,"Apata",'FC inventory'!$C$2:$C999,"In")-sumifs('FC inventory'!K2:K999,'FC inventory'!$A$2:$A999,"<"&$A$1,'FC inventory'!$B$2:$B999,"Apata",'FC inventory'!$C$2:$C999,"Out")+SUMIFS('FC inventory'!K2:K999,'FC inventory'!$A$2:$A999,"<"&$A$1,'FC inventory'!$B$2:$B999,"Apata",'FC inventory'!$C$2:$C999,"Returned") -> 0 | ... AF3: =sumifs('FC inventory'!AH2:AH999,'FC inventory'!$A$2:$A999,"<"&$A$1,'FC inventory'!$B$2:$B999,"Apata",'FC inventory'!$C$2:$C999,"In")-sumifs('FC inventory'!AH2:AH999,'FC inventory'!$A$2:$A999,"<"&$A$1,'FC inventory'!$B$2:$B999,"Apata",'FC inventory'!$C$2:$C999,"Out")+SUMIFS('FC inventory'!AH2:AH999,'FC inventory'!$A$2:$A999,"<"&$A$1,'FC inventory'!$B$2:$B999,"Apata",'FC inventory'!$C$2:$C999,"Returned") -> 0
A4: In | B4: =sumifs('FC inventory'!D2:D999,'FC inventory'!$A$2:$A999,$A$1,'FC inventory'!$B$2:$B999,"Apata",'FC inventory'!$C$2:$C999,"In") -> 0 | C4: =sumifs('FC inventory'!E2:E999,'FC inventory'!$A$2:$A999,$A$1,'FC inventory'!$B$2:$B999,"Apata",'FC inventory'!$C$2:$C999,"In") -> 0 | D4: =sumifs('FC inventory'!F2:F999,'FC inventory'!$A$2:$A999,$A$1,'FC inventory'!$B$2:$B999,"Apata",'FC inventory'!$C$2:$C999,"In") -> 0 | E4: =sumifs('FC inventory'!G2:G999,'FC inventory'!$A$2:$A999,$A$1,'FC inventory'!$B$2:$B999,"Apata",'FC inventory'!$C$2:$C999,"In") -> 0 | F4: =sumifs('FC inventory'!H2:H999,'FC inventory'!$A$2:$A999,$A$1,'FC inventory'!$B$2:$B999,"Apata",'FC inventory'!$C$2:$C999,"In") -> 0 | G4: =sumifs('FC inventory'!I2:I999,'FC inventory'!$A$2:$A999,$A$1,'FC inventory'!$B$2:$B999,"Apata",'FC inventory'!$C$2:$C999,"In") -> 0 | H4: =sumifs('FC inventory'!J2:J999,'FC inventory'!$A$2:$A999,$A$1,'FC inventory'!$B$2:$B999,"Apata",'FC inventory'!$C$2:$C999,"In") -> 0 | I4: =sumifs('FC inventory'!K2:K999,'FC inventory'!$A$2:$A999,$A$1,'FC inventory'!$B$2:$B999,"Apata",'FC inventory'!$C$2:$C999,"In") -> 0 | ... AF4: =sumifs('FC inventory'!AH2:AH999,'FC inventory'!$A$2:$A999,$A$1,'FC inventory'!$B$2:$B999,"Apata",'FC inventory'!$C$2:$C999,"In") -> 0
A5: Out | B5: =sumifs('FC inventory'!D2:D999,'FC inventory'!$A$2:$A999,$A$1,'FC inventory'!$B$2:$B999,"Apata",'FC inventory'!$C$2:$C999,"Out") -> 0 | C5: =sumifs('FC inventory'!E2:E999,'FC inventory'!$A$2:$A999,$A$1,'FC inventory'!$B$2:$B999,"Apata",'FC inventory'!$C$2:$C999,"Out") -> 0 | D5: =sumifs('FC inventory'!F2:F999,'FC inventory'!$A$2:$A999,$A$1,'FC inventory'!$B$2:$B999,"Apata",'FC inventory'!$C$2:$C999,"Out") -> 0 | E5: =sumifs('FC inventory'!G2:G999,'FC inventory'!$A$2:$A999,$A$1,'FC inventory'!$B$2:$B999,"Apata",'FC inventory'!$C$2:$C999,"Out") -> 0 | F5: =sumifs('FC inventory'!H2:H999,'FC inventory'!$A$2:$A999,$A$1,'FC inventory'!$B$2:$B999,"Apata",'FC inventory'!$C$2:$C999,"Out") -> 0 | G5: =sumifs('FC inventory'!I2:I999,'FC inventory'!$A$2:$A999,$A$1,'FC inventory'!$B$2:$B999,"Apata",'FC inventory'!$C$2:$C999,"Out") -> 0 | H5: =sumifs('FC inventory'!J2:J999,'FC inventory'!$A$2:$A999,$A$1,'FC inventory'!$B$2:$B999,"Apata",'FC inventory'!$C$2:$C999,"Out") -> 0 | I5: =sumifs('FC inventory'!K2:K999,'FC inventory'!$A$2:$A999,$A$1,'FC inventory'!$B$2:$B999,"Apata",'FC inventory'!$C$2:$C999,"Out") -> 0 | ... AF5: =sumifs('FC inventory'!AH2:AH999,'FC inventory'!$A$2:$A999,$A$1,'FC inventory'!$B$2:$B999,"Apata",'FC inventory'!$C$2:$C999,"Out") -> 0
A6: Returned | B6: =SUMIFS('FC inventory'!D2:D999,'FC inventory'!$A$2:$A999,$A$1,'FC inventory'!$B$2:$B999,"Apata",'FC inventory'!$C$2:$C999,"Returned") -> 0 | C6: =SUMIFS('FC inventory'!E2:E999,'FC inventory'!$A$2:$A999,$A$1,'FC inventory'!$B$2:$B999,"Apata",'FC inventory'!$C$2:$C999,"Returned") -> 0 | D6: =SUMIFS('FC inventory'!F2:F999,'FC inventory'!$A$2:$A999,$A$1,'FC inventory'!$B$2:$B999,"Apata",'FC inventory'!$C$2:$C999,"Returned") -> 0 | E6: =SUMIFS('FC inventory'!G2:G999,'FC inventory'!$A$2:$A999,$A$1,'FC inventory'!$B$2:$B999,"Apata",'FC inventory'!$C$2:$C999,"Returned") -> 0 | F6: =SUMIFS('FC inventory'!H2:H999,'FC inventory'!$A$2:$A999,$A$1,'FC inventory'!$B$2:$B999,"Apata",'FC inventory'!$C$2:$C999,"Returned") -> 0 | G6: =SUMIFS('FC inventory'!I2:I999,'FC inventory'!$A$2:$A999,$A$1,'FC inventory'!$B$2:$B999,"Apata",'FC inventory'!$C$2:$C999,"Returned") -> 0 | H6: =SUMIFS('FC inventory'!J2:J999,'FC inventory'!$A$2:$A999,$A$1,'FC inventory'!$B$2:$B999,"Apata",'FC inventory'!$C$2:$C999,"Returned") -> 0 | I6: =SUMIFS('FC inventory'!K2:K999,'FC inventory'!$A$2:$A999,$A$1,'FC inventory'!$B$2:$B999,"Apata",'FC inventory'!$C$2:$C999,"Returned") -> 0 | ... AF6: =SUMIFS('FC inventory'!AH2:AH999,'FC inventory'!$A$2:$A999,$A$1,'FC inventory'!$B$2:$B999,"Apata",'FC inventory'!$C$2:$C999,"Returned") -> 0
A7: Balance | B7: =B3+B4-B5+B6 -> 6 | C7: =C3+C4-C5+C6 -> 0 | D7: =D3+D4-D5+D6 -> 1 | E7: =E3+E4-E5+E6 -> 3 | F7: =F3+F4-F5+F6 -> 0 | G7: =G3+G4-G5+G6 -> 56 | H7: =H3+H4-H5+H6 -> 0 | I7: =I3+I4-I5+I6 -> 0 | ... AF7: =AF3+AF4-AF5+AF6 -> 0

Sheet Alakia
A1: =TODAY() -> 45889 | B1: Agemawo 1kg | C1: Boneless Beef 1kg | D1: Cow Hump 1kg | E1: Cow Head & Neck 1kg | F1: Goat Meat 1kg | G1: Chicken 1kg | H1: Titus 1kg (uncleaned) | I1: Titus 1kg (Cleaned) | J1: Hake 1kg (Cleaned) | K1: Hake 1kg (Uncleaned) | L1: Value Pack (Cow Tongue) | M1: Value Pack (Cow Assorted) | N1: Token Pack (Cow Minced Meat) | O1: Token Pack (Agemawo) | P1: Token pack(boneless beef) | Q1: Token Pack (Cow Tail) | R1: Token Pack (Cow Head & Neck) | S1: Token Pack (Cow Hump) | T1: Token Pack (Goat Meat) | U1: Token Pack (Chicken) | V1: Token Pack (Chicken Gizzard) | W1: Token Pack (Pomo) | X1: Token Pack (Shaki & Roundabout) | Y1: Token Pack (Cow Assorted) | Z1: Token Pack (Cow Leg) | AA1: Token Pack (Goat Assorted) | AB1: Token Pack (Titus) | AC1: Token Pack (Hake) | AD1: Token (small snail) | AE1: Token (big snail) | AF1: Token (Goat head & leg)
A2: Stock Count | B2: 0 | C2: 0 | D2: 0 | E2: 0 | F2: 0 | G2: 0 | H2: 0 | I2: 0 | J2: 0 | K2: 0 | L2: 0 | M2: 0 | N2: 0 | O2: 0 | P2: 0 | Q2: 0 | R2: 0 | S2: 0 | T2: 0 | U2: 0 | V2: 0 | W2: 0 | X2: 0 | Y2: 0 | Z2: 0 | AA2: 0 | AB2: 0 | AC2: 0 | AD2: 0 | AE2: 0 | AF2: 0
A3: Opening Stock | B3: =sumifs('FC inventory'!D2:D999,'FC inventory'!$A$2:$A999,"<"&$A$1,'FC inventory'!$B$2:$B999,"Alakia",'FC inventory'!$C$2:$C999,"In")-sumifs('FC inventory'!D2:D999,'FC inventory'!$A$2:$A999,"<"&$A$1,'FC inventory'!$B$2:$B999,"Alakia",'FC inventory'!$C$2:$C999,"Out")+SUMIFS('FC inventory'!D2:D999,'FC inventory'!$A$2:$A999,"<"&$A$1,'FC inventory'!$B$2:$B999,"Alakia",'FC inventory'!$C$2:$C999,"Returned") -> 0 | C3: =sumifs('FC inventory'!E2:E999,'FC inventory'!$A$2:$A999,"<"&$A$1,'FC inventory'!$B$2:$B999,"Alakia",'FC inventory'!$C$2:$C999,"In")-sumifs('FC inventory'!E2:E999,'FC inventory'!$A$2:$A999,"<"&$A$1,'FC inventory'!$B$2:$B999,"Alakia",'FC inventory'!$C$2:$C999,"Out")+SUMIFS('FC inventory'!E2:E999,'FC inventory'!$A$2:$A999,"<"&$A$1,'FC inventory'!$B$2:$B999,"Alakia",'FC inventory'!$C$2:$C999,"Returned") -> 3 | D3: =sumifs('FC inventory'!F2:F999,'FC inventory'!$A$2:$A999,"<"&$A$1,'FC inventory'!$B$2:$B999,"Alakia",'FC inventory'!$C$2:$C999,"In")-sumifs('FC inventory'!F2:F999,'FC inventory'!$A$2:$A999,"<"&$A$1,'FC inventory'!$B$2:$B999,"Alakia",'FC inventory'!$C$2:$C999,"Out")+SUMIFS('FC inventory'!F2:F999,'FC inventory'!$A$2:$A999,"<"&$A$1,'FC inventory'!$B$2:$B999,"Alakia",'FC inventory'!$C$2:$C999,"Returned") -> 0 | E3: =sumifs('FC inventory'!G2:G999,'FC inventory'!$A$2:$A999,"<"&$A$1,'FC inventory'!$B$2:$B999,"Alakia",'FC inventory'!$C$2:$C999,"In")-sumifs('FC inventory'!G2:G999,'FC inventory'!$A$2:$A999,"<"&$A$1,'FC inventory'!$B$2:$B999,"Alakia",'FC inventory'!$C$2:$C999,"Out")+SUMIFS('FC inventory'!G2:G999,'FC inventory'!$A$2:$A999,"<"&$A$1,'FC inventory'!$B$2:$B999,"Alakia",'FC inventory'!$C$2:$C999,"Returned") -> 0 | F3: =sumifs('FC inventory'!H2:H999,'FC inventory'!$A$2:$A999,"<"&$A$1,'FC inventory'!$B$2:$B999,"Alakia",'FC inventory'!$C$2:$C999,"In")-sumifs('FC inventory'!H2:H999,'FC inventory'!$A$2:$A999,"<"&$A$1,'FC inventory'!$B$2:$B999,"Alakia",'FC inventory'!$C$2:$C999,"Out")+SUMIFS('FC inventory'!H2:H999,'FC inventory'!$A$2:$A999,"<"&$A$1,'FC inventory'!$B$2:$B999,"Alakia",'FC inventory'!$C$2:$C999,"Returned") -> 0 | G3: =sumifs('FC inventory'!I2:I999,'FC inventory'!$A$2:$A999,"<"&$A$1,'FC inventory'!$B$2:$B999,"Alakia",'FC inventory'!$C$2:$C999,"In")-sumifs('FC inventory'!I2:I999,'FC inventory'!$A$2:$A999,"<"&$A$1,'FC inventory'!$B$2:$B999,"Alakia",'FC inventory'!$C$2:$C999,"Out")+SUMIFS('FC inventory'!I2:I999,'FC inventory'!$A$2:$A999,"<"&$A$1,'FC inventory'!$B$2:$B999,"Alakia",'FC inventory'!$C$2:$C999,"Returned") -> 25 | H3: =sumifs('FC inventory'!J2:J999,'FC inventory'!$A$2:$A999,"<"&$A$1,'FC inventory'!$B$2:$B999,"Alakia",'FC inventory'!$C$2:$C999,"In")-sumifs('FC inventory'!J2:J999,'FC inventory'!$A$2:$A999,"<"&$A$1,'FC inventory'!$B$2:$B999,"Alakia",'FC inventory'!$C$2:$C999,"Out")+SUMIFS('FC inventory'!J2:J999,'FC inventory'!$A$2:$A999,"<"&$A$1,'FC inventory'!$B$2:$B999,"Alakia",'FC inventory'!$C$2:$C999,"Returned") -> 0 | I3: =sumifs('FC inventory'!K2:K999,'FC inventory'!$A$2:$A999,"<"&$A$1,'FC inventory'!$B$2:$B999,"Alakia",'FC inventory'!$C$2:$C999,"In")-sumifs('FC inventory'!K2:K999,'FC inventory'!$A$2:$A999,"<"&$A$1,'FC inventory'!$B$2:$B999,"Alakia",'FC inventory'!$C$2:$C999,"Out")+SUMIFS('FC inventory'!K2:K999,'FC inventory'!$A$2:$A999,"<"&$A$1,'FC inventory'!$B$2:$B999,"Alakia",'FC inventory'!$C$2:$C999,"Returned") -> 0 | ... AF3: =sumifs('FC inventory'!AH2:AH999,'FC inventory'!$A$2:$A999,"<"&$A$1,'FC inventory'!$B$2:$B999,"Alakia",'FC inventory'!$C$2:$C999,"In")-sumifs('FC inventory'!AH2:AH999,'FC inventory'!$A$2:$A999,"<"&$A$1,'FC inventory'!$B$2:$B999,"Alakia",'FC inventory'!$C$2:$C999,"Out")+SUMIFS('FC inventory'!AH2:AH999,'FC inventory'!$A$2:$A999,"<"&$A$1,'FC inventory'!$B$2:$B999,"Alakia",'FC inventory'!$C$2:$C999,"Returned") -> 0
A4: In | B4: =sumifs('FC inventory'!D2:D999,'FC inventory'!$A$2:$A999,$A$1,'FC inventory'!$B$2:$B999,"Alakia",'FC inventory'!$C$2:$C999,"In") -> 0 | C4: =sumifs('FC inventory'!E2:E999,'FC inventory'!$A$2:$A999,$A$1,'FC inventory'!$B$2:$B999,"Alakia",'FC inventory'!$C$2:$C999,"In") -> 0 | D4: =sumifs('FC inventory'!F2:F999,'FC inventory'!$A$2:$A999,$A$1,'FC inventory'!$B$2:$B999,"Alakia",'FC inventory'!$C$2:$C999,"In") -> 0 | E4: =sumifs('FC inventory'!G2:G999,'FC inventory'!$A$2:$A999,$A$1,'FC inventory'!$B$2:$B999,"Alakia",'FC inventory'!$C$2:$C999,"In") -> 0 | F4: =sumifs('FC inventory'!H2:H999,'FC inventory'!$A$2:$A999,$A$1,'FC inventory'!$B$2:$B999,"Alakia",'FC inventory'!$C$2:$C999,"In") -> 0 | G4: =sumifs('FC inventory'!I2:I999,'FC inventory'!$A$2:$A999,$A$1,'FC inventory'!$B$2:$B999,"Alakia",'FC inventory'!$C$2:$C999,"In") -> 0 | H4: =sumifs('FC inventory'!J2:J999,'FC inventory'!$A$2:$A999,$A$1,'FC inventory'!$B$2:$B999,"Alakia",'FC inventory'!$C$2:$C999,"In") -> 0 | I4: =sumifs('FC inventory'!K2:K999,'FC inventory'!$A$2:$A999,$A$1,'FC inventory'!$B$2:$B999,"Alakia",'FC inventory'!$C$2:$C999,"In") -> 0 | ... AF4: =sumifs('FC inventory'!AH2:AH999,'FC inventory'!$A$2:$A999,$A$1,'FC inventory'!$B$2:$B999,"Alakia",'FC inventory'!$C$2:$C999,"In") -> 0
A5: Out | B5: =sumifs('FC inventory'!D2:D999,'FC inventory'!$A$2:$A999,$A$1,'FC inventory'!$B$2:$B999,"Alakia",'FC inventory'!$C$2:$C999,"Out") -> 0 | C5: =sumifs('FC inventory'!E2:E999,'FC inventory'!$A$2:$A999,$A$1,'FC inventory'!$B$2:$B999,"Alakia",'FC inventory'!$C$2:$C999,"Out") -> 0 | D5: =sumifs('FC inventory'!F2:F999,'FC inventory'!$A$2:$A999,$A$1,'FC inventory'!$B$2:$B999,"Alakia",'FC inventory'!$C$2:$C999,"Out") -> 0 | E5: =sumifs('FC inventory'!G2:G999,'FC inventory'!$A$2:$A999,$A$1,'FC inventory'!$B$2:$B999,"Alakia",'FC inventory'!$C$2:$C999,"Out") -> 0 | F5: =sumifs('FC inventory'!H2:H999,'FC inventory'!$A$2:$A999,$A$1,'FC inventory'!$B$2:$B999,"Alakia",'FC inventory'!$C$2:$C999,"Out") -> 0 | G5: =sumifs('FC inventory'!I2:I999,'FC inventory'!$A$2:$A999,$A$1,'FC inventory'!$B$2:$B999,"Alakia",'FC inventory'!$C$2:$C999,"Out") -> 0 | H5: =sumifs('FC inventory'!J2:J999,'FC inventory'!$A$2:$A999,$A$1,'FC inventory'!$B$2:$B999,"Alakia",'FC inventory'!$C$2:$C999,"Out") -> 0 | I5: =sumifs('FC inventory'!K2:K999,'FC inventory'!$A$2:$A999,$A$1,'FC inventory'!$B$2:$B999,"Alakia",'FC inventory'!$C$2:$C999,"Out") -> 0 | ... AF5: =sumifs('FC inventory'!AH2:AH999,'FC inventory'!$A$2:$A999,$A$1,'FC inventory'!$B$2:$B999,"Alakia",'FC inventory'!$C$2:$C999,"Out") -> 0
A6: Returned | B6: =SUMIFS('FC inventory'!D2:D999,'FC inventory'!$A$2:$A999,$A$1,'FC inventory'!$B$2:$B999,"Alakia",'FC inventory'!$C$2:$C999,"Returned") -> 0 | C6: =SUMIFS('FC inventory'!E2:E999,'FC inventory'!$A$2:$A999,$A$1,'FC inventory'!$B$2:$B999,"Alakia",'FC inventory'!$C$2:$C999,"Returned") -> 0 | D6: =SUMIFS('FC inventory'!F2:F999,'FC inventory'!$A$2:$A999,$A$1,'FC inventory'!$B$2:$B999,"Alakia",'FC inventory'!$C$2:$C999,"Returned") -> 0 | E6: =SUMIFS('FC inventory'!G2:G999,'FC inventory'!$A$2:$A999,$A$1,'FC inventory'!$B$2:$B999,"Alakia",'FC inventory'!$C$2:$C999,"Returned") -> 0 | F6: =SUMIFS('FC inventory'!H2:H999,'FC inventory'!$A$2:$A999,$A$1,'FC inventory'!$B$2:$B999,"Alakia",'FC inventory'!$C$2:$C999,"Returned") -> 0 | G6: =SUMIFS('FC inventory'!I2:I999,'FC inventory'!$A$2:$A999,$A$1,'FC inventory'!$B$2:$B999,"Alakia",'FC inventory'!$C$2:$C999,"Returned") -> 0 | H6: =SUMIFS('FC inventory'!J2:J999,'FC inventory'!$A$2:$A999,$A$1,'FC inventory'!$B$2:$B999,"Alakia",'FC inventory'!$C$2:$C999,"Returned") -> 0 | I6: =SUMIFS('FC inventory'!K2:K999,'FC inventory'!$A$2:$A999,$A$1,'FC inventory'!$B$2:$B999,"Alakia",'FC inventory'!$C$2:$C999,"Returned") -> 0 | ... AF6: =SUMIFS('FC inventory'!AH2:AH999,'FC inventory'!$A$2:$A999,$A$1,'FC inventory'!$B$2:$B999,"Alakia",'FC inventory'!$C$2:$C999,"Returned") -> 0
A7: Balance | B7: =B3+B4-B5+B6 -> 0 | C7: =C3+C4-C5+C6 -> 3 | D7: =D3+D4-D5+D6 -> 0 | E7: =E3+E4-E5+E6 -> 0 | F7: =F3+F4-F5+F6 -> 0 | G7: =G3+G4-G5+G6 -> 25 | H7: =H3+H4-H5+H6 -> 0 | I7: =I3+I4-I5+I6 -> 0 | ... AF7: =AF3+AF4-AF5+AF6 -> 0
AA18: .

Sheet Bashorun
A1: =TODAY() -> 45889 | B1: Agemawo 1kg | C1: Boneless Beef 1kg | D1: Cow Hump 1kg | E1: Cow Head & Neck 1kg | F1: Goat Meat 1kg | G1: Chicken 1kg | H1: Titus 1kg (uncleaned) | I1: Titus 1kg (Cleaned) | J1: Hake 1kg (Cleaned) | K1: Hake 1kg (Uncleaned) | L1: Value Pack (Cow Tongue) | M1: Value Pack (Cow Assorted) | N1: Token Pack (Cow Minced Meat) | O1: Token Pack (Agemawo) | P1: Token pack(boneless beef) | Q1: Token Pack (Cow Tail) | R1: Token Pack (Cow Head & Neck) | S1: Token Pack (Cow Hump) | T1: Token Pack (Goat Meat) | U1: Token Pack (Chicken) | V1: Token Pack (Chicken Gizzard) | W1: Token Pack (Pomo) | X1: Token Pack (Shaki & Roundabout) | Y1: Token Pack (Cow Assorted) | Z1: Token Pack (Cow Leg) | AA1: Token Pack (Goat Assorted) | AB1: Token Pack (Titus) | AC1: Token Pack (Hake) | AD1: Token (small snail) | AE1: Token (big snail) | AF1: Token (Goat head & leg)
A2: Stock Count | B2: 0 | C2: 0 | D2: 0 | E2: 0 | F2: 0 | G2: 0 | H2: 0 | I2: 0 | J2: 0 | K2: 0 | L2: 0 | M2: 0 | N2: 0 | O2: 0 | P2: 0 | Q2: 0 | R2: 0 | S2: 0 | T2: 0 | U2: 0 | V2: 0 | W2: 0 | X2: 0 | Y2: 0 | Z2: 0 | AA2: 0 | AB2: 0 | AC2: 0 | AD2: 0 | AE2: 0 | AF2: 0
A3: Opening Stock | B3: =sumifs('FC inventory'!D2:D984,'FC inventory'!$A$2:$A984,"<"&$A$1,'FC inventory'!$B$2:$B984,"Bashorun",'FC inventory'!$C$2:$C984,"In")-sumifs('FC inventory'!D2:D984,'FC inventory'!$A$2:$A984,"<"&$A$1,'FC inventory'!$B$2:$B984,"Bashorun",'FC inventory'!$C$2:$C984,"Out")+SUMIFS('FC inventory'!D2:D984,'FC inventory'!$A$2:$A984,"<"&$A$1,'FC inventory'!$B$2:$B984,"Bashorun",'FC inventory'!$C$2:$C984,"Returned") -> 0 | C3: =sumifs('FC inventory'!E2:E984,'FC inventory'!$A$2:$A984,"<"&$A$1,'FC inventory'!$B$2:$B984,"Bashorun",'FC inventory'!$C$2:$C984,"In")-sumifs('FC inventory'!E2:E984,'FC inventory'!$A$2:$A984,"<"&$A$1,'FC inventory'!$B$2:$B984,"Bashorun",'FC inventory'!$C$2:$C984,"Out")+SUMIFS('FC inventory'!E2:E984,'FC inventory'!$A$2:$A984,"<"&$A$1,'FC inventory'!$B$2:$B984,"Bashorun",'FC inventory'!$C$2:$C984,"Returned") -> 0 | D3: =sumifs('FC inventory'!F2:F984,'FC inventory'!$A$2:$A984,"<"&$A$1,'FC inventory'!$B$2:$B984,"Bashorun",'FC inventory'!$C$2:$C984,"In")-sumifs('FC inventory'!F2:F984,'FC inventory'!$A$2:$A984,"<"&$A$1,'FC inventory'!$B$2:$B984,"Bashorun",'FC inventory'!$C$2:$C984,"Out")+SUMIFS('FC inventory'!F2:F984,'FC inventory'!$A$2:$A984,"<"&$A$1,'FC inventory'!$B$2:$B984,"Bashorun",'FC inventory'!$C$2:$C984,"Returned") -> 1 | E3: =sumifs('FC inventory'!G2:G984,'FC inventory'!$A$2:$A984,"<"&$A$1,'FC inventory'!$B$2:$B984,"Bashorun",'FC inventory'!$C$2:$C984,"In")-sumifs('FC inventory'!G2:G984,'FC inventory'!$A$2:$A984,"<"&$A$1,'FC inventory'!$B$2:$B984,"Bashorun",'FC inventory'!$C$2:$C984,"Out")+SUMIFS('FC inventory'!G2:G984,'FC inventory'!$A$2:$A984,"<"&$A$1,'FC inventory'!$B$2:$B984,"Bashorun",'FC inventory'!$C$2:$C984,"Returned") -> 0 | F3: =sumifs('FC inventory'!H2:H984,'FC inventory'!$A$2:$A984,"<"&$A$1,'FC inventory'!$B$2:$B984,"Bashorun",'FC inventory'!$C$2:$C984,"In")-sumifs('FC inventory'!H2:H984,'FC inventory'!$A$2:$A984,"<"&$A$1,'FC inventory'!$B$2:$B984,"Bashorun",'FC inventory'!$C$2:$C984,"Out")+SUMIFS('FC inventory'!H2:H984,'FC inventory'!$A$2:$A984,"<"&$A$1,'FC inventory'!$B$2:$B984,"Bashorun",'FC inventory'!$C$2:$C984,"Returned") -> 0 | G3: =sumifs('FC inventory'!I2:I984,'FC inventory'!$A$2:$A984,"<"&$A$1,'FC inventory'!$B$2:$B984,"Bashorun",'FC inventory'!$C$2:$C984,"In")-sumifs('FC inventory'!I2:I984,'FC inventory'!$A$2:$A984,"<"&$A$1,'FC inventory'!$B$2:$B984,"Bashorun",'FC inventory'!$C$2:$C984,"Out")+SUMIFS('FC inventory'!I2:I984,'FC inventory'!$A$2:$A984,"<"&$A$1,'FC inventory'!$B$2:$B984,"Bashorun",'FC inventory'!$C$2:$C984,"Returned") -> 42 | H3: =sumifs('FC inventory'!J2:J984,'FC inventory'!$A$2:$A984,"<"&$A$1,'FC inventory'!$B$2:$B984,"Bashorun",'FC inventory'!$C$2:$C984,"In")-sumifs('FC inventory'!J2:J984,'FC inventory'!$A$2:$A984,"<"&$A$1,'FC inventory'!$B$2:$B984,"Bashorun",'FC inventory'!$C$2:$C984,"Out")+SUMIFS('FC inventory'!J2:J984,'FC inventory'!$A$2:$A984,"<"&$A$1,'FC inventory'!$B$2:$B984,"Bashorun",'FC inventory'!$C$2:$C984,"Returned") -> 0 | I3: =sumifs('FC inventory'!K2:K984,'FC inventory'!$A$2:$A984,"<"&$A$1,'FC inventory'!$B$2:$B984,"Bashorun",'FC inventory'!$C$2:$C984,"In")-sumifs('FC inventory'!K2:K984,'FC inventory'!$A$2:$A984,"<"&$A$1,'FC inventory'!$B$2:$B984,"Bashorun",'FC inventory'!$C$2:$C984,"Out")+SUMIFS('FC inventory'!K2:K984,'FC inventory'!$A$2:$A984,"<"&$A$1,'FC inventory'!$B$2:$B984,"Bashorun",'FC inventory'!$C$2:$C984,"Returned") -> 0 | ... AF3: =sumifs('FC inventory'!AH2:AH984,'FC inventory'!$A$2:$A984,"<"&$A$1,'FC inventory'!$B$2:$B984,"Bashorun",'FC inventory'!$C$2:$C984,"In")-sumifs('FC inventory'!AH2:AH984,'FC inventory'!$A$2:$A984,"<"&$A$1,'FC inventory'!$B$2:$B984,"Bashorun",'FC inventory'!$C$2:$C984,"Out")+SUMIFS('FC inventory'!AH2:AH984,'FC inventory'!$A$2:$A984,"<"&$A$1,'FC inventory'!$B$2:$B984,"Bashorun",'FC inventory'!$C$2:$C984,"Returned") -> 0
A4: In | B4: =sumifs('FC inventory'!D2:D984,'FC inventory'!$A$2:$A984,$A$1,'FC inventory'!$B$2:$B984,"Bashorun",'FC inventory'!$C$2:$C984,"In") -> 0 | C4: =sumifs('FC inventory'!E2:E984,'FC inventory'!$A$2:$A984,$A$1,'FC inventory'!$B$2:$B984,"Bashorun",'FC inventory'!$C$2:$C984,"In") -> 0 | D4: =sumifs('FC inventory'!F2:F984,'FC inventory'!$A$2:$A984,$A$1,'FC inventory'!$B$2:$B984,"Bashorun",'FC inventory'!$C$2:$C984,"In") -> 0 | E4: =sumifs('FC inventory'!G2:G984,'FC inventory'!$A$2:$A984,$A$1,'FC inventory'!$B$2:$B984,"Bashorun",'FC inventory'!$C$2:$C984,"In") -> 0 | F4: =sumifs('FC inventory'!H2:H984,'FC inventory'!$A$2:$A984,$A$1,'FC inventory'!$B$2:$B984,"Bashorun",'FC inventory'!$C$2:$C984,"In") -> 0 | G4: =sumifs('FC inventory'!I2:I984,'FC inventory'!$A$2:$A984,$A$1,'FC inventory'!$B$2:$B984,"Bashorun",'FC inventory'!$C$2:$C984,"In") -> 0 | H4: =sumifs('FC inventory'!J2:J984,'FC inventory'!$A$2:$A984,$A$1,'FC inventory'!$B$2:$B984,"Bashorun",'FC inventory'!$C$2:$C984,"In") -> 0 | I4: =sumifs('FC inventory'!K2:K984,'FC inventory'!$A$2:$A984,$A$1,'FC inventory'!$B$2:$B984,"Bashorun",'FC inventory'!$C$2:$C984,"In") -> 0 | ... AF4: =sumifs('FC inventory'!AH2:AH984,'FC inventory'!$A$2:$A984,$A$1,'FC inventory'!$B$2:$B984,"Bashorun",'FC inventory'!$C$2:$C984,"In") -> 0
A5: Out | B5: =sumifs('FC inventory'!D2:D984,'FC inventory'!$A$2:$A984,$A$1,'FC inventory'!$B$2:$B984,"Bashorun",'FC inventory'!$C$2:$C984,"Out") -> 0 | C5: =sumifs('FC inventory'!E2:E984,'FC inventory'!$A$2:$A984,$A$1,'FC inventory'!$B$2:$B984,"Bashorun",'FC inventory'!$C$2:$C984,"Out") -> 0 | D5: =sumifs('FC inventory'!F2:F984,'FC inventory'!$A$2:$A984,$A$1,'FC inventory'!$B$2:$B984,"Bashorun",'FC inventory'!$C$2:$C984,"Out") -> 0 | E5: =sumifs('FC inventory'!G2:G984,'FC inventory'!$A$2:$A984,$A$1,'FC inventory'!$B$2:$B984,"Bashorun",'FC inventory'!$C$2:$C984,"Out") -> 0 | F5: =sumifs('FC inventory'!H2:H984,'FC inventory'!$A$2:$A984,$A$1,'FC inventory'!$B$2:$B984,"Bashorun",'FC inventory'!$C$2:$C984,"Out") -> 0 | G5: =sumifs('FC inventory'!I2:I984,'FC inventory'!$A$2:$A984,$A$1,'FC inventory'!$B$2:$B984,"Bashorun",'FC inventory'!$C$2:$C984,"Out") -> 0 | H5: =sumifs('FC inventory'!J2:J984,'FC inventory'!$A$2:$A984,$A$1,'FC inventory'!$B$2:$B984,"Bashorun",'FC inventory'!$C$2:$C984,"Out") -> 0 | I5: =sumifs('FC inventory'!K2:K984,'FC inventory'!$A$2:$A984,$A$1,'FC inventory'!$B$2:$B984,"Bashorun",'FC inventory'!$C$2:$C984,"Out") -> 0 | ... AF5: =sumifs('FC inventory'!AH2:AH984,'FC inventory'!$A$2:$A984,$A$1,'FC inventory'!$B$2:$B984,"Bashorun",'FC inventory'!$C$2:$C984,"Out") -> 0
A6: Returned | B6: =SUMIFS('FC inventory'!D2:D984,'FC inventory'!$A$2:$A984,$A$1,'FC inventory'!$B$2:$B984,"Bashorun",'FC inventory'!$C$2:$C984,"Returned") -> 0 | C6: =SUMIFS('FC inventory'!E2:E984,'FC inventory'!$A$2:$A984,$A$1,'FC inventory'!$B$2:$B984,"Bashorun",'FC inventory'!$C$2:$C984,"Returned") -> 0 | D6: =SUMIFS('FC inventory'!F2:F984,'FC inventory'!$A$2:$A984,$A$1,'FC inventory'!$B$2:$B984,"Bashorun",'FC inventory'!$C$2:$C984,"Returned") -> 0 | E6: =SUMIFS('FC inventory'!G2:G984,'FC inventory'!$A$2:$A984,$A$1,'FC inventory'!$B$2:$B984,"Bashorun",'FC inventory'!$C$2:$C984,"Returned") -> 0 | F6: =SUMIFS('FC inventory'!H2:H984,'FC inventory'!$A$2:$A984,$A$1,'FC inventory'!$B$2:$B984,"Bashorun",'FC inventory'!$C$2:$C984,"Returned") -> 0 | G6: =SUMIFS('FC inventory'!I2:I984,'FC inventory'!$A$2:$A984,$A$1,'FC inventory'!$B$2:$B984,"Bashorun",'FC inventory'!$C$2:$C984,"Returned") -> 0 | H6: =SUMIFS('FC inventory'!J2:J984,'FC inventory'!$A$2:$A984,$A$1,'FC inventory'!$B$2:$B984,"Bashorun",'FC inventory'!$C$2:$C984,"Returned") -> 0 | I6: =SUMIFS('FC inventory'!K2:K984,'FC inventory'!$A$2:$A984,$A$1,'FC inventory'!$B$2:$B984,"Bashorun",'FC inventory'!$C$2:$C984,"Returned") -> 0 | ... AF6: =SUMIFS('FC inventory'!AH2:AH984,'FC inventory'!$A$2:$A984,$A$1,'FC inventory'!$B$2:$B984,"Bashorun",'FC inventory'!$C$2:$C984,"Returned") -> 0
A7: Balance | B7: =B3+B4-B5+B6 -> 0 | C7: =C3+C4-C5+C6 -> 0 | D7: =D3+D4-D5+D6 -> 1 | E7: =E3+E4-E5+E6 -> 0 | F7: =F3+F4-F5+F6 -> 0 | G7: =G3+G4-G5+G6 -> 42 | H7: =H3+H4-H5+H6 -> 0 | I7: =I3+I4-I5+I6 -> 0 | ... AF7: =AF3+AF4-AF5+AF6 -> 0

Sheet BCT
A1: =TODAY() -> 45889 | B1: Agemawo 1kg | C1: Boneless Beef 1kg | D1: Cow Hump 1kg | E1: Cow Head & Neck 1kg | F1: Goat Meat 1kg | G1: Chicken 1kg | H1: Titus 1kg (uncleaned) | I1: Titus 1kg (Cleaned) | J1: Hake 1kg (Cleaned) | K1: Hake 1kg (Uncleaned) | L1: Value Pack (Cow Tongue) | M1: Value Pack (Cow Assorted) | N1: Token Pack (Cow Minced Meat) | O1: Token Pack (Agemawo) | P1: Token pack(boneless beef) | Q1: Token Pack (Cow Tail) | R1: Token Pack (Cow Head & Neck) | S1: Token Pack (Cow Hump) | T1: Token Pack (Goat Meat) | U1: Token Pack (Chicken) | V1: Token Pack (Chicken Gizzard) | W1: Token Pack (Pomo) | X1: Token Pack (Shaki & Roundabout) | Y1: Token Pack (Cow Assorted) | Z1: Token Pack (Cow Leg) | AA1: Token Pack (Goat Assorted) | AB1: Token Pack (Titus) | AC1: Token Pack (Hake) | AD1: Token (small snail) | AE1: Token (big snail) | AF1: Token (Goat head & leg)
A2: Stock Count | B2: 0 | C2: 0 | D2: 0 | E2: 0 | F2: 0 | G2: 0 | H2: 0 | I2: 0 | J2: 0 | K2: 0 | L2: 0 | M2: 0 | N2: 0 | O2: 0 | P2: 0 | Q2: 0 | R2: 0 | S2: 0 | T2: 0 | U2: 0 | V2: 0 | W2: 0 | X2: 0 | Y2: 0 | Z2: 0 | AA2: 0 | AB2: 0 | AC2: 0 | AD2: 0 | AE2: 0 | AF2: 0
A3: Opening Stock | B3: =sumifs('FC inventory'!D2:D999,'FC inventory'!$A$2:$A999,"<"&$A$1,'FC inventory'!$B$2:$B999,"BCT",'FC inventory'!$C$2:$C999,"In")-sumifs('FC inventory'!D2:D999,'FC inventory'!$A$2:$A999,"<"&$A$1,'FC inventory'!$B$2:$B999,"BCT",'FC inventory'!$C$2:$C999,"Out")+SUMIFS('FC inventory'!D2:D999,'FC inventory'!$A$2:$A999,"<"&$A$1,'FC inventory'!$B$2:$B999,"BCT",'FC inventory'!$C$2:$C999,"Returned") -> -2 | C3: =sumifs('FC inventory'!E2:E999,'FC inventory'!$A$2:$A999,"<"&$A$1,'FC inventory'!$B$2:$B999,"BCT",'FC inventory'!$C$2:$C999,"In")-sumifs('FC inventory'!E2:E999,'FC inventory'!$A$2:$A999,"<"&$A$1,'FC inventory'!$B$2:$B999,"BCT",'FC inventory'!$C$2:$C999,"Out")+SUMIFS('FC inventory'!E2:E999,'FC inventory'!$A$2:$A999,"<"&$A$1,'FC inventory'!$B$2:$B999,"BCT",'FC inventory'!$C$2:$C999,"Returned") -> 0 | D3: =sumifs('FC inventory'!F2:F999,'FC inventory'!$A$2:$A999,"<"&$A$1,'FC inventory'!$B$2:$B999,"BCT",'FC inventory'!$C$2:$C999,"In")-sumifs('FC inventory'!F2:F999,'FC inventory'!$A$2:$A999,"<"&$A$1,'FC inventory'!$B$2:$B999,"BCT",'FC inventory'!$C$2:$C999,"Out")+SUMIFS('FC inventory'!F2:F999,'FC inventory'!$A$2:$A999,"<"&$A$1,'FC inventory'!$B$2:$B999,"BCT",'FC inventory'!$C$2:$C999,"Returned") -> 0 | E3: =sumifs('FC inventory'!G2:G999,'FC inventory'!$A$2:$A999,"<"&$A$1,'FC inventory'!$B$2:$B999,"BCT",'FC inventory'!$C$2:$C999,"In")-sumifs('FC inventory'!G2:G999,'FC inventory'!$A$2:$A999,"<"&$A$1,'FC inventory'!$B$2:$B999,"BCT",'FC inventory'!$C$2:$C999,"Out")+SUMIFS('FC inventory'!G2:G999,'FC inventory'!$A$2:$A999,"<"&$A$1,'FC inventory'!$B$2:$B999,"BCT",'FC inventory'!$C$2:$C999,"Returned") -> -1 | F3: =sumifs('FC inventory'!H2:H999,'FC inventory'!$A$2:$A999,"<"&$A$1,'FC inventory'!$B$2:$B999,"BCT",'FC inventory'!$C$2:$C999,"In")-sumifs('FC inventory'!H2:H999,'FC inventory'!$A$2:$A999,"<"&$A$1,'FC inventory'!$B$2:$B999,"BCT",'FC inventory'!$C$2:$C999,"Out")+SUMIFS('FC inventory'!H2:H999,'FC inventory'!$A$2:$A999,"<"&$A$1,'FC inventory'!$B$2:$B999,"BCT",'FC inventory'!$C$2:$C999,"Returned") -> 0 | G3: =sumifs('FC inventory'!I2:I999,'FC inventory'!$A$2:$A999,"<"&$A$1,'FC inventory'!$B$2:$B999,"BCT",'FC inventory'!$C$2:$C999,"In")-sumifs('FC inventory'!I2:I999,'FC inventory'!$A$2:$A999,"<"&$A$1,'FC inventory'!$B$2:$B999,"BCT",'FC inventory'!$C$2:$C999,"Out")+SUMIFS('FC inventory'!I2:I999,'FC inventory'!$A$2:$A999,"<"&$A$1,'FC inventory'!$B$2:$B999,"BCT",'FC inventory'!$C$2:$C999,"Returned") -> 35 | H3: =sumifs('FC inventory'!J2:J999,'FC inventory'!$A$2:$A999,"<"&$A$1,'FC inventory'!$B$2:$B999,"BCT",'FC inventory'!$C$2:$C999,"In")-sumifs('FC inventory'!J2:J999,'FC inventory'!$A$2:$A999,"<"&$A$1,'FC inventory'!$B$2:$B999,"BCT",'FC inventory'!$C$2:$C999,"Out")+SUMIFS('FC inventory'!J2:J999,'FC inventory'!$A$2:$A999,"<"&$A$1,'FC inventory'!$B$2:$B999,"BCT",'FC inventory'!$C$2:$C999,"Returned") -> 0 | I3: =sumifs('FC inventory'!K2:K999,'FC inventory'!$A$2:$A999,"<"&$A$1,'FC inventory'!$B$2:$B999,"BCT",'FC inventory'!$C$2:$C999,"In")-sumifs('FC inventory'!K2:K999,'FC inventory'!$A$2:$A999,"<"&$A$1,'FC inventory'!$B$2:$B999,"BCT",'FC inventory'!$C$2:$C999,"Out")+SUMIFS('FC inventory'!K2:K999,'FC inventory'!$A$2:$A999,"<"&$A$1,'FC inventory'!$B$2:$B999,"BCT",'FC inventory'!$C$2:$C999,"Returned") -> 0 | ... AF3: =sumifs('FC inventory'!AH2:AH999,'FC inventory'!$A$2:$A999,"<"&$A$1,'FC inventory'!$B$2:$B999,"BCT",'FC inventory'!$C$2:$C999,"In")-sumifs('FC inventory'!AH2:AH999,'FC inventory'!$A$2:$A999,"<"&$A$1,'FC inventory'!$B$2:$B999,"BCT",'FC inventory'!$C$2:$C999,"Out")+SUMIFS('FC inventory'!AH2:AH999,'FC inventory'!$A$2:$A999,"<"&$A$1,'FC inventory'!$B$2:$B999,"BCT",'FC inventory'!$C$2:$C999,"Returned") -> 0
A4: In | B4: =sumifs('FC inventory'!D2:D999,'FC inventory'!$A$2:$A999,$A$1,'FC inventory'!$B$2:$B999,"BCT",'FC inventory'!$C$2:$C999,"In") -> 0 | C4: =sumifs('FC inventory'!E2:E999,'FC inventory'!$A$2:$A999,$A$1,'FC inventory'!$B$2:$B999,"BCT",'FC inventory'!$C$2:$C999,"In") -> 0 | D4: =sumifs('FC inventory'!F2:F999,'FC inventory'!$A$2:$A999,$A$1,'FC inventory'!$B$2:$B999,"BCT",'FC inventory'!$C$2:$C999,"In") -> 0 | E4: =sumifs('FC inventory'!G2:G999,'FC inventory'!$A$2:$A999,$A$1,'FC inventory'!$B$2:$B999,"BCT",'FC inventory'!$C$2:$C999,"In") -> 0 | F4: =sumifs('FC inventory'!H2:H999,'FC inventory'!$A$2:$A999,$A$1,'FC inventory'!$B$2:$B999,"BCT",'FC inventory'!$C$2:$C999,"In") -> 0 | G4: =sumifs('FC inventory'!I2:I999,'FC inventory'!$A$2:$A999,$A$1,'FC inventory'!$B$2:$B999,"BCT",'FC inventory'!$C$2:$C999,"In") -> 0 | H4: =sumifs('FC inventory'!J2:J999,'FC inventory'!$A$2:$A999,$A$1,'FC inventory'!$B$2:$B999,"BCT",'FC inventory'!$C$2:$C999,"In") -> 0 | I4: =sumifs('FC inventory'!K2:K999,'FC inventory'!$A$2:$A999,$A$1,'FC inventory'!$B$2:$B999,"BCT",'FC inventory'!$C$2:$C999,"In") -> 0 | ... AF4: =sumifs('FC inventory'!AH2:AH999,'FC inventory'!$A$2:$A999,$A$1,'FC inventory'!$B$2:$B999,"BCT",'FC inventory'!$C$2:$C999,"In") -> 0
A5: Out | B5: =sumifs('FC inventory'!D2:D999,'FC inventory'!$A$2:$A999,$A$1,'FC inventory'!$B$2:$B999,"BCT",'FC inventory'!$C$2:$C999,"Out") -> 0 | C5: =sumifs('FC inventory'!E2:E999,'FC inventory'!$A$2:$A999,$A$1,'FC inventory'!$B$2:$B999,"BCT",'FC inventory'!$C$2:$C999,"Out") -> 0 | D5: =sumifs('FC inventory'!F2:F999,'FC inventory'!$A$2:$A999,$A$1,'FC inventory'!$B$2:$B999,"BCT",'FC inventory'!$C$2:$C999,"Out") -> 0 | E5: =sumifs('FC inventory'!G2:G999,'FC inventory'!$A$2:$A999,$A$1,'FC inventory'!$B$2:$B999,"BCT",'FC inventory'!$C$2:$C999,"Out") -> 0 | F5: =sumifs('FC inventory'!H2:H999,'FC inventory'!$A$2:$A999,$A$1,'FC inventory'!$B$2:$B999,"BCT",'FC inventory'!$C$2:$C999,"Out") -> 0 | G5: =sumifs('FC inventory'!I2:I999,'FC inventory'!$A$2:$A999,$A$1,'FC inventory'!$B$2:$B999,"BCT",'FC inventory'!$C$2:$C999,"Out") -> 0 | H5: =sumifs('FC inventory'!J2:J999,'FC inventory'!$A$2:$A999,$A$1,'FC inventory'!$B$2:$B999,"BCT",'FC inventory'!$C$2:$C999,"Out") -> 0 | I5: =sumifs('FC inventory'!K2:K999,'FC inventory'!$A$2:$A999,$A$1,'FC inventory'!$B$2:$B999,"BCT",'FC inventory'!$C$2:$C999,"Out") -> 0 | ... AF5: =sumifs('FC inventory'!AH2:AH999,'FC inventory'!$A$2:$A999,$A$1,'FC inventory'!$B$2:$B999,"BCT",'FC inventory'!$C$2:$C999,"Out") -> 0
A6: Returned | B6: =SUMIFS('FC inventory'!D2:D999,'FC inventory'!$A$2:$A999,$A$1,'FC inventory'!$B$2:$B999,"BCT",'FC inventory'!$C$2:$C999,"Returned") -> 0 | C6: =SUMIFS('FC inventory'!E2:E999,'FC inventory'!$A$2:$A999,$A$1,'FC inventory'!$B$2:$B999,"BCT",'FC inventory'!$C$2:$C999,"Returned") -> 0 | D6: =SUMIFS('FC inventory'!F2:F999,'FC inventory'!$A$2:$A999,$A$1,'FC inventory'!$B$2:$B999,"BCT",'FC inventory'!$C$2:$C999,"Returned") -> 0 | E6: =SUMIFS('FC inventory'!G2:G999,'FC inventory'!$A$2:$A999,$A$1,'FC inventory'!$B$2:$B999,"BCT",'FC inventory'!$C$2:$C999,"Returned") -> 0 | F6: =SUMIFS('FC inventory'!H2:H999,'FC inventory'!$A$2:$A999,$A$1,'FC inventory'!$B$2:$B999,"BCT",'FC inventory'!$C$2:$C999,"Returned") -> 0 | G6: =SUMIFS('FC inventory'!I2:I999,'FC inventory'!$A$2:$A999,$A$1,'FC inventory'!$B$2:$B999,"BCT",'FC inventory'!$C$2:$C999,"Returned") -> 0 | H6: =SUMIFS('FC inventory'!J2:J999,'FC inventory'!$A$2:$A999,$A$1,'FC inventory'!$B$2:$B999,"BCT",'FC inventory'!$C$2:$C999,"Returned") -> 0 | I6: =SUMIFS('FC inventory'!K2:K999,'FC inventory'!$A$2:$A999,$A$1,'FC inventory'!$B$2:$B999,"BCT",'FC inventory'!$C$2:$C999,"Returned") -> 0 | ... AF6: =SUMIFS('FC inventory'!AH2:AH999,'FC inventory'!$A$2:$A999,$A$1,'FC inventory'!$B$2:$B999,"BCT",'FC inventory'!$C$2:$C999,"Returned") -> 0
A7: Balance | B7: =B3+B4-B5+B6 -> -2 | C7: =C3+C4-C5+C6 -> 0 | D7: =D3+D4-D5+D6 -> 0 | E7: =E3+E4-E5+E6 -> -1 | F7: =F3+F4-F5+F6 -> 0 | G7: =G3+G4-G5+G6 -> 35 | H7: =H3+H4-H5+H6 -> 0 | I7: =I3+I4-I5+I6 -> 0 | ... AF7: =AF3+AF4-AF5+AF6 -> 0

Sheet Eleyele
A1: =TODAY() -> 45889 | B1: Agemawo 1kg | C1: Boneless Beef 1kg | D1: Cow Hump 1kg | E1: Cow Head & Neck 1kg | F1: Goat Meat 1kg | G1: Chicken 1kg | H1: Titus 1kg (uncleaned) | I1: Titus 1kg (Cleaned) | J1: Hake 1kg (Cleaned) | K1: Hake 1kg (Uncleaned) | L1: Value Pack (Cow Tongue) | M1: Value Pack (Cow Assorted) | N1: Token Pack (Cow Minced Meat) | O1: Token Pack (Agemawo) | P1: Token pack(boneless beef) | Q1: Token Pack (Cow Tail) | R1: Token Pack (Cow Head & Neck) | S1: Token Pack (Cow Hump) | T1: Token Pack (Goat Meat) | U1: Token Pack (Chicken) | V1: Token Pack (Chicken Gizzard) | W1: Token Pack (Pomo) | X1: Token Pack (Shaki & Roundabout) | Y1: Token Pack (Cow Assorted) | Z1: Token Pack (Cow Leg) | AA1: Token Pack (Goat Assorted) | AB1: Token Pack (Titus) | AC1: Token Pack (Hake) | AD1: Token (small snail) | AE1: Token (big snail) | AF1: Token (Goat head & leg)
A2: Stock Count | B2: 0 | C2: 0 | D2: 0 | E2: 0 | F2: 0 | G2: 0 | H2: 0 | I2: 0 | J2: 0 | K2: 0 | L2: 0 | M2: 0 | N2: 0 | O2: 0 | P2: 0 | Q2: 0 | R2: 0 | S2: 0 | T2: 0 | U2: 0 | V2: 0 | W2: 0 | X2: 0 | Y2: 0 | Z2: 0 | AA2: 0 | AB2: 0 | AC2: 0 | AD2: 0 | AE2: 0 | AF2: 0
A3: Opening Stock | B3: =sumifs('FC inventory'!D2:D999,'FC inventory'!$A$2:$A999,"<"&$A$1,'FC inventory'!$B$2:$B999,"Eleyele",'FC inventory'!$C$2:$C999,"In")-sumifs('FC inventory'!D2:D999,'FC inventory'!$A$2:$A999,"<"&$A$1,'FC inventory'!$B$2:$B999,"Eleyele",'FC inventory'!$C$2:$C999,"Out")+SUMIFS('FC inventory'!D2:D999,'FC inventory'!$A$2:$A999,"<"&$A$1,'FC inventory'!$B$2:$B999,"Eleyele",'FC inventory'!$C$2:$C999,"Returned") -> 0 | C3: =sumifs('FC inventory'!E2:E999,'FC inventory'!$A$2:$A999,"<"&$A$1,'FC inventory'!$B$2:$B999,"Eleyele",'FC inventory'!$C$2:$C999,"In")-sumifs('FC inventory'!E2:E999,'FC inventory'!$A$2:$A999,"<"&$A$1,'FC inventory'!$B$2:$B999,"Eleyele",'FC inventory'!$C$2:$C999,"Out")+SUMIFS('FC inventory'!E2:E999,'FC inventory'!$A$2:$A999,"<"&$A$1,'FC inventory'!$B$2:$B999,"Eleyele",'FC inventory'!$C$2:$C999,"Returned") -> 0 | D3: =sumifs('FC inventory'!F2:F999,'FC inventory'!$A$2:$A999,"<"&$A$1,'FC inventory'!$B$2:$B999,"Eleyele",'FC inventory'!$C$2:$C999,"In")-sumifs('FC inventory'!F2:F999,'FC inventory'!$A$2:$A999,"<"&$A$1,'FC inventory'!$B$2:$B999,"Eleyele",'FC inventory'!$C$2:$C999,"Out")+SUMIFS('FC inventory'!F2:F999,'FC inventory'!$A$2:$A999,"<"&$A$1,'FC inventory'!$B$2:$B999,"Eleyele",'FC inventory'!$C$2:$C999,"Returned") -> 0 | E3: =sumifs('FC inventory'!G2:G999,'FC inventory'!$A$2:$A999,"<"&$A$1,'FC inventory'!$B$2:$B999,"Eleyele",'FC inventory'!$C$2:$C999,"In")-sumifs('FC inventory'!G2:G999,'FC inventory'!$A$2:$A999,"<"&$A$1,'FC inventory'!$B$2:$B999,"Eleyele",'FC inventory'!$C$2:$C999,"Out")+SUMIFS('FC inventory'!G2:G999,'FC inventory'!$A$2:$A999,"<"&$A$1,'FC inventory'!$B$2:$B999,"Eleyele",'FC inventory'!$C$2:$C999,"Returned") -> 0 | F3: =sumifs('FC inventory'!H2:H999,'FC inventory'!$A$2:$A999,"<"&$A$1,'FC inventory'!$B$2:$B999,"Eleyele",'FC inventory'!$C$2:$C999,"In")-sumifs('FC inventory'!H2:H999,'FC inventory'!$A$2:$A999,"<"&$A$1,'FC inventory'!$B$2:$B999,"Eleyele",'FC inventory'!$C$2:$C999,"Out")+SUMIFS('FC inventory'!H2:H999,'FC inventory'!$A$2:$A999,"<"&$A$1,'FC inventory'!$B$2:$B999,"Eleyele",'FC inventory'!$C$2:$C999,"Returned") -> 0 | G3: =sumifs('FC inventory'!I2:I999,'FC inventory'!$A$2:$A999,"<"&$A$1,'FC inventory'!$B$2:$B999,"Eleyele",'FC inventory'!$C$2:$C999,"In")-sumifs('FC inventory'!I2:I999,'FC inventory'!$A$2:$A999,"<"&$A$1,'FC inventory'!$B$2:$B999,"Eleyele",'FC inventory'!$C$2:$C999,"Out")+SUMIFS('FC inventory'!I2:I999,'FC inventory'!$A$2:$A999,"<"&$A$1,'FC inventory'!$B$2:$B999,"Eleyele",'FC inventory'!$C$2:$C999,"Returned") -> 0 | H3: =sumifs('FC inventory'!J2:J999,'FC inventory'!$A$2:$A999,"<"&$A$1,'FC inventory'!$B$2:$B999,"Eleyele",'FC inventory'!$C$2:$C999,"In")-sumifs('FC inventory'!J2:J999,'FC inventory'!$A$2:$A999,"<"&$A$1,'FC inventory'!$B$2:$B999,"Eleyele",'FC inventory'!$C$2:$C999,"Out")+SUMIFS('FC inventory'!J2:J999,'FC inventory'!$A$2:$A999,"<"&$A$1,'FC inventory'!$B$2:$B999,"Eleyele",'FC inventory'!$C$2:$C999,"Returned") -> 0 | I3: =sumifs('FC inventory'!K2:K999,'FC inventory'!$A$2:$A999,"<"&$A$1,'FC inventory'!$B$2:$B999,"Eleyele",'FC inventory'!$C$2:$C999,"In")-sumifs('FC inventory'!K2:K999,'FC inventory'!$A$2:$A999,"<"&$A$1,'FC inventory'!$B$2:$B999,"Eleyele",'FC inventory'!$C$2:$C999,"Out")+SUMIFS('FC inventory'!K2:K999,'FC inventory'!$A$2:$A999,"<"&$A$1,'FC inventory'!$B$2:$B999,"Eleyele",'FC inventory'!$C$2:$C999,"Returned") -> 0 | ... AF3: =sumifs('FC inventory'!AH2:AH999,'FC inventory'!$A$2:$A999,"<"&$A$1,'FC inventory'!$B$2:$B999,"Eleyele",'FC inventory'!$C$2:$C999,"In")-sumifs('FC inventory'!AH2:AH999,'FC inventory'!$A$2:$A999,"<"&$A$1,'FC inventory'!$B$2:$B999,"Eleyele",'FC inventory'!$C$2:$C999,"Out")+SUMIFS('FC inventory'!AH2:AH999,'FC inventory'!$A$2:$A999,"<"&$A$1,'FC inventory'!$B$2:$B999,"Eleyele",'FC inventory'!$C$2:$C999,"Returned") -> 0
A4: In | B4: =sumifs('FC inventory'!D2:D999,'FC inventory'!$A$2:$A999,$A$1,'FC inventory'!$B$2:$B999,"Eleyele",'FC inventory'!$C$2:$C999,"In") -> 0 | C4: =sumifs('FC inventory'!E2:E999,'FC inventory'!$A$2:$A999,$A$1,'FC inventory'!$B$2:$B999,"Eleyele",'FC inventory'!$C$2:$C999,"In") -> 0 | D4: =sumifs('FC inventory'!F2:F999,'FC inventory'!$A$2:$A999,$A$1,'FC inventory'!$B$2:$B999,"Eleyele",'FC inventory'!$C$2:$C999,"In") -> 0 | E4: =sumifs('FC inventory'!G2:G999,'FC inventory'!$A$2:$A999,$A$1,'FC inventory'!$B$2:$B999,"Eleyele",'FC inventory'!$C$2:$C999,"In") -> 0 | F4: =sumifs('FC inventory'!H2:H999,'FC inventory'!$A$2:$A999,$A$1,'FC inventory'!$B$2:$B999,"Eleyele",'FC inventory'!$C$2:$C999,"In") -> 0 | G4: =sumifs('FC inventory'!I2:I999,'FC inventory'!$A$2:$A999,$A$1,'FC inventory'!$B$2:$B999,"Eleyele",'FC inventory'!$C$2:$C999,"In") -> 0 | H4: =sumifs('FC inventory'!J2:J999,'FC inventory'!$A$2:$A999,$A$1,'FC inventory'!$B$2:$B999,"Eleyele",'FC inventory'!$C$2:$C999,"In") -> 0 | I4: =sumifs('FC inventory'!K2:K999,'FC inventory'!$A$2:$A999,$A$1,'FC inventory'!$B$2:$B999,"Eleyele",'FC inventory'!$C$2:$C999,"In") -> 0 | ... AF4: =sumifs('FC inventory'!AH2:AH999,'FC inventory'!$A$2:$A999,$A$1,'FC inventory'!$B$2:$B999,"Eleyele",'FC inventory'!$C$2:$C999,"In") -> 0
A5: Out | B5: =sumifs('FC inventory'!D2:D999,'FC inventory'!$A$2:$A999,$A$1,'FC inventory'!$B$2:$B999,"Eleyele",'FC inventory'!$C$2:$C999,"Out") -> 0 | C5: =sumifs('FC inventory'!E2:E999,'FC inventory'!$A$2:$A999,$A$1,'FC inventory'!$B$2:$B999,"Eleyele",'FC inventory'!$C$2:$C999,"Out") -> 0 | D5: =sumifs('FC inventory'!F2:F999,'FC inventory'!$A$2:$A999,$A$1,'FC inventory'!$B$2:$B999,"Eleyele",'FC inventory'!$C$2:$C999,"Out") -> 0 | E5: =sumifs('FC inventory'!G2:G999,'FC inventory'!$A$2:$A999,$A$1,'FC inventory'!$B$2:$B999,"Eleyele",'FC inventory'!$C$2:$C999,"Out") -> 0 | F5: =sumifs('FC inventory'!H2:H999,'FC inventory'!$A$2:$A999,$A$1,'FC inventory'!$B$2:$B999,"Eleyele",'FC inventory'!$C$2:$C999,"Out") -> 0 | G5: =sumifs('FC inventory'!I2:I999,'FC inventory'!$A$2:$A999,$A$1,'FC inventory'!$B$2:$B999,"Eleyele",'FC inventory'!$C$2:$C999,"Out") -> 0 | H5: =sumifs('FC inventory'!J2:J999,'FC inventory'!$A$2:$A999,$A$1,'FC inventory'!$B$2:$B999,"Eleyele",'FC inventory'!$C$2:$C999,"Out") -> 0 | I5: =sumifs('FC inventory'!K2:K999,'FC inventory'!$A$2:$A999,$A$1,'FC inventory'!$B$2:$B999,"Eleyele",'FC inventory'!$C$2:$C999,"Out") -> 0 | ... AF5: =sumifs('FC inventory'!AH2:AH999,'FC inventory'!$A$2:$A999,$A$1,'FC inventory'!$B$2:$B999,"Eleyele",'FC inventory'!$C$2:$C999,"Out") -> 0
A6: Returned | B6: =SUMIFS('FC inventory'!D2:D999,'FC inventory'!$A$2:$A999,$A$1,'FC inventory'!$B$2:$B999,"Eleyele",'FC inventory'!$C$2:$C999,"Returned") -> 0 | C6: =SUMIFS('FC inventory'!E2:E999,'FC inventory'!$A$2:$A999,$A$1,'FC inventory'!$B$2:$B999,"Eleyele",'FC inventory'!$C$2:$C999,"Returned") -> 0 | D6: =SUMIFS('FC inventory'!F2:F999,'FC inventory'!$A$2:$A999,$A$1,'FC inventory'!$B$2:$B999,"Eleyele",'FC inventory'!$C$2:$C999,"Returned") -> 0 | E6: =SUMIFS('FC inventory'!G2:G999,'FC inventory'!$A$2:$A999,$A$1,'FC inventory'!$B$2:$B999,"Eleyele",'FC inventory'!$C$2:$C999,"Returned") -> 0 | F6: =SUMIFS('FC inventory'!H2:H999,'FC inventory'!$A$2:$A999,$A$1,'FC inventory'!$B$2:$B999,"Eleyele",'FC inventory'!$C$2:$C999,"Returned") -> 0 | G6: =SUMIFS('FC inventory'!I2:I999,'FC inventory'!$A$2:$A999,$A$1,'FC inventory'!$B$2:$B999,"Eleyele",'FC inventory'!$C$2:$C999,"Returned") -> 0 | H6: =SUMIFS('FC inventory'!J2:J999,'FC inventory'!$A$2:$A999,$A$1,'FC inventory'!$B$2:$B999,"Eleyele",'FC inventory'!$C$2:$C999,"Returned") -> 0 | I6: =SUMIFS('FC inventory'!K2:K999,'FC inventory'!$A$2:$A999,$A$1,'FC inventory'!$B$2:$B999,"Eleyele",'FC inventory'!$C$2:$C999,"Returned") -> 0 | ... AF6: =SUMIFS('FC inventory'!AH2:AH999,'FC inventory'!$A$2:$A999,$A$1,'FC inventory'!$B$2:$B999,"Eleyele",'FC inventory'!$C$2:$C999,"Returned") -> 0
A7: Balance | B7: =B3+B4-B5+B6 -> 0 | C7: =C3+C4-C5+C6 -> 0 | D7: =D3+D4-D5+D6 -> 0 | E7: =E3+E4-E5+E6 -> 0 | F7: =F3+F4-F5+F6 -> 0 | G7: =G3+G4-G5+G6 -> 0 | H7: =H3+H4-H5+H6 -> 0 | I7: =I3+I4-I5+I6 -> 0 | ... AF7: =AF3+AF4-AF5+AF6 -> 0

Sheet Felele
A1: =TODAY() -> 45889 | B1: Agemawo 1kg | C1: Boneless Beef 1kg | D1: Cow Hump 1kg | E1: Cow Head & Neck 1kg | F1: Goat Meat 1kg | G1: Chicken 1kg | H1: Titus 1kg (uncleaned) | I1: Titus 1kg (Cleaned) | J1: Hake 1kg (Cleaned) | K1: Hake 1kg (Uncleaned) | L1: Value Pack (Cow Tongue) | M1: Value Pack (Cow Assorted) | N1: Token Pack (Cow Minced Meat) | O1: Token Pack (Agemawo) | P1: Token pack(boneless beef) | Q1: Token Pack (Cow Tail) | R1: Token Pack (Cow Head & Neck) | S1: Token Pack (Cow Hump) | T1: Token Pack (Goat Meat) | U1: Token Pack (Chicken) | V1: Token Pack (Chicken Gizzard) | W1: Token Pack (Pomo) | X1: Token Pack (Shaki & Roundabout) | Y1: Token Pack (Cow Assorted) | Z1: Token Pack (Cow Leg) | AA1: Token Pack (Goat Assorted) | AB1: Token Pack (Titus) | AC1: Token Pack (Hake) | AD1: Token (small snail) | AE1: Token (big snail) | AF1: Token (Goat head & leg)
A2: Stock Count | B2: 0 | C2: 0 | D2: 0 | E2: 0 | F2: 0 | G2: 0 | H2: 0 | I2: 0 | J2: 0 | K2: 0 | L2: 0 | M2: 0 | N2: 0 | O2: 0 | P2: 0 | Q2: 0 | R2: 0 | S2: 0 | T2: 0 | U2: 0 | V2: 0 | W2: 0 | X2: 0 | Y2: 0 | Z2: 0 | AA2: 0 | AB2: 0 | AC2: 0 | AD2: 0 | AE2: 0 | AF2: 0
A3: Opening Stock | B3: =sumifs('FC inventory'!D2:D999,'FC inventory'!$A$2:$A999,"<"&$A$1,'FC inventory'!$B$2:$B999,"Felele",'FC inventory'!$C$2:$C999,"In")-sumifs('FC inventory'!D2:D999,'FC inventory'!$A$2:$A999,"<"&$A$1,'FC inventory'!$B$2:$B999,"Felele",'FC inventory'!$C$2:$C999,"Out")+SUMIFS('FC inventory'!D2:D999,'FC inventory'!$A$2:$A999,"<"&$A$1,'FC inventory'!$B$2:$B999,"Felele",'FC inventory'!$C$2:$C999,"Returned") -> 0 | C3: =sumifs('FC inventory'!E2:E999,'FC inventory'!$A$2:$A999,"<"&$A$1,'FC inventory'!$B$2:$B999,"Felele",'FC inventory'!$C$2:$C999,"In")-sumifs('FC inventory'!E2:E999,'FC inventory'!$A$2:$A999,"<"&$A$1,'FC inventory'!$B$2:$B999,"Felele",'FC inventory'!$C$2:$C999,"Out")+SUMIFS('FC inventory'!E2:E999,'FC inventory'!$A$2:$A999,"<"&$A$1,'FC inventory'!$B$2:$B999,"Felele",'FC inventory'!$C$2:$C999,"Returned") -> 0 | D3: =sumifs('FC inventory'!F2:F999,'FC inventory'!$A$2:$A999,"<"&$A$1,'FC inventory'!$B$2:$B999,"Felele",'FC inventory'!$C$2:$C999,"In")-sumifs('FC inventory'!F2:F999,'FC inventory'!$A$2:$A999,"<"&$A$1,'FC inventory'!$B$2:$B999,"Felele",'FC inventory'!$C$2:$C999,"Out")+SUMIFS('FC inventory'!F2:F999,'FC inventory'!$A$2:$A999,"<"&$A$1,'FC inventory'!$B$2:$B999,"Felele",'FC inventory'!$C$2:$C999,"Returned") -> 0 | E3: =sumifs('FC inventory'!G2:G999,'FC inventory'!$A$2:$A999,"<"&$A$1,'FC inventory'!$B$2:$B999,"Felele",'FC inventory'!$C$2:$C999,"In")-sumifs('FC inventory'!G2:G999,'FC inventory'!$A$2:$A999,"<"&$A$1,'FC inventory'!$B$2:$B999,"Felele",'FC inventory'!$C$2:$C999,"Out")+SUMIFS('FC inventory'!G2:G999,'FC inventory'!$A$2:$A999,"<"&$A$1,'FC inventory'!$B$2:$B999,"Felele",'FC inventory'!$C$2:$C999,"Returned") -> 0 | F3: =sumifs('FC inventory'!H2:H999,'FC inventory'!$A$2:$A999,"<"&$A$1,'FC inventory'!$B$2:$B999,"Felele",'FC inventory'!$C$2:$C999,"In")-sumifs('FC inventory'!H2:H999,'FC inventory'!$A$2:$A999,"<"&$A$1,'FC inventory'!$B$2:$B999,"Felele",'FC inventory'!$C$2:$C999,"Out")+SUMIFS('FC inventory'!H2:H999,'FC inventory'!$A$2:$A999,"<"&$A$1,'FC inventory'!$B$2:$B999,"Felele",'FC inventory'!$C$2:$C999,"Returned") -> 0 | G3: =sumifs('FC inventory'!I2:I999,'FC inventory'!$A$2:$A999,"<"&$A$1,'FC inventory'!$B$2:$B999,"Felele",'FC inventory'!$C$2:$C999,"In")-sumifs('FC inventory'!I2:I999,'FC inventory'!$A$2:$A999,"<"&$A$1,'FC inventory'!$B$2:$B999,"Felele",'FC inventory'!$C$2:$C999,"Out")+SUMIFS('FC inventory'!I2:I999,'FC inventory'!$A$2:$A999,"<"&$A$1,'FC inventory'!$B$2:$B999,"Felele",'FC inventory'!$C$2:$C999,"Returned") -> 26 | H3: =sumifs('FC inventory'!J2:J999,'FC inventory'!$A$2:$A999,"<"&$A$1,'FC inventory'!$B$2:$B999,"Felele",'FC inventory'!$C$2:$C999,"In")-sumifs('FC inventory'!J2:J999,'FC inventory'!$A$2:$A999,"<"&$A$1,'FC inventory'!$B$2:$B999,"Felele",'FC inventory'!$C$2:$C999,"Out")+SUMIFS('FC inventory'!J2:J999,'FC inventory'!$A$2:$A999,"<"&$A$1,'FC inventory'!$B$2:$B999,"Felele",'FC inventory'!$C$2:$C999,"Returned") -> 0 | I3: =sumifs('FC inventory'!K2:K999,'FC inventory'!$A$2:$A999,"<"&$A$1,'FC inventory'!$B$2:$B999,"Felele",'FC inventory'!$C$2:$C999,"In")-sumifs('FC inventory'!K2:K999,'FC inventory'!$A$2:$A999,"<"&$A$1,'FC inventory'!$B$2:$B999,"Felele",'FC inventory'!$C$2:$C999,"Out")+SUMIFS('FC inventory'!K2:K999,'FC inventory'!$A$2:$A999,"<"&$A$1,'FC inventory'!$B$2:$B999,"Felele",'FC inventory'!$C$2:$C999,"Returned") -> 0 | ... AF3: =sumifs('FC inventory'!AH2:AH999,'FC inventory'!$A$2:$A999,"<"&$A$1,'FC inventory'!$B$2:$B999,"Felele",'FC inventory'!$C$2:$C999,"In")-sumifs('FC inventory'!AH2:AH999,'FC inventory'!$A$2:$A999,"<"&$A$1,'FC inventory'!$B$2:$B999,"Felele",'FC inventory'!$C$2:$C999,"Out")+SUMIFS('FC inventory'!AH2:AH999,'FC inventory'!$A$2:$A999,"<"&$A$1,'FC inventory'!$B$2:$B999,"Felele",'FC inventory'!$C$2:$C999,"Returned") -> 0
A4: In | B4: =sumifs('FC inventory'!D2:D999,'FC inventory'!$A$2:$A999,$A$1,'FC inventory'!$B$2:$B999,"Felele",'FC inventory'!$C$2:$C999,"In") -> 0 | C4: =sumifs('FC inventory'!E2:E999,'FC inventory'!$A$2:$A999,$A$1,'FC inventory'!$B$2:$B999,"Felele",'FC inventory'!$C$2:$C999,"In") -> 0 | D4: =sumifs('FC inventory'!F2:F999,'FC inventory'!$A$2:$A999,$A$1,'FC inventory'!$B$2:$B999,"Felele",'FC inventory'!$C$2:$C999,"In") -> 0 | E4: =sumifs('FC inventory'!G2:G999,'FC inventory'!$A$2:$A999,$A$1,'FC inventory'!$B$2:$B999,"Felele",'FC inventory'!$C$2:$C999,"In") -> 0 | F4: =sumifs('FC inventory'!H2:H999,'FC inventory'!$A$2:$A999,$A$1,'FC inventory'!$B$2:$B999,"Felele",'FC inventory'!$C$2:$C999,"In") -> 0 | G4: =sumifs('FC inventory'!I2:I999,'FC inventory'!$A$2:$A999,$A$1,'FC inventory'!$B$2:$B999,"Felele",'FC inventory'!$C$2:$C999,"In") -> 0 | H4: =sumifs('FC inventory'!J2:J999,'FC inventory'!$A$2:$A999,$A$1,'FC inventory'!$B$2:$B999,"Felele",'FC inventory'!$C$2:$C999,"In") -> 0 | I4: =sumifs('FC inventory'!K2:K999,'FC inventory'!$A$2:$A999,$A$1,'FC inventory'!$B$2:$B999,"Felele",'FC inventory'!$C$2:$C999,"In") -> 0 | ... AF4: =sumifs('FC inventory'!AH2:AH999,'FC inventory'!$A$2:$A999,$A$1,'FC inventory'!$B$2:$B999,"Felele",'FC inventory'!$C$2:$C999,"In") -> 0
A5: Out | B5: =sumifs('FC inventory'!D2:D999,'FC inventory'!$A$2:$A999,$A$1,'FC inventory'!$B$2:$B999,"Felele",'FC inventory'!$C$2:$C999,"Out") -> 0 | C5: =sumifs('FC inventory'!E2:E999,'FC inventory'!$A$2:$A999,$A$1,'FC inventory'!$B$2:$B999,"Felele",'FC inventory'!$C$2:$C999,"Out") -> 0 | D5: =sumifs('FC inventory'!F2:F999,'FC inventory'!$A$2:$A999,$A$1,'FC inventory'!$B$2:$B999,"Felele",'FC inventory'!$C$2:$C999,"Out") -> 0 | E5: =sumifs('FC inventory'!G2:G999,'FC inventory'!$A$2:$A999,$A$1,'FC inventory'!$B$2:$B999,"Felele",'FC inventory'!$C$2:$C999,"Out") -> 0 | F5: =sumifs('FC inventory'!H2:H999,'FC inventory'!$A$2:$A999,$A$1,'FC inventory'!$B$2:$B999,"Felele",'FC inventory'!$C$2:$C999,"Out") -> 0 | G5: =sumifs('FC inventory'!I2:I999,'FC inventory'!$A$2:$A999,$A$1,'FC inventory'!$B$2:$B999,"Felele",'FC inventory'!$C$2:$C999,"Out") -> 0 | H5: =sumifs('FC inventory'!J2:J999,'FC inventory'!$A$2:$A999,$A$1,'FC inventory'!$B$2:$B999,"Felele",'FC inventory'!$C$2:$C999,"Out") -> 0 | I5: =sumifs('FC inventory'!K2:K999,'FC inventory'!$A$2:$A999,$A$1,'FC inventory'!$B$2:$B999,"Felele",'FC inventory'!$C$2:$C999,"Out") -> 0 | ... AF5: =sumifs('FC inventory'!AH2:AH999,'FC inventory'!$A$2:$A999,$A$1,'FC inventory'!$B$2:$B999,"Felele",'FC inventory'!$C$2:$C999,"Out") -> 0
A6: Returned | B6: =SUMIFS('FC inventory'!D2:D999,'FC inventory'!$A$2:$A999,$A$1,'FC inventory'!$B$2:$B999,"Felele",'FC inventory'!$C$2:$C999,"Returned") -> 0 | C6: =SUMIFS('FC inventory'!E2:E999,'FC inventory'!$A$2:$A999,$A$1,'FC inventory'!$B$2:$B999,"Felele",'FC inventory'!$C$2:$C999,"Returned") -> 0 | D6: =SUMIFS('FC inventory'!F2:F999,'FC inventory'!$A$2:$A999,$A$1,'FC inventory'!$B$2:$B999,"Felele",'FC inventory'!$C$2:$C999,"Returned") -> 0 | E6: =SUMIFS('FC inventory'!G2:G999,'FC inventory'!$A$2:$A999,$A$1,'FC inventory'!$B$2:$B999,"Felele",'FC inventory'!$C$2:$C999,"Returned") -> 0 | F6: =SUMIFS('FC inventory'!H2:H999,'FC inventory'!$A$2:$A999,$A$1,'FC inventory'!$B$2:$B999,"Felele",'FC inventory'!$C$2:$C999,"Returned") -> 0 | G6: =SUMIFS('FC inventory'!I2:I999,'FC inventory'!$A$2:$A999,$A$1,'FC inventory'!$B$2:$B999,"Felele",'FC inventory'!$C$2:$C999,"Returned") -> 0 | H6: =SUMIFS('FC inventory'!J2:J999,'FC inventory'!$A$2:$A999,$A$1,'FC inventory'!$B$2:$B999,"Felele",'FC inventory'!$C$2:$C999,"Returned") -> 0 | I6: =SUMIFS('FC inventory'!K2:K999,'FC inventory'!$A$2:$A999,$A$1,'FC inventory'!$B$2:$B999,"Felele",'FC inventory'!$C$2:$C999,"Returned") -> 0 | ... AF6: =SUMIFS('FC inventory'!AH2:AH999,'FC inventory'!$A$2:$A999,$A$1,'FC inventory'!$B$2:$B999,"Felele",'FC inventory'!$C$2:$C999,"Returned") -> 0
A7: Balance | B7: =B3+B4-B5+B6 -> 0 | C7: =C3+C4-C5+C6 -> 0 | D7: =D3+D4-D5+D6 -> 0 | E7: =E3+E4-E5+E6 -> 0 | F7: =F3+F4-F5+F6 -> 0 | G7: =G3+G4-G5+G6 -> 26 | H7: =H3+H4-H5+H6 -> 0 | I7: =I3+I4-I5+I6 -> 0 | ... AF7: =AF3+AF4-AF5+AF6 -> 0

Sheet Closing stock
A1: Name of fulfillment centre | B1: Agemawo 1kg | C1: Boneless Beef 1kg | D1: Cow Hump 1kg | E1: Cow Head & Neck 1kg | F1: Goat Meat 1kg | G1: Chicken 1kg | H1: Titus 1kg (uncleaned) | I1: Titus 1kg (Cleaned) | J1: Hake 1kg (Cleaned) | K1: Hake 1kg (Uncleaned) | L1: Value Pack (Cow Tongue) | M1: Value Pack (Cow Assorted) | N1: Token Pack (Cow Minced Meat) | O1: Token Pack (Agemawo) | P1: Token pack(boneless beef) | Q1: Token Pack (Cow Tail) | R1: Token Pack (Cow Head & Neck) | S1: Token Pack (Cow Hump) | T1: Token Pack (Goat Meat) | U1: Token Pack (Chicken) | V1: Token Pack (Chicken Gizzard) | W1: Token Pack (Pomo) | X1: Token Pack (Shaki & Roundabout) | Y1: Token Pack (Cow Assorted) | Z1: Token Pack (Cow Leg) | AA1: Token Pack (Goat Assorted) | AB1: Token Pack (Titus) | AC1: Token Pack (Hake) | AD1: Token (small snail) | AE1: Token (big snail) | AF1: Token (Goat head & leg)
A2: Bashorun | B2: =(SUMIFS('FC inventory'!D$2:D1000,'FC inventory'!$C$2:$C1000,"In",'FC inventory'!$B$2:$B1000,$A2,'FC inventory'!$A$2:$A1000,"<"&Today())-SUMIFS('FC inventory'!D$2:D1000,'FC inventory'!$C$2:$C1000,"Out",'FC inventory'!$B$2:$B1000,$A2,'FC inventory'!$A$2:$A1000,"<"&Today())+SUMIFS('FC inventory'!D$2:D1000,'FC inventory'!$C$2:$C1000,"Return",'FC inventory'!$B$2:$B1000,$A2,'FC inventory'!$A$2:$A1000,"<"&Today())-SUMIFS('FC inventory'!D$2:D1000,'FC inventory'!$C$2:$C1000,"Spoilage",'FC inventory'!$B$2:$B1000,$A2,'FC inventory'!$A$2:$A1000,"<"&today()))+ (SUMIFS('FC inventory'!D$2:D1000,'FC inventory'!$C$2:$C1000,"In",'FC inventory'!$B$2:$B1000,$A2,'FC inventory'!$A$2:$A1000,Today()))-(SUMIFS('FC inventory'!D$2:D1000,'FC inventory'!$C$2:$C1000,"Out",'FC inventory'!$B$2:$B1000,$A2,'FC inventory'!$A$2:$A1000,Today()) - (SUMIFS('FC inventory'!D$2:D1000,'FC inventory'!$C$2:$C1000,"Retuned",'FC inventory'!$B$2:$B1000,$A2,'FC inventory'!$A$2:$A1000,Today()) - (SUMIFS('FC inventory'!D$2:D1000,'FC inventory'!$C$2:$C1000,"Spoilage",'FC inventory'!$B$2:$B1000,$A2,'FC inventory'!$A$2:$A1000,Today())))) -> 0 | C2: =(SUMIFS('FC inventory'!E$2:E1000,'FC inventory'!$C$2:$C1000,"In",'FC inventory'!$B$2:$B1000,$A2,'FC inventory'!$A$2:$A1000,"<"&Today())-SUMIFS('FC inventory'!E$2:E1000,'FC inventory'!$C$2:$C1000,"Out",'FC inventory'!$B$2:$B1000,$A2,'FC inventory'!$A$2:$A1000,"<"&Today())+SUMIFS('FC inventory'!E$2:E1000,'FC inventory'!$C$2:$C1000,"Return",'FC inventory'!$B$2:$B1000,$A2,'FC inventory'!$A$2:$A1000,"<"&Today())-SUMIFS('FC inventory'!E$2:E1000,'FC inventory'!$C$2:$C1000,"Spoilage",'FC inventory'!$B$2:$B1000,$A2,'FC inventory'!$A$2:$A1000,"<"&today()))+ (SUMIFS('FC inventory'!E$2:E1000,'FC inventory'!$C$2:$C1000,"In",'FC inventory'!$B$2:$B1000,$A2,'FC inventory'!$A$2:$A1000,Today()))-(SUMIFS('FC inventory'!E$2:E1000,'FC inventory'!$C$2:$C1000,"Out",'FC inventory'!$B$2:$B1000,$A2,'FC inventory'!$A$2:$A1000,Today()) - (SUMIFS('FC inventory'!E$2:E1000,'FC inventory'!$C$2:$C1000,"Retuned",'FC inventory'!$B$2:$B1000,$A2,'FC inventory'!$A$2:$A1000,Today()) - (SUMIFS('FC inventory'!E$2:E1000,'FC inventory'!$C$2:$C1000,"Spoilage",'FC inventory'!$B$2:$B1000,$A2,'FC inventory'!$A$2:$A1000,Today())))) -> 0 | D2: =(SUMIFS('FC inventory'!F$2:F1000,'FC inventory'!$C$2:$C1000,"In",'FC inventory'!$B$2:$B1000,$A2,'FC inventory'!$A$2:$A1000,"<"&Today())-SUMIFS('FC inventory'!F$2:F1000,'FC inventory'!$C$2:$C1000,"Out",'FC inventory'!$B$2:$B1000,$A2,'FC inventory'!$A$2:$A1000,"<"&Today())+SUMIFS('FC inventory'!F$2:F1000,'FC inventory'!$C$2:$C1000,"Return",'FC inventory'!$B$2:$B1000,$A2,'FC inventory'!$A$2:$A1000,"<"&Today())-SUMIFS('FC inventory'!F$2:F1000,'FC inventory'!$C$2:$C1000,"Spoilage",'FC inventory'!$B$2:$B1000,$A2,'FC inventory'!$A$2:$A1000,"<"&today()))+ (SUMIFS('FC inventory'!F$2:F1000,'FC inventory'!$C$2:$C1000,"In",'FC inventory'!$B$2:$B1000,$A2,'FC inventory'!$A$2:$A1000,Today()))-(SUMIFS('FC inventory'!F$2:F1000,'FC inventory'!$C$2:$C1000,"Out",'FC inventory'!$B$2:$B1000,$A2,'FC inventory'!$A$2:$A1000,Today()) - (SUMIFS('FC inventory'!F$2:F1000,'FC inventory'!$C$2:$C1000,"Retuned",'FC inventory'!$B$2:$B1000,$A2,'FC inventory'!$A$2:$A1000,Today()) - (SUMIFS('FC inventory'!F$2:F1000,'FC inventory'!$C$2:$C1000,"Spoilage",'FC inventory'!$B$2:$B1000,$A2,'FC inventory'!$A$2:$A1000,Today())))) -> 1 | E2: =(SUMIFS('FC inventory'!G$2:G1000,'FC inventory'!$C$2:$C1000,"In",'FC inventory'!$B$2:$B1000,$A2,'FC inventory'!$A$2:$A1000,"<"&Today())-SUMIFS('FC inventory'!G$2:G1000,'FC inventory'!$C$2:$C1000,"Out",'FC inventory'!$B$2:$B1000,$A2,'FC inventory'!$A$2:$A1000,"<"&Today())+SUMIFS('FC inventory'!G$2:G1000,'FC inventory'!$C$2:$C1000,"Return",'FC inventory'!$B$2:$B1000,$A2,'FC inventory'!$A$2:$A1000,"<"&Today())-SUMIFS('FC inventory'!G$2:G1000,'FC inventory'!$C$2:$C1000,"Spoilage",'FC inventory'!$B$2:$B1000,$A2,'FC inventory'!$A$2:$A1000,"<"&today()))+ (SUMIFS('FC inventory'!G$2:G1000,'FC inventory'!$C$2:$C1000,"In",'FC inventory'!$B$2:$B1000,$A2,'FC inventory'!$A$2:$A1000,Today()))-(SUMIFS('FC inventory'!G$2:G1000,'FC inventory'!$C$2:$C1000,"Out",'FC inventory'!$B$2:$B1000,$A2,'FC inventory'!$A$2:$A1000,Today()) - (SUMIFS('FC inventory'!G$2:G1000,'FC inventory'!$C$2:$C1000,"Retuned",'FC inventory'!$B$2:$B1000,$A2,'FC inventory'!$A$2:$A1000,Today()) - (SUMIFS('FC inventory'!G$2:G1000,'FC inventory'!$C$2:$C1000,"Spoilage",'FC inventory'!$B$2:$B1000,$A2,'FC inventory'!$A$2:$A1000,Today())))) -> 0 | F2: =(SUMIFS('FC inventory'!H$2:H1000,'FC inventory'!$C$2:$C1000,"In",'FC inventory'!$B$2:$B1000,$A2,'FC inventory'!$A$2:$A1000,"<"&Today())-SUMIFS('FC inventory'!H$2:H1000,'FC inventory'!$C$2:$C1000,"Out",'FC inventory'!$B$2:$B1000,$A2,'FC inventory'!$A$2:$A1000,"<"&Today())+SUMIFS('FC inventory'!H$2:H1000,'FC inventory'!$C$2:$C1000,"Return",'FC inventory'!$B$2:$B1000,$A2,'FC inventory'!$A$2:$A1000,"<"&Today())-SUMIFS('FC inventory'!H$2:H1000,'FC inventory'!$C$2:$C1000,"Spoilage",'FC inventory'!$B$2:$B1000,$A2,'FC inventory'!$A$2:$A1000,"<"&today()))+ (SUMIFS('FC inventory'!H$2:H1000,'FC inventory'!$C$2:$C1000,"In",'FC inventory'!$B$2:$B1000,$A2,'FC inventory'!$A$2:$A1000,Today()))-(SUMIFS('FC inventory'!H$2:H1000,'FC inventory'!$C$2:$C1000,"Out",'FC inventory'!$B$2:$B1000,$A2,'FC inventory'!$A$2:$A1000,Today()) - (SUMIFS('FC inventory'!H$2:H1000,'FC inventory'!$C$2:$C1000,"Retuned",'FC inventory'!$B$2:$B1000,$A2,'FC inventory'!$A$2:$A1000,Today()) - (SUMIFS('FC inventory'!H$2:H1000,'FC inventory'!$C$2:$C1000,"Spoilage",'FC inventory'!$B$2:$B1000,$A2,'FC inventory'!$A$2:$A1000,Today())))) -> 0 | G2: =(SUMIFS('FC inventory'!I$2:I1000,'FC inventory'!$C$2:$C1000,"In",'FC inventory'!$B$2:$B1000,$A2,'FC inventory'!$A$2:$A1000,"<"&Today())-SUMIFS('FC inventory'!I$2:I1000,'FC inventory'!$C$2:$C1000,"Out",'FC inventory'!$B$2:$B1000,$A2,'FC inventory'!$A$2:$A1000,"<"&Today())+SUMIFS('FC inventory'!I$2:I1000,'FC inventory'!$C$2:$C1000,"Return",'FC inventory'!$B$2:$B1000,$A2,'FC inventory'!$A$2:$A1000,"<"&Today())-SUMIFS('FC inventory'!I$2:I1000,'FC inventory'!$C$2:$C1000,"Spoilage",'FC inventory'!$B$2:$B1000,$A2,'FC inventory'!$A$2:$A1000,"<"&today()))+ (SUMIFS('FC inventory'!I$2:I1000,'FC inventory'!$C$2:$C1000,"In",'FC inventory'!$B$2:$B1000,$A2,'FC inventory'!$A$2:$A1000,Today()))-(SUMIFS('FC inventory'!I$2:I1000,'FC inventory'!$C$2:$C1000,"Out",'FC inventory'!$B$2:$B1000,$A2,'FC inventory'!$A$2:$A1000,Today()) - (SUMIFS('FC inventory'!I$2:I1000,'FC inventory'!$C$2:$C1000,"Retuned",'FC inventory'!$B$2:$B1000,$A2,'FC inventory'!$A$2:$A1000,Today()) - (SUMIFS('FC inventory'!I$2:I1000,'FC inventory'!$C$2:$C1000,"Spoilage",'FC inventory'!$B$2:$B1000,$A2,'FC inventory'!$A$2:$A1000,Today())))) -> 42 | H2: =(SUMIFS('FC inventory'!J$2:J1000,'FC inventory'!$C$2:$C1000,"In",'FC inventory'!$B$2:$B1000,$A2,'FC inventory'!$A$2:$A1000,"<"&Today())-SUMIFS('FC inventory'!J$2:J1000,'FC inventory'!$C$2:$C1000,"Out",'FC inventory'!$B$2:$B1000,$A2,'FC inventory'!$A$2:$A1000,"<"&Today())+SUMIFS('FC inventory'!J$2:J1000,'FC inventory'!$C$2:$C1000,"Return",'FC inventory'!$B$2:$B1000,$A2,'FC inventory'!$A$2:$A1000,"<"&Today())-SUMIFS('FC inventory'!J$2:J1000,'FC inventory'!$C$2:$C1000,"Spoilage",'FC inventory'!$B$2:$B1000,$A2,'FC inventory'!$A$2:$A1000,"<"&today()))+ (SUMIFS('FC inventory'!J$2:J1000,'FC inventory'!$C$2:$C1000,"In",'FC inventory'!$B$2:$B1000,$A2,'FC inventory'!$A$2:$A1000,Today()))-(SUMIFS('FC inventory'!J$2:J1000,'FC inventory'!$C$2:$C1000,"Out",'FC inventory'!$B$2:$B1000,$A2,'FC inventory'!$A$2:$A1000,Today()) - (SUMIFS('FC inventory'!J$2:J1000,'FC inventory'!$C$2:$C1000,"Retuned",'FC inventory'!$B$2:$B1000,$A2,'FC inventory'!$A$2:$A1000,Today()) - (SUMIFS('FC inventory'!J$2:J1000,'FC inventory'!$C$2:$C1000,"Spoilage",'FC inventory'!$B$2:$B1000,$A2,'FC inventory'!$A$2:$A1000,Today())))) -> 0 | I2: =(SUMIFS('FC inventory'!K$2:K1000,'FC inventory'!$C$2:$C1000,"In",'FC inventory'!$B$2:$B1000,$A2,'FC inventory'!$A$2:$A1000,"<"&Today())-SUMIFS('FC inventory'!K$2:K1000,'FC inventory'!$C$2:$C1000,"Out",'FC inventory'!$B$2:$B1000,$A2,'FC inventory'!$A$2:$A1000,"<"&Today())+SUMIFS('FC inventory'!K$2:K1000,'FC inventory'!$C$2:$C1000,"Return",'FC inventory'!$B$2:$B1000,$A2,'FC inventory'!$A$2:$A1000,"<"&Today())-SUMIFS('FC inventory'!K$2:K1000,'FC inventory'!$C$2:$C1000,"Spoilage",'FC inventory'!$B$2:$B1000,$A2,'FC inventory'!$A$2:$A1000,"<"&today()))+ (SUMIFS('FC inventory'!K$2:K1000,'FC inventory'!$C$2:$C1000,"In",'FC inventory'!$B$2:$B1000,$A2,'FC inventory'!$A$2:$A1000,Today()))-(SUMIFS('FC inventory'!K$2:K1000,'FC inventory'!$C$2:$C1000,"Out",'FC inventory'!$B$2:$B1000,$A2,'FC inventory'!$A$2:$A1000,Today()) - (SUMIFS('FC inventory'!K$2:K1000,'FC inventory'!$C$2:$C1000,"Retuned",'FC inventory'!$B$2:$B1000,$A2,'FC inventory'!$A$2:$A1000,Today()) - (SUMIFS('FC inventory'!K$2:K1000,'FC inventory'!$C$2:$C1000,"Spoilage",'FC inventory'!$B$2:$B1000,$A2,'FC inventory'!$A$2:$A1000,Today())))) -> 0 | ... AF2: =(SUMIFS('FC inventory'!AH$2:AH1000,'FC inventory'!$C$2:$C1000,"In",'FC inventory'!$B$2:$B1000,$A2,'FC inventory'!$A$2:$A1000,"<"&Today())-SUMIFS('FC inventory'!AH$2:AH1000,'FC inventory'!$C$2:$C1000,"Out",'FC inventory'!$B$2:$B1000,$A2,'FC inventory'!$A$2:$A1000,"<"&Today())+SUMIFS('FC inventory'!AH$2:AH1000,'FC inventory'!$C$2:$C1000,"Return",'FC inventory'!$B$2:$B1000,$A2,'FC inventory'!$A$2:$A1000,"<"&Today())-SUMIFS('FC inventory'!AH$2:AH1000,'FC inventory'!$C$2:$C1000,"Spoilage",'FC inventory'!$B$2:$B1000,$A2,'FC inventory'!$A$2:$A1000,"<"&today()))+ (SUMIFS('FC inventory'!AH$2:AH1000,'FC inventory'!$C$2:$C1000,"In",'FC inventory'!$B$2:$B1000,$A2,'FC inventory'!$A$2:$A1000,Today()))-(SUMIFS('FC inventory'!AH$2:AH1000,'FC inventory'!$C$2:$C1000,"Out",'FC inventory'!$B$2:$B1000,$A2,'FC inventory'!$A$2:$A1000,Today()) - (SUMIFS('FC inventory'!AH$2:AH1000,'FC inventory'!$C$2:$C1000,"Retuned",'FC inventory'!$B$2:$B1000,$A2,'FC inventory'!$A$2:$A1000,Today()) - (SUMIFS('FC inventory'!AH$2:AH1000,'FC inventory'!$C$2:$C1000,"Spoilage",'FC inventory'!$B$2:$B1000,$A2,'FC inventory'!$A$2:$A1000,Today())))) -> 0
A3: Alakia | B3: =(SUMIFS('FC inventory'!D$2:D1000,'FC inventory'!$C$2:$C1000,"In",'FC inventory'!$B$2:$B1000,$A3,'FC inventory'!$A$2:$A1000,"<"&Today())-SUMIFS('FC inventory'!D$2:D1000,'FC inventory'!$C$2:$C1000,"Out",'FC inventory'!$B$2:$B1000,$A3,'FC inventory'!$A$2:$A1000,"<"&Today())+SUMIFS('FC inventory'!D$2:D1000,'FC inventory'!$C$2:$C1000,"Return",'FC inventory'!$B$2:$B1000,$A3,'FC inventory'!$A$2:$A1000,"<"&Today())-SUMIFS('FC inventory'!D$2:D1000,'FC inventory'!$C$2:$C1000,"Spoilage",'FC inventory'!$B$2:$B1000,$A3,'FC inventory'!$A$2:$A1000,"<"&today()))+ (SUMIFS('FC inventory'!D$2:D1000,'FC inventory'!$C$2:$C1000,"In",'FC inventory'!$B$2:$B1000,$A3,'FC inventory'!$A$2:$A1000,Today()))-(SUMIFS('FC inventory'!D$2:D1000,'FC inventory'!$C$2:$C1000,"Out",'FC inventory'!$B$2:$B1000,$A3,'FC inventory'!$A$2:$A1000,Today()) - (SUMIFS('FC inventory'!D$2:D1000,'FC inventory'!$C$2:$C1000,"Retuned",'FC inventory'!$B$2:$B1000,$A3,'FC inventory'!$A$2:$A1000,Today()) - (SUMIFS('FC inventory'!D$2:D1000,'FC inventory'!$C$2:$C1000,"Spoilage",'FC inventory'!$B$2:$B1000,$A3,'FC inventory'!$A$2:$A1000,Today())))) -> 0 | C3: =(SUMIFS('FC inventory'!E$2:E1000,'FC inventory'!$C$2:$C1000,"In",'FC inventory'!$B$2:$B1000,$A3,'FC inventory'!$A$2:$A1000,"<"&Today())-SUMIFS('FC inventory'!E$2:E1000,'FC inventory'!$C$2:$C1000,"Out",'FC inventory'!$B$2:$B1000,$A3,'FC inventory'!$A$2:$A1000,"<"&Today())+SUMIFS('FC inventory'!E$2:E1000,'FC inventory'!$C$2:$C1000,"Return",'FC inventory'!$B$2:$B1000,$A3,'FC inventory'!$A$2:$A1000,"<"&Today())-SUMIFS('FC inventory'!E$2:E1000,'FC inventory'!$C$2:$C1000,"Spoilage",'FC inventory'!$B$2:$B1000,$A3,'FC inventory'!$A$2:$A1000,"<"&today()))+ (SUMIFS('FC inventory'!E$2:E1000,'FC inventory'!$C$2:$C1000,"In",'FC inventory'!$B$2:$B1000,$A3,'FC inventory'!$A$2:$A1000,Today()))-(SUMIFS('FC inventory'!E$2:E1000,'FC inventory'!$C$2:$C1000,"Out",'FC inventory'!$B$2:$B1000,$A3,'FC inventory'!$A$2:$A1000,Today()) - (SUMIFS('FC inventory'!E$2:E1000,'FC inventory'!$C$2:$C1000,"Retuned",'FC inventory'!$B$2:$B1000,$A3,'FC inventory'!$A$2:$A1000,Today()) - (SUMIFS('FC inventory'!E$2:E1000,'FC inventory'!$C$2:$C1000,"Spoilage",'FC inventory'!$B$2:$B1000,$A3,'FC inventory'!$A$2:$A1000,Today())))) -> 3 | D3: =(SUMIFS('FC inventory'!F$2:F1000,'FC inventory'!$C$2:$C1000,"In",'FC inventory'!$B$2:$B1000,$A3,'FC inventory'!$A$2:$A1000,"<"&Today())-SUMIFS('FC inventory'!F$2:F1000,'FC inventory'!$C$2:$C1000,"Out",'FC inventory'!$B$2:$B1000,$A3,'FC inventory'!$A$2:$A1000,"<"&Today())+SUMIFS('FC inventory'!F$2:F1000,'FC inventory'!$C$2:$C1000,"Return",'FC inventory'!$B$2:$B1000,$A3,'FC inventory'!$A$2:$A1000,"<"&Today())-SUMIFS('FC inventory'!F$2:F1000,'FC inventory'!$C$2:$C1000,"Spoilage",'FC inventory'!$B$2:$B1000,$A3,'FC inventory'!$A$2:$A1000,"<"&today()))+ (SUMIFS('FC inventory'!F$2:F1000,'FC inventory'!$C$2:$C1000,"In",'FC inventory'!$B$2:$B1000,$A3,'FC inventory'!$A$2:$A1000,Today()))-(SUMIFS('FC inventory'!F$2:F1000,'FC inventory'!$C$2:$C1000,"Out",'FC inventory'!$B$2:$B1000,$A3,'FC inventory'!$A$2:$A1000,Today()) - (SUMIFS('FC inventory'!F$2:F1000,'FC inventory'!$C$2:$C1000,"Retuned",'FC inventory'!$B$2:$B1000,$A3,'FC inventory'!$A$2:$A1000,Today()) - (SUMIFS('FC inventory'!F$2:F1000,'FC inventory'!$C$2:$C1000,"Spoilage",'FC inventory'!$B$2:$B1000,$A3,'FC inventory'!$A$2:$A1000,Today())))) -> 0 | E3: =(SUMIFS('FC inventory'!G$2:G1000,'FC inventory'!$C$2:$C1000,"In",'FC inventory'!$B$2:$B1000,$A3,'FC inventory'!$A$2:$A1000,"<"&Today())-SUMIFS('FC inventory'!G$2:G1000,'FC inventory'!$C$2:$C1000,"Out",'FC inventory'!$B$2:$B1000,$A3,'FC inventory'!$A$2:$A1000,"<"&Today())+SUMIFS('FC inventory'!G$2:G1000,'FC inventory'!$C$2:$C1000,"Return",'FC inventory'!$B$2:$B1000,$A3,'FC inventory'!$A$2:$A1000,"<"&Today())-SUMIFS('FC inventory'!G$2:G1000,'FC inventory'!$C$2:$C1000,"Spoilage",'FC inventory'!$B$2:$B1000,$A3,'FC inventory'!$A$2:$A1000,"<"&today()))+ (SUMIFS('FC inventory'!G$2:G1000,'FC inventory'!$C$2:$C1000,"In",'FC inventory'!$B$2:$B1000,$A3,'FC inventory'!$A$2:$A1000,Today()))-(SUMIFS('FC inventory'!G$2:G1000,'FC inventory'!$C$2:$C1000,"Out",'FC inventory'!$B$2:$B1000,$A3,'FC inventory'!$A$2:$A1000,Today()) - (SUMIFS('FC inventory'!G$2:G1000,'FC inventory'!$C$2:$C1000,"Retuned",'FC inventory'!$B$2:$B1000,$A3,'FC inventory'!$A$2:$A1000,Today()) - (SUMIFS('FC inventory'!G$2:G1000,'FC inventory'!$C$2:$C1000,"Spoilage",'FC inventory'!$B$2:$B1000,$A3,'FC inventory'!$A$2:$A1000,Today())))) -> 0 | F3: =(SUMIFS('FC inventory'!H$2:H1000,'FC inventory'!$C$2:$C1000,"In",'FC inventory'!$B$2:$B1000,$A3,'FC inventory'!$A$2:$A1000,"<"&Today())-SUMIFS('FC inventory'!H$2:H1000,'FC inventory'!$C$2:$C1000,"Out",'FC inventory'!$B$2:$B1000,$A3,'FC inventory'!$A$2:$A1000,"<"&Today())+SUMIFS('FC inventory'!H$2:H1000,'FC inventory'!$C$2:$C1000,"Return",'FC inventory'!$B$2:$B1000,$A3,'FC inventory'!$A$2:$A1000,"<"&Today())-SUMIFS('FC inventory'!H$2:H1000,'FC inventory'!$C$2:$C1000,"Spoilage",'FC inventory'!$B$2:$B1000,$A3,'FC inventory'!$A$2:$A1000,"<"&today()))+ (SUMIFS('FC inventory'!H$2:H1000,'FC inventory'!$C$2:$C1000,"In",'FC inventory'!$B$2:$B1000,$A3,'FC inventory'!$A$2:$A1000,Today()))-(SUMIFS('FC inventory'!H$2:H1000,'FC inventory'!$C$2:$C1000,"Out",'FC inventory'!$B$2:$B1000,$A3,'FC inventory'!$A$2:$A1000,Today()) - (SUMIFS('FC inventory'!H$2:H1000,'FC inventory'!$C$2:$C1000,"Retuned",'FC inventory'!$B$2:$B1000,$A3,'FC inventory'!$A$2:$A1000,Today()) - (SUMIFS('FC inventory'!H$2:H1000,'FC inventory'!$C$2:$C1000,"Spoilage",'FC inventory'!$B$2:$B1000,$A3,'FC inventory'!$A$2:$A1000,Today())))) -> 0 | G3: =(SUMIFS('FC inventory'!I$2:I1000,'FC inventory'!$C$2:$C1000,"In",'FC inventory'!$B$2:$B1000,$A3,'FC inventory'!$A$2:$A1000,"<"&Today())-SUMIFS('FC inventory'!I$2:I1000,'FC inventory'!$C$2:$C1000,"Out",'FC inventory'!$B$2:$B1000,$A3,'FC inventory'!$A$2:$A1000,"<"&Today())+SUMIFS('FC inventory'!I$2:I1000,'FC inventory'!$C$2:$C1000,"Return",'FC inventory'!$B$2:$B1000,$A3,'FC inventory'!$A$2:$A1000,"<"&Today())-SUMIFS('FC inventory'!I$2:I1000,'FC inventory'!$C$2:$C1000,"Spoilage",'FC inventory'!$B$2:$B1000,$A3,'FC inventory'!$A$2:$A1000,"<"&today()))+ (SUMIFS('FC inventory'!I$2:I1000,'FC inventory'!$C$2:$C1000,"In",'FC inventory'!$B$2:$B1000,$A3,'FC inventory'!$A$2:$A1000,Today()))-(SUMIFS('FC inventory'!I$2:I1000,'FC inventory'!$C$2:$C1000,"Out",'FC inventory'!$B$2:$B1000,$A3,'FC inventory'!$A$2:$A1000,Today()) - (SUMIFS('FC inventory'!I$2:I1000,'FC inventory'!$C$2:$C1000,"Retuned",'FC inventory'!$B$2:$B1000,$A3,'FC inventory'!$A$2:$A1000,Today()) - (SUMIFS('FC inventory'!I$2:I1000,'FC inventory'!$C$2:$C1000,"Spoilage",'FC inventory'!$B$2:$B1000,$A3,'FC inventory'!$A$2:$A1000,Today())))) -> 25 | H3: =(SUMIFS('FC inventory'!J$2:J1000,'FC inventory'!$C$2:$C1000,"In",'FC inventory'!$B$2:$B1000,$A3,'FC inventory'!$A$2:$A1000,"<"&Today())-SUMIFS('FC inventory'!J$2:J1000,'FC inventory'!$C$2:$C1000,"Out",'FC inventory'!$B$2:$B1000,$A3,'FC inventory'!$A$2:$A1000,"<"&Today())+SUMIFS('FC inventory'!J$2:J1000,'FC inventory'!$C$2:$C1000,"Return",'FC inventory'!$B$2:$B1000,$A3,'FC inventory'!$A$2:$A1000,"<"&Today())-SUMIFS('FC inventory'!J$2:J1000,'FC inventory'!$C$2:$C1000,"Spoilage",'FC inventory'!$B$2:$B1000,$A3,'FC inventory'!$A$2:$A1000,"<"&today()))+ (SUMIFS('FC inventory'!J$2:J1000,'FC inventory'!$C$2:$C1000,"In",'FC inventory'!$B$2:$B1000,$A3,'FC inventory'!$A$2:$A1000,Today()))-(SUMIFS('FC inventory'!J$2:J1000,'FC inventory'!$C$2:$C1000,"Out",'FC inventory'!$B$2:$B1000,$A3,'FC inventory'!$A$2:$A1000,Today()) - (SUMIFS('FC inventory'!J$2:J1000,'FC inventory'!$C$2:$C1000,"Retuned",'FC inventory'!$B$2:$B1000,$A3,'FC inventory'!$A$2:$A1000,Today()) - (SUMIFS('FC inventory'!J$2:J1000,'FC inventory'!$C$2:$C1000,"Spoilage",'FC inventory'!$B$2:$B1000,$A3,'FC inventory'!$A$2:$A1000,Today())))) -> 0 | I3: =(SUMIFS('FC inventory'!K$2:K1000,'FC inventory'!$C$2:$C1000,"In",'FC inventory'!$B$2:$B1000,$A3,'FC inventory'!$A$2:$A1000,"<"&Today())-SUMIFS('FC inventory'!K$2:K1000,'FC inventory'!$C$2:$C1000,"Out",'FC inventory'!$B$2:$B1000,$A3,'FC inventory'!$A$2:$A1000,"<"&Today())+SUMIFS('FC inventory'!K$2:K1000,'FC inventory'!$C$2:$C1000,"Return",'FC inventory'!$B$2:$B1000,$A3,'FC inventory'!$A$2:$A1000,"<"&Today())-SUMIFS('FC inventory'!K$2:K1000,'FC inventory'!$C$2:$C1000,"Spoilage",'FC inventory'!$B$2:$B1000,$A3,'FC inventory'!$A$2:$A1000,"<"&today()))+ (SUMIFS('FC inventory'!K$2:K1000,'FC inventory'!$C$2:$C1000,"In",'FC inventory'!$B$2:$B1000,$A3,'FC inventory'!$A$2:$A1000,Today()))-(SUMIFS('FC inventory'!K$2:K1000,'FC inventory'!$C$2:$C1000,"Out",'FC inventory'!$B$2:$B1000,$A3,'FC inventory'!$A$2:$A1000,Today()) - (SUMIFS('FC inventory'!K$2:K1000,'FC inventory'!$C$2:$C1000,"Retuned",'FC inventory'!$B$2:$B1000,$A3,'FC inventory'!$A$2:$A1000,Today()) - (SUMIFS('FC inventory'!K$2:K1000,'FC inventory'!$C$2:$C1000,"Spoilage",'FC inventory'!$B$2:$B1000,$A3,'FC inventory'!$A$2:$A1000,Today())))) -> 0 | ... AF3: =(SUMIFS('FC inventory'!AH$2:AH1000,'FC inventory'!$C$2:$C1000,"In",'FC inventory'!$B$2:$B1000,$A3,'FC inventory'!$A$2:$A1000,"<"&Today())-SUMIFS('FC inventory'!AH$2:AH1000,'FC inventory'!$C$2:$C1000,"Out",'FC inventory'!$B$2:$B1000,$A3,'FC inventory'!$A$2:$A1000,"<"&Today())+SUMIFS('FC inventory'!AH$2:AH1000,'FC inventory'!$C$2:$C1000,"Return",'FC inventory'!$B$2:$B1000,$A3,'FC inventory'!$A$2:$A1000,"<"&Today())-SUMIFS('FC inventory'!AH$2:AH1000,'FC inventory'!$C$2:$C1000,"Spoilage",'FC inventory'!$B$2:$B1000,$A3,'FC inventory'!$A$2:$A1000,"<"&today()))+ (SUMIFS('FC inventory'!AH$2:AH1000,'FC inventory'!$C$2:$C1000,"In",'FC inventory'!$B$2:$B1000,$A3,'FC inventory'!$A$2:$A1000,Today()))-(SUMIFS('FC inventory'!AH$2:AH1000,'FC inventory'!$C$2:$C1000,"Out",'FC inventory'!$B$2:$B1000,$A3,'FC inventory'!$A$2:$A1000,Today()) - (SUMIFS('FC inventory'!AH$2:AH1000,'FC inventory'!$C$2:$C1000,"Retuned",'FC inventory'!$B$2:$B1000,$A3,'FC inventory'!$A$2:$A1000,Today()) - (SUMIFS('FC inventory'!AH$2:AH1000,'FC inventory'!$C$2:$C1000,"Spoilage",'FC inventory'!$B$2:$B1000,$A3,'FC inventory'!$A$2:$A1000,Today())))) -> 0
A4: BCT | B4: =(SUMIFS('FC inventory'!D$2:D1000,'FC inventory'!$C$2:$C1000,"In",'FC inventory'!$B$2:$B1000,$A4,'FC inventory'!$A$2:$A1000,"<"&Today())-SUMIFS('FC inventory'!D$2:D1000,'FC inventory'!$C$2:$C1000,"Out",'FC inventory'!$B$2:$B1000,$A4,'FC inventory'!$A$2:$A1000,"<"&Today())+SUMIFS('FC inventory'!D$2:D1000,'FC inventory'!$C$2:$C1000,"Return",'FC inventory'!$B$2:$B1000,$A4,'FC inventory'!$A$2:$A1000,"<"&Today())-SUMIFS('FC inventory'!D$2:D1000,'FC inventory'!$C$2:$C1000,"Spoilage",'FC inventory'!$B$2:$B1000,$A4,'FC inventory'!$A$2:$A1000,"<"&today()))+ (SUMIFS('FC inventory'!D$2:D1000,'FC inventory'!$C$2:$C1000,"In",'FC inventory'!$B$2:$B1000,$A4,'FC inventory'!$A$2:$A1000,Today()))-(SUMIFS('FC inventory'!D$2:D1000,'FC inventory'!$C$2:$C1000,"Out",'FC inventory'!$B$2:$B1000,$A4,'FC inventory'!$A$2:$A1000,Today()) - (SUMIFS('FC inventory'!D$2:D1000,'FC inventory'!$C$2:$C1000,"Retuned",'FC inventory'!$B$2:$B1000,$A4,'FC inventory'!$A$2:$A1000,Today()) - (SUMIFS('FC inventory'!D$2:D1000,'FC inventory'!$C$2:$C1000,"Spoilage",'FC inventory'!$B$2:$B1000,$A4,'FC inventory'!$A$2:$A1000,Today())))) -> -2 | C4: =(SUMIFS('FC inventory'!E$2:E1000,'FC inventory'!$C$2:$C1000,"In",'FC inventory'!$B$2:$B1000,$A4,'FC inventory'!$A$2:$A1000,"<"&Today())-SUMIFS('FC inventory'!E$2:E1000,'FC inventory'!$C$2:$C1000,"Out",'FC inventory'!$B$2:$B1000,$A4,'FC inventory'!$A$2:$A1000,"<"&Today())+SUMIFS('FC inventory'!E$2:E1000,'FC inventory'!$C$2:$C1000,"Return",'FC inventory'!$B$2:$B1000,$A4,'FC inventory'!$A$2:$A1000,"<"&Today())-SUMIFS('FC inventory'!E$2:E1000,'FC inventory'!$C$2:$C1000,"Spoilage",'FC inventory'!$B$2:$B1000,$A4,'FC inventory'!$A$2:$A1000,"<"&today()))+ (SUMIFS('FC inventory'!E$2:E1000,'FC inventory'!$C$2:$C1000,"In",'FC inventory'!$B$2:$B1000,$A4,'FC inventory'!$A$2:$A1000,Today()))-(SUMIFS('FC inventory'!E$2:E1000,'FC inventory'!$C$2:$C1000,"Out",'FC inventory'!$B$2:$B1000,$A4,'FC inventory'!$A$2:$A1000,Today()) - (SUMIFS('FC inventory'!E$2:E1000,'FC inventory'!$C$2:$C1000,"Retuned",'FC inventory'!$B$2:$B1000,$A4,'FC inventory'!$A$2:$A1000,Today()) - (SUMIFS('FC inventory'!E$2:E1000,'FC inventory'!$C$2:$C1000,"Spoilage",'FC inventory'!$B$2:$B1000,$A4,'FC inventory'!$A$2:$A1000,Today())))) -> 0 | D4: =(SUMIFS('FC inventory'!F$2:F1000,'FC inventory'!$C$2:$C1000,"In",'FC inventory'!$B$2:$B1000,$A4,'FC inventory'!$A$2:$A1000,"<"&Today())-SUMIFS('FC inventory'!F$2:F1000,'FC inventory'!$C$2:$C1000,"Out",'FC inventory'!$B$2:$B1000,$A4,'FC inventory'!$A$2:$A1000,"<"&Today())+SUMIFS('FC inventory'!F$2:F1000,'FC inventory'!$C$2:$C1000,"Return",'FC inventory'!$B$2:$B1000,$A4,'FC inventory'!$A$2:$A1000,"<"&Today())-SUMIFS('FC inventory'!F$2:F1000,'FC inventory'!$C$2:$C1000,"Spoilage",'FC inventory'!$B$2:$B1000,$A4,'FC inventory'!$A$2:$A1000,"<"&today()))+ (SUMIFS('FC inventory'!F$2:F1000,'FC inventory'!$C$2:$C1000,"In",'FC inventory'!$B$2:$B1000,$A4,'FC inventory'!$A$2:$A1000,Today()))-(SUMIFS('FC inventory'!F$2:F1000,'FC inventory'!$C$2:$C1000,"Out",'FC inventory'!$B$2:$B1000,$A4,'FC inventory'!$A$2:$A1000,Today()) - (SUMIFS('FC inventory'!F$2:F1000,'FC inventory'!$C$2:$C1000,"Retuned",'FC inventory'!$B$2:$B1000,$A4,'FC inventory'!$A$2:$A1000,Today()) - (SUMIFS('FC inventory'!F$2:F1000,'FC inventory'!$C$2:$C1000,"Spoilage",'FC inventory'!$B$2:$B1000,$A4,'FC inventory'!$A$2:$A1000,Today())))) -> 0 | E4: =(SUMIFS('FC inventory'!G$2:G1000,'FC inventory'!$C$2:$C1000,"In",'FC inventory'!$B$2:$B1000,$A4,'FC inventory'!$A$2:$A1000,"<"&Today())-SUMIFS('FC inventory'!G$2:G1000,'FC inventory'!$C$2:$C1000,"Out",'FC inventory'!$B$2:$B1000,$A4,'FC inventory'!$A$2:$A1000,"<"&Today())+SUMIFS('FC inventory'!G$2:G1000,'FC inventory'!$C$2:$C1000,"Return",'FC inventory'!$B$2:$B1000,$A4,'FC inventory'!$A$2:$A1000,"<"&Today())-SUMIFS('FC inventory'!G$2:G1000,'FC inventory'!$C$2:$C1000,"Spoilage",'FC inventory'!$B$2:$B1000,$A4,'FC inventory'!$A$2:$A1000,"<"&today()))+ (SUMIFS('FC inventory'!G$2:G1000,'FC inventory'!$C$2:$C1000,"In",'FC inventory'!$B$2:$B1000,$A4,'FC inventory'!$A$2:$A1000,Today()))-(SUMIFS('FC inventory'!G$2:G1000,'FC inventory'!$C$2:$C1000,"Out",'FC inventory'!$B$2:$B1000,$A4,'FC inventory'!$A$2:$A1000,Today()) - (SUMIFS('FC inventory'!G$2:G1000,'FC inventory'!$C$2:$C1000,"Retuned",'FC inventory'!$B$2:$B1000,$A4,'FC inventory'!$A$2:$A1000,Today()) - (SUMIFS('FC inventory'!G$2:G1000,'FC inventory'!$C$2:$C1000,"Spoilage",'FC inventory'!$B$2:$B1000,$A4,'FC inventory'!$A$2:$A1000,Today())))) -> -1 | F4: =(SUMIFS('FC inventory'!H$2:H1000,'FC inventory'!$C$2:$C1000,"In",'FC inventory'!$B$2:$B1000,$A4,'FC inventory'!$A$2:$A1000,"<"&Today())-SUMIFS('FC inventory'!H$2:H1000,'FC inventory'!$C$2:$C1000,"Out",'FC inventory'!$B$2:$B1000,$A4,'FC inventory'!$A$2:$A1000,"<"&Today())+SUMIFS('FC inventory'!H$2:H1000,'FC inventory'!$C$2:$C1000,"Return",'FC inventory'!$B$2:$B1000,$A4,'FC inventory'!$A$2:$A1000,"<"&Today())-SUMIFS('FC inventory'!H$2:H1000,'FC inventory'!$C$2:$C1000,"Spoilage",'FC inventory'!$B$2:$B1000,$A4,'FC inventory'!$A$2:$A1000,"<"&today()))+ (SUMIFS('FC inventory'!H$2:H1000,'FC inventory'!$C$2:$C1000,"In",'FC inventory'!$B$2:$B1000,$A4,'FC inventory'!$A$2:$A1000,Today()))-(SUMIFS('FC inventory'!H$2:H1000,'FC inventory'!$C$2:$C1000,"Out",'FC inventory'!$B$2:$B1000,$A4,'FC inventory'!$A$2:$A1000,Today()) - (SUMIFS('FC inventory'!H$2:H1000,'FC inventory'!$C$2:$C1000,"Retuned",'FC inventory'!$B$2:$B1000,$A4,'FC inventory'!$A$2:$A1000,Today()) - (SUMIFS('FC inventory'!H$2:H1000,'FC inventory'!$C$2:$C1000,"Spoilage",'FC inventory'!$B$2:$B1000,$A4,'FC inventory'!$A$2:$A1000,Today())))) -> 0 | G4: =(SUMIFS('FC inventory'!I$2:I1000,'FC inventory'!$C$2:$C1000,"In",'FC inventory'!$B$2:$B1000,$A4,'FC inventory'!$A$2:$A1000,"<"&Today())-SUMIFS('FC inventory'!I$2:I1000,'FC inventory'!$C$2:$C1000,"Out",'FC inventory'!$B$2:$B1000,$A4,'FC inventory'!$A$2:$A1000,"<"&Today())+SUMIFS('FC inventory'!I$2:I1000,'FC inventory'!$C$2:$C1000,"Return",'FC inventory'!$B$2:$B1000,$A4,'FC inventory'!$A$2:$A1000,"<"&Today())-SUMIFS('FC inventory'!I$2:I1000,'FC inventory'!$C$2:$C1000,"Spoilage",'FC inventory'!$B$2:$B1000,$A4,'FC inventory'!$A$2:$A1000,"<"&today()))+ (SUMIFS('FC inventory'!I$2:I1000,'FC inventory'!$C$2:$C1000,"In",'FC inventory'!$B$2:$B1000,$A4,'FC inventory'!$A$2:$A1000,Today()))-(SUMIFS('FC inventory'!I$2:I1000,'FC inventory'!$C$2:$C1000,"Out",'FC inventory'!$B$2:$B1000,$A4,'FC inventory'!$A$2:$A1000,Today()) - (SUMIFS('FC inventory'!I$2:I1000,'FC inventory'!$C$2:$C1000,"Retuned",'FC inventory'!$B$2:$B1000,$A4,'FC inventory'!$A$2:$A1000,Today()) - (SUMIFS('FC inventory'!I$2:I1000,'FC inventory'!$C$2:$C1000,"Spoilage",'FC inventory'!$B$2:$B1000,$A4,'FC inventory'!$A$2:$A1000,Today())))) -> 35 | H4: =(SUMIFS('FC inventory'!J$2:J1000,'FC inventory'!$C$2:$C1000,"In",'FC inventory'!$B$2:$B1000,$A4,'FC inventory'!$A$2:$A1000,"<"&Today())-SUMIFS('FC inventory'!J$2:J1000,'FC inventory'!$C$2:$C1000,"Out",'FC inventory'!$B$2:$B1000,$A4,'FC inventory'!$A$2:$A1000,"<"&Today())+SUMIFS('FC inventory'!J$2:J1000,'FC inventory'!$C$2:$C1000,"Return",'FC inventory'!$B$2:$B1000,$A4,'FC inventory'!$A$2:$A1000,"<"&Today())-SUMIFS('FC inventory'!J$2:J1000,'FC inventory'!$C$2:$C1000,"Spoilage",'FC inventory'!$B$2:$B1000,$A4,'FC inventory'!$A$2:$A1000,"<"&today()))+ (SUMIFS('FC inventory'!J$2:J1000,'FC inventory'!$C$2:$C1000,"In",'FC inventory'!$B$2:$B1000,$A4,'FC inventory'!$A$2:$A1000,Today()))-(SUMIFS('FC inventory'!J$2:J1000,'FC inventory'!$C$2:$C1000,"Out",'FC inventory'!$B$2:$B1000,$A4,'FC inventory'!$A$2:$A1000,Today()) - (SUMIFS('FC inventory'!J$2:J1000,'FC inventory'!$C$2:$C1000,"Retuned",'FC inventory'!$B$2:$B1000,$A4,'FC inventory'!$A$2:$A1000,Today()) - (SUMIFS('FC inventory'!J$2:J1000,'FC inventory'!$C$2:$C1000,"Spoilage",'FC inventory'!$B$2:$B1000,$A4,'FC inventory'!$A$2:$A1000,Today())))) -> 0 | I4: =(SUMIFS('FC inventory'!K$2:K1000,'FC inventory'!$C$2:$C1000,"In",'FC inventory'!$B$2:$B1000,$A4,'FC inventory'!$A$2:$A1000,"<"&Today())-SUMIFS('FC inventory'!K$2:K1000,'FC inventory'!$C$2:$C1000,"Out",'FC inventory'!$B$2:$B1000,$A4,'FC inventory'!$A$2:$A1000,"<"&Today())+SUMIFS('FC inventory'!K$2:K1000,'FC inventory'!$C$2:$C1000,"Return",'FC inventory'!$B$2:$B1000,$A4,'FC inventory'!$A$2:$A1000,"<"&Today())-SUMIFS('FC inventory'!K$2:K1000,'FC inventory'!$C$2:$C1000,"Spoilage",'FC inventory'!$B$2:$B1000,$A4,'FC inventory'!$A$2:$A1000,"<"&today()))+ (SUMIFS('FC inventory'!K$2:K1000,'FC inventory'!$C$2:$C1000,"In",'FC inventory'!$B$2:$B1000,$A4,'FC inventory'!$A$2:$A1000,Today()))-(SUMIFS('FC inventory'!K$2:K1000,'FC inventory'!$C$2:$C1000,"Out",'FC inventory'!$B$2:$B1000,$A4,'FC inventory'!$A$2:$A1000,Today()) - (SUMIFS('FC inventory'!K$2:K1000,'FC inventory'!$C$2:$C1000,"Retuned",'FC inventory'!$B$2:$B1000,$A4,'FC inventory'!$A$2:$A1000,Today()) - (SUMIFS('FC inventory'!K$2:K1000,'FC inventory'!$C$2:$C1000,"Spoilage",'FC inventory'!$B$2:$B1000,$A4,'FC inventory'!$A$2:$A1000,Today())))) -> 0 | ... AF4: =(SUMIFS('FC inventory'!AH$2:AH1000,'FC inventory'!$C$2:$C1000,"In",'FC inventory'!$B$2:$B1000,$A4,'FC inventory'!$A$2:$A1000,"<"&Today())-SUMIFS('FC inventory'!AH$2:AH1000,'FC inventory'!$C$2:$C1000,"Out",'FC inventory'!$B$2:$B1000,$A4,'FC inventory'!$A$2:$A1000,"<"&Today())+SUMIFS('FC inventory'!AH$2:AH1000,'FC inventory'!$C$2:$C1000,"Return",'FC inventory'!$B$2:$B1000,$A4,'FC inventory'!$A$2:$A1000,"<"&Today())-SUMIFS('FC inventory'!AH$2:AH1000,'FC inventory'!$C$2:$C1000,"Spoilage",'FC inventory'!$B$2:$B1000,$A4,'FC inventory'!$A$2:$A1000,"<"&today()))+ (SUMIFS('FC inventory'!AH$2:AH1000,'FC inventory'!$C$2:$C1000,"In",'FC inventory'!$B$2:$B1000,$A4,'FC inventory'!$A$2:$A1000,Today()))-(SUMIFS('FC inventory'!AH$2:AH1000,'FC inventory'!$C$2:$C1000,"Out",'FC inventory'!$B$2:$B1000,$A4,'FC inventory'!$A$2:$A1000,Today()) - (SUMIFS('FC inventory'!AH$2:AH1000,'FC inventory'!$C$2:$C1000,"Retuned",'FC inventory'!$B$2:$B1000,$A4,'FC inventory'!$A$2:$A1000,Today()) - (SUMIFS('FC inventory'!AH$2:AH1000,'FC inventory'!$C$2:$C1000,"Spoilage",'FC inventory'!$B$2:$B1000,$A4,'FC inventory'!$A$2:$A1000,Today())))) -> 0
A5: Felele | B5: =(SUMIFS('FC inventory'!D$2:D1000,'FC inventory'!$C$2:$C1000,"In",'FC inventory'!$B$2:$B1000,$A5,'FC inventory'!$A$2:$A1000,"<"&Today())-SUMIFS('FC inventory'!D$2:D1000,'FC inventory'!$C$2:$C1000,"Out",'FC inventory'!$B$2:$B1000,$A5,'FC inventory'!$A$2:$A1000,"<"&Today())+SUMIFS('FC inventory'!D$2:D1000,'FC inventory'!$C$2:$C1000,"Return",'FC inventory'!$B$2:$B1000,$A5,'FC inventory'!$A$2:$A1000,"<"&Today())-SUMIFS('FC inventory'!D$2:D1000,'FC inventory'!$C$2:$C1000,"Spoilage",'FC inventory'!$B$2:$B1000,$A5,'FC inventory'!$A$2:$A1000,"<"&today()))+ (SUMIFS('FC inventory'!D$2:D1000,'FC inventory'!$C$2:$C1000,"In",'FC inventory'!$B$2:$B1000,$A5,'FC inventory'!$A$2:$A1000,Today()))-(SUMIFS('FC inventory'!D$2:D1000,'FC inventory'!$C$2:$C1000,"Out",'FC inventory'!$B$2:$B1000,$A5,'FC inventory'!$A$2:$A1000,Today()) - (SUMIFS('FC inventory'!D$2:D1000,'FC inventory'!$C$2:$C1000,"Retuned",'FC inventory'!$B$2:$B1000,$A5,'FC inventory'!$A$2:$A1000,Today()) - (SUMIFS('FC inventory'!D$2:D1000,'FC inventory'!$C$2:$C1000,"Spoilage",'FC inventory'!$B$2:$B1000,$A5,'FC inventory'!$A$2:$A1000,Today())))) -> 0 | C5: =(SUMIFS('FC inventory'!E$2:E1000,'FC inventory'!$C$2:$C1000,"In",'FC inventory'!$B$2:$B1000,$A5,'FC inventory'!$A$2:$A1000,"<"&Today())-SUMIFS('FC inventory'!E$2:E1000,'FC inventory'!$C$2:$C1000,"Out",'FC inventory'!$B$2:$B1000,$A5,'FC inventory'!$A$2:$A1000,"<"&Today())+SUMIFS('FC inventory'!E$2:E1000,'FC inventory'!$C$2:$C1000,"Return",'FC inventory'!$B$2:$B1000,$A5,'FC inventory'!$A$2:$A1000,"<"&Today())-SUMIFS('FC inventory'!E$2:E1000,'FC inventory'!$C$2:$C1000,"Spoilage",'FC inventory'!$B$2:$B1000,$A5,'FC inventory'!$A$2:$A1000,"<"&today()))+ (SUMIFS('FC inventory'!E$2:E1000,'FC inventory'!$C$2:$C1000,"In",'FC inventory'!$B$2:$B1000,$A5,'FC inventory'!$A$2:$A1000,Today()))-(SUMIFS('FC inventory'!E$2:E1000,'FC inventory'!$C$2:$C1000,"Out",'FC inventory'!$B$2:$B1000,$A5,'FC inventory'!$A$2:$A1000,Today()) - (SUMIFS('FC inventory'!E$2:E1000,'FC inventory'!$C$2:$C1000,"Retuned",'FC inventory'!$B$2:$B1000,$A5,'FC inventory'!$A$2:$A1000,Today()) - (SUMIFS('FC inventory'!E$2:E1000,'FC inventory'!$C$2:$C1000,"Spoilage",'FC inventory'!$B$2:$B1000,$A5,'FC inventory'!$A$2:$A1000,Today())))) -> 0 | D5: =(SUMIFS('FC inventory'!F$2:F1000,'FC inventory'!$C$2:$C1000,"In",'FC inventory'!$B$2:$B1000,$A5,'FC inventory'!$A$2:$A1000,"<"&Today())-SUMIFS('FC inventory'!F$2:F1000,'FC inventory'!$C$2:$C1000,"Out",'FC inventory'!$B$2:$B1000,$A5,'FC inventory'!$A$2:$A1000,"<"&Today())+SUMIFS('FC inventory'!F$2:F1000,'FC inventory'!$C$2:$C1000,"Return",'FC inventory'!$B$2:$B1000,$A5,'FC inventory'!$A$2:$A1000,"<"&Today())-SUMIFS('FC inventory'!F$2:F1000,'FC inventory'!$C$2:$C1000,"Spoilage",'FC inventory'!$B$2:$B1000,$A5,'FC inventory'!$A$2:$A1000,"<"&today()))+ (SUMIFS('FC inventory'!F$2:F1000,'FC inventory'!$C$2:$C1000,"In",'FC inventory'!$B$2:$B1000,$A5,'FC inventory'!$A$2:$A1000,Today()))-(SUMIFS('FC inventory'!F$2:F1000,'FC inventory'!$C$2:$C1000,"Out",'FC inventory'!$B$2:$B1000,$A5,'FC inventory'!$A$2:$A1000,Today()) - (SUMIFS('FC inventory'!F$2:F1000,'FC inventory'!$C$2:$C1000,"Retuned",'FC inventory'!$B$2:$B1000,$A5,'FC inventory'!$A$2:$A1000,Today()) - (SUMIFS('FC inventory'!F$2:F1000,'FC inventory'!$C$2:$C1000,"Spoilage",'FC inventory'!$B$2:$B1000,$A5,'FC inventory'!$A$2:$A1000,Today())))) -> 0 | E5: =(SUMIFS('FC inventory'!G$2:G1000,'FC inventory'!$C$2:$C1000,"In",'FC inventory'!$B$2:$B1000,$A5,'FC inventory'!$A$2:$A1000,"<"&Today())-SUMIFS('FC inventory'!G$2:G1000,'FC inventory'!$C$2:$C1000,"Out",'FC inventory'!$B$2:$B1000,$A5,'FC inventory'!$A$2:$A1000,"<"&Today())+SUMIFS('FC inventory'!G$2:G1000,'FC inventory'!$C$2:$C1000,"Return",'FC inventory'!$B$2:$B1000,$A5,'FC inventory'!$A$2:$A1000,"<"&Today())-SUMIFS('FC inventory'!G$2:G1000,'FC inventory'!$C$2:$C1000,"Spoilage",'FC inventory'!$B$2:$B1000,$A5,'FC inventory'!$A$2:$A1000,"<"&today()))+ (SUMIFS('FC inventory'!G$2:G1000,'FC inventory'!$C$2:$C1000,"In",'FC inventory'!$B$2:$B1000,$A5,'FC inventory'!$A$2:$A1000,Today()))-(SUMIFS('FC inventory'!G$2:G1000,'FC inventory'!$C$2:$C1000,"Out",'FC inventory'!$B$2:$B1000,$A5,'FC inventory'!$A$2:$A1000,Today()) - (SUMIFS('FC inventory'!G$2:G1000,'FC inventory'!$C$2:$C1000,"Retuned",'FC inventory'!$B$2:$B1000,$A5,'FC inventory'!$A$2:$A1000,Today()) - (SUMIFS('FC inventory'!G$2:G1000,'FC inventory'!$C$2:$C1000,"Spoilage",'FC inventory'!$B$2:$B1000,$A5,'FC inventory'!$A$2:$A1000,Today())))) -> 0 | F5: =(SUMIFS('FC inventory'!H$2:H1000,'FC inventory'!$C$2:$C1000,"In",'FC inventory'!$B$2:$B1000,$A5,'FC inventory'!$A$2:$A1000,"<"&Today())-SUMIFS('FC inventory'!H$2:H1000,'FC inventory'!$C$2:$C1000,"Out",'FC inventory'!$B$2:$B1000,$A5,'FC inventory'!$A$2:$A1000,"<"&Today())+SUMIFS('FC inventory'!H$2:H1000,'FC inventory'!$C$2:$C1000,"Return",'FC inventory'!$B$2:$B1000,$A5,'FC inventory'!$A$2:$A1000,"<"&Today())-SUMIFS('FC inventory'!H$2:H1000,'FC inventory'!$C$2:$C1000,"Spoilage",'FC inventory'!$B$2:$B1000,$A5,'FC inventory'!$A$2:$A1000,"<"&today()))+ (SUMIFS('FC inventory'!H$2:H1000,'FC inventory'!$C$2:$C1000,"In",'FC inventory'!$B$2:$B1000,$A5,'FC inventory'!$A$2:$A1000,Today()))-(SUMIFS('FC inventory'!H$2:H1000,'FC inventory'!$C$2:$C1000,"Out",'FC inventory'!$B$2:$B1000,$A5,'FC inventory'!$A$2:$A1000,Today()) - (SUMIFS('FC inventory'!H$2:H1000,'FC inventory'!$C$2:$C1000,"Retuned",'FC inventory'!$B$2:$B1000,$A5,'FC inventory'!$A$2:$A1000,Today()) - (SUMIFS('FC inventory'!H$2:H1000,'FC inventory'!$C$2:$C1000,"Spoilage",'FC inventory'!$B$2:$B1000,$A5,'FC inventory'!$A$2:$A1000,Today())))) -> 0 | G5: =(SUMIFS('FC inventory'!I$2:I1000,'FC inventory'!$C$2:$C1000,"In",'FC inventory'!$B$2:$B1000,$A5,'FC inventory'!$A$2:$A1000,"<"&Today())-SUMIFS('FC inventory'!I$2:I1000,'FC inventory'!$C$2:$C1000,"Out",'FC inventory'!$B$2:$B1000,$A5,'FC inventory'!$A$2:$A1000,"<"&Today())+SUMIFS('FC inventory'!I$2:I1000,'FC inventory'!$C$2:$C1000,"Return",'FC inventory'!$B$2:$B1000,$A5,'FC inventory'!$A$2:$A1000,"<"&Today())-SUMIFS('FC inventory'!I$2:I1000,'FC inventory'!$C$2:$C1000,"Spoilage",'FC inventory'!$B$2:$B1000,$A5,'FC inventory'!$A$2:$A1000,"<"&today()))+ (SUMIFS('FC inventory'!I$2:I1000,'FC inventory'!$C$2:$C1000,"In",'FC inventory'!$B$2:$B1000,$A5,'FC inventory'!$A$2:$A1000,Today()))-(SUMIFS('FC inventory'!I$2:I1000,'FC inventory'!$C$2:$C1000,"Out",'FC inventory'!$B$2:$B1000,$A5,'FC inventory'!$A$2:$A1000,Today()) - (SUMIFS('FC inventory'!I$2:I1000,'FC inventory'!$C$2:$C1000,"Retuned",'FC inventory'!$B$2:$B1000,$A5,'FC inventory'!$A$2:$A1000,Today()) - (SUMIFS('FC inventory'!I$2:I1000,'FC inventory'!$C$2:$C1000,"Spoilage",'FC inventory'!$B$2:$B1000,$A5,'FC inventory'!$A$2:$A1000,Today())))) -> 26 | H5: =(SUMIFS('FC inventory'!J$2:J1000,'FC inventory'!$C$2:$C1000,"In",'FC inventory'!$B$2:$B1000,$A5,'FC inventory'!$A$2:$A1000,"<"&Today())-SUMIFS('FC inventory'!J$2:J1000,'FC inventory'!$C$2:$C1000,"Out",'FC inventory'!$B$2:$B1000,$A5,'FC inventory'!$A$2:$A1000,"<"&Today())+SUMIFS('FC inventory'!J$2:J1000,'FC inventory'!$C$2:$C1000,"Return",'FC inventory'!$B$2:$B1000,$A5,'FC inventory'!$A$2:$A1000,"<"&Today())-SUMIFS('FC inventory'!J$2:J1000,'FC inventory'!$C$2:$C1000,"Spoilage",'FC inventory'!$B$2:$B1000,$A5,'FC inventory'!$A$2:$A1000,"<"&today()))+ (SUMIFS('FC inventory'!J$2:J1000,'FC inventory'!$C$2:$C1000,"In",'FC inventory'!$B$2:$B1000,$A5,'FC inventory'!$A$2:$A1000,Today()))-(SUMIFS('FC inventory'!J$2:J1000,'FC inventory'!$C$2:$C1000,"Out",'FC inventory'!$B$2:$B1000,$A5,'FC inventory'!$A$2:$A1000,Today()) - (SUMIFS('FC inventory'!J$2:J1000,'FC inventory'!$C$2:$C1000,"Retuned",'FC inventory'!$B$2:$B1000,$A5,'FC inventory'!$A$2:$A1000,Today()) - (SUMIFS('FC inventory'!J$2:J1000,'FC inventory'!$C$2:$C1000,"Spoilage",'FC inventory'!$B$2:$B1000,$A5,'FC inventory'!$A$2:$A1000,Today())))) -> 0 | I5: =(SUMIFS('FC inventory'!K$2:K1000,'FC inventory'!$C$2:$C1000,"In",'FC inventory'!$B$2:$B1000,$A5,'FC inventory'!$A$2:$A1000,"<"&Today())-SUMIFS('FC inventory'!K$2:K1000,'FC inventory'!$C$2:$C1000,"Out",'FC inventory'!$B$2:$B1000,$A5,'FC inventory'!$A$2:$A1000,"<"&Today())+SUMIFS('FC inventory'!K$2:K1000,'FC inventory'!$C$2:$C1000,"Return",'FC inventory'!$B$2:$B1000,$A5,'FC inventory'!$A$2:$A1000,"<"&Today())-SUMIFS('FC inventory'!K$2:K1000,'FC inventory'!$C$2:$C1000,"Spoilage",'FC inventory'!$B$2:$B1000,$A5,'FC inventory'!$A$2:$A1000,"<"&today()))+ (SUMIFS('FC inventory'!K$2:K1000,'FC inventory'!$C$2:$C1000,"In",'FC inventory'!$B$2:$B1000,$A5,'FC inventory'!$A$2:$A1000,Today()))-(SUMIFS('FC inventory'!K$2:K1000,'FC inventory'!$C$2:$C1000,"Out",'FC inventory'!$B$2:$B1000,$A5,'FC inventory'!$A$2:$A1000,Today()) - (SUMIFS('FC inventory'!K$2:K1000,'FC inventory'!$C$2:$C1000,"Retuned",'FC inventory'!$B$2:$B1000,$A5,'FC inventory'!$A$2:$A1000,Today()) - (SUMIFS('FC inventory'!K$2:K1000,'FC inventory'!$C$2:$C1000,"Spoilage",'FC inventory'!$B$2:$B1000,$A5,'FC inventory'!$A$2:$A1000,Today())))) -> 0 | ... AF5: =(SUMIFS('FC inventory'!AH$2:AH1000,'FC inventory'!$C$2:$C1000,"In",'FC inventory'!$B$2:$B1000,$A5,'FC inventory'!$A$2:$A1000,"<"&Today())-SUMIFS('FC inventory'!AH$2:AH1000,'FC inventory'!$C$2:$C1000,"Out",'FC inventory'!$B$2:$B1000,$A5,'FC inventory'!$A$2:$A1000,"<"&Today())+SUMIFS('FC inventory'!AH$2:AH1000,'FC inventory'!$C$2:$C1000,"Return",'FC inventory'!$B$2:$B1000,$A5,'FC inventory'!$A$2:$A1000,"<"&Today())-SUMIFS('FC inventory'!AH$2:AH1000,'FC inventory'!$C$2:$C1000,"Spoilage",'FC inventory'!$B$2:$B1000,$A5,'FC inventory'!$A$2:$A1000,"<"&today()))+ (SUMIFS('FC inventory'!AH$2:AH1000,'FC inventory'!$C$2:$C1000,"In",'FC inventory'!$B$2:$B1000,$A5,'FC inventory'!$A$2:$A1000,Today()))-(SUMIFS('FC inventory'!AH$2:AH1000,'FC inventory'!$C$2:$C1000,"Out",'FC inventory'!$B$2:$B1000,$A5,'FC inventory'!$A$2:$A1000,Today()) - (SUMIFS('FC inventory'!AH$2:AH1000,'FC inventory'!$C$2:$C1000,"Retuned",'FC inventory'!$B$2:$B1000,$A5,'FC inventory'!$A$2:$A1000,Today()) - (SUMIFS('FC inventory'!AH$2:AH1000,'FC inventory'!$C$2:$C1000,"Spoilage",'FC inventory'!$B$2:$B1000,$A5,'FC inventory'!$A$2:$A1000,Today())))) -> 0
A6: Eleyele | B6: =(SUMIFS('FC inventory'!D$2:D1000,'FC inventory'!$C$2:$C1000,"In",'FC inventory'!$B$2:$B1000,$A6,'FC inventory'!$A$2:$A1000,"<"&Today())-SUMIFS('FC inventory'!D$2:D1000,'FC inventory'!$C$2:$C1000,"Out",'FC inventory'!$B$2:$B1000,$A6,'FC inventory'!$A$2:$A1000,"<"&Today())+SUMIFS('FC inventory'!D$2:D1000,'FC inventory'!$C$2:$C1000,"Return",'FC inventory'!$B$2:$B1000,$A6,'FC inventory'!$A$2:$A1000,"<"&Today())-SUMIFS('FC inventory'!D$2:D1000,'FC inventory'!$C$2:$C1000,"Spoilage",'FC inventory'!$B$2:$B1000,$A6,'FC inventory'!$A$2:$A1000,"<"&today()))+ (SUMIFS('FC inventory'!D$2:D1000,'FC inventory'!$C$2:$C1000,"In",'FC inventory'!$B$2:$B1000,$A6,'FC inventory'!$A$2:$A1000,Today()))-(SUMIFS('FC inventory'!D$2:D1000,'FC inventory'!$C$2:$C1000,"Out",'FC inventory'!$B$2:$B1000,$A6,'FC inventory'!$A$2:$A1000,Today()) - (SUMIFS('FC inventory'!D$2:D1000,'FC inventory'!$C$2:$C1000,"Retuned",'FC inventory'!$B$2:$B1000,$A6,'FC inventory'!$A$2:$A1000,Today()) - (SUMIFS('FC inventory'!D$2:D1000,'FC inventory'!$C$2:$C1000,"Spoilage",'FC inventory'!$B$2:$B1000,$A6,'FC inventory'!$A$2:$A1000,Today())))) -> 0 | C6: =(SUMIFS('FC inventory'!E$2:E1000,'FC inventory'!$C$2:$C1000,"In",'FC inventory'!$B$2:$B1000,$A6,'FC inventory'!$A$2:$A1000,"<"&Today())-SUMIFS('FC inventory'!E$2:E1000,'FC inventory'!$C$2:$C1000,"Out",'FC inventory'!$B$2:$B1000,$A6,'FC inventory'!$A$2:$A1000,"<"&Today())+SUMIFS('FC inventory'!E$2:E1000,'FC inventory'!$C$2:$C1000,"Return",'FC inventory'!$B$2:$B1000,$A6,'FC inventory'!$A$2:$A1000,"<"&Today())-SUMIFS('FC inventory'!E$2:E1000,'FC inventory'!$C$2:$C1000,"Spoilage",'FC inventory'!$B$2:$B1000,$A6,'FC inventory'!$A$2:$A1000,"<"&today()))+ (SUMIFS('FC inventory'!E$2:E1000,'FC inventory'!$C$2:$C1000,"In",'FC inventory'!$B$2:$B1000,$A6,'FC inventory'!$A$2:$A1000,Today()))-(SUMIFS('FC inventory'!E$2:E1000,'FC inventory'!$C$2:$C1000,"Out",'FC inventory'!$B$2:$B1000,$A6,'FC inventory'!$A$2:$A1000,Today()) - (SUMIFS('FC inventory'!E$2:E1000,'FC inventory'!$C$2:$C1000,"Retuned",'FC inventory'!$B$2:$B1000,$A6,'FC inventory'!$A$2:$A1000,Today()) - (SUMIFS('FC inventory'!E$2:E1000,'FC inventory'!$C$2:$C1000,"Spoilage",'FC inventory'!$B$2:$B1000,$A6,'FC inventory'!$A$2:$A1000,Today())))) -> 0 | D6: =(SUMIFS('FC inventory'!F$2:F1000,'FC inventory'!$C$2:$C1000,"In",'FC inventory'!$B$2:$B1000,$A6,'FC inventory'!$A$2:$A1000,"<"&Today())-SUMIFS('FC inventory'!F$2:F1000,'FC inventory'!$C$2:$C1000,"Out",'FC inventory'!$B$2:$B1000,$A6,'FC inventory'!$A$2:$A1000,"<"&Today())+SUMIFS('FC inventory'!F$2:F1000,'FC inventory'!$C$2:$C1000,"Return",'FC inventory'!$B$2:$B1000,$A6,'FC inventory'!$A$2:$A1000,"<"&Today())-SUMIFS('FC inventory'!F$2:F1000,'FC inventory'!$C$2:$C1000,"Spoilage",'FC inventory'!$B$2:$B1000,$A6,'FC inventory'!$A$2:$A1000,"<"&today()))+ (SUMIFS('FC inventory'!F$2:F1000,'FC inventory'!$C$2:$C1000,"In",'FC inventory'!$B$2:$B1000,$A6,'FC inventory'!$A$2:$A1000,Today()))-(SUMIFS('FC inventory'!F$2:F1000,'FC inventory'!$C$2:$C1000,"Out",'FC inventory'!$B$2:$B1000,$A6,'FC inventory'!$A$2:$A1000,Today()) - (SUMIFS('FC inventory'!F$2:F1000,'FC inventory'!$C$2:$C1000,"Retuned",'FC inventory'!$B$2:$B1000,$A6,'FC inventory'!$A$2:$A1000,Today()) - (SUMIFS('FC inventory'!F$2:F1000,'FC inventory'!$C$2:$C1000,"Spoilage",'FC inventory'!$B$2:$B1000,$A6,'FC inventory'!$A$2:$A1000,Today())))) -> 0 | E6: =(SUMIFS('FC inventory'!G$2:G1000,'FC inventory'!$C$2:$C1000,"In",'FC inventory'!$B$2:$B1000,$A6,'FC inventory'!$A$2:$A1000,"<"&Today())-SUMIFS('FC inventory'!G$2:G1000,'FC inventory'!$C$2:$C1000,"Out",'FC inventory'!$B$2:$B1000,$A6,'FC inventory'!$A$2:$A1000,"<"&Today())+SUMIFS('FC inventory'!G$2:G1000,'FC inventory'!$C$2:$C1000,"Return",'FC inventory'!$B$2:$B1000,$A6,'FC inventory'!$A$2:$A1000,"<"&Today())-SUMIFS('FC inventory'!G$2:G1000,'FC inventory'!$C$2:$C1000,"Spoilage",'FC inventory'!$B$2:$B1000,$A6,'FC inventory'!$A$2:$A1000,"<"&today()))+ (SUMIFS('FC inventory'!G$2:G1000,'FC inventory'!$C$2:$C1000,"In",'FC inventory'!$B$2:$B1000,$A6,'FC inventory'!$A$2:$A1000,Today()))-(SUMIFS('FC inventory'!G$2:G1000,'FC inventory'!$C$2:$C1000,"Out",'FC inventory'!$B$2:$B1000,$A6,'FC inventory'!$A$2:$A1000,Today()) - (SUMIFS('FC inventory'!G$2:G1000,'FC inventory'!$C$2:$C1000,"Retuned",'FC inventory'!$B$2:$B1000,$A6,'FC inventory'!$A$2:$A1000,Today()) - (SUMIFS('FC inventory'!G$2:G1000,'FC inventory'!$C$2:$C1000,"Spoilage",'FC inventory'!$B$2:$B1000,$A6,'FC inventory'!$A$2:$A1000,Today())))) -> 0 | F6: =(SUMIFS('FC inventory'!H$2:H1000,'FC inventory'!$C$2:$C1000,"In",'FC inventory'!$B$2:$B1000,$A6,'FC inventory'!$A$2:$A1000,"<"&Today())-SUMIFS('FC inventory'!H$2:H1000,'FC inventory'!$C$2:$C1000,"Out",'FC inventory'!$B$2:$B1000,$A6,'FC inventory'!$A$2:$A1000,"<"&Today())+SUMIFS('FC inventory'!H$2:H1000,'FC inventory'!$C$2:$C1000,"Return",'FC inventory'!$B$2:$B1000,$A6,'FC inventory'!$A$2:$A1000,"<"&Today())-SUMIFS('FC inventory'!H$2:H1000,'FC inventory'!$C$2:$C1000,"Spoilage",'FC inventory'!$B$2:$B1000,$A6,'FC inventory'!$A$2:$A1000,"<"&today()))+ (SUMIFS('FC inventory'!H$2:H1000,'FC inventory'!$C$2:$C1000,"In",'FC inventory'!$B$2:$B1000,$A6,'FC inventory'!$A$2:$A1000,Today()))-(SUMIFS('FC inventory'!H$2:H1000,'FC inventory'!$C$2:$C1000,"Out",'FC inventory'!$B$2:$B1000,$A6,'FC inventory'!$A$2:$A1000,Today()) - (SUMIFS('FC inventory'!H$2:H1000,'FC inventory'!$C$2:$C1000,"Retuned",'FC inventory'!$B$2:$B1000,$A6,'FC inventory'!$A$2:$A1000,Today()) - (SUMIFS('FC inventory'!H$2:H1000,'FC inventory'!$C$2:$C1000,"Spoilage",'FC inventory'!$B$2:$B1000,$A6,'FC inventory'!$A$2:$A1000,Today())))) -> 0 | G6: =(SUMIFS('FC inventory'!I$2:I1000,'FC inventory'!$C$2:$C1000,"In",'FC inventory'!$B$2:$B1000,$A6,'FC inventory'!$A$2:$A1000,"<"&Today())-SUMIFS('FC inventory'!I$2:I1000,'FC inventory'!$C$2:$C1000,"Out",'FC inventory'!$B$2:$B1000,$A6,'FC inventory'!$A$2:$A1000,"<"&Today())+SUMIFS('FC inventory'!I$2:I1000,'FC inventory'!$C$2:$C1000,"Return",'FC inventory'!$B$2:$B1000,$A6,'FC inventory'!$A$2:$A1000,"<"&Today())-SUMIFS('FC inventory'!I$2:I1000,'FC inventory'!$C$2:$C1000,"Spoilage",'FC inventory'!$B$2:$B1000,$A6,'FC inventory'!$A$2:$A1000,"<"&today()))+ (SUMIFS('FC inventory'!I$2:I1000,'FC inventory'!$C$2:$C1000,"In",'FC inventory'!$B$2:$B1000,$A6,'FC inventory'!$A$2:$A1000,Today()))-(SUMIFS('FC inventory'!I$2:I1000,'FC inventory'!$C$2:$C1000,"Out",'FC inventory'!$B$2:$B1000,$A6,'FC inventory'!$A$2:$A1000,Today()) - (SUMIFS('FC inventory'!I$2:I1000,'FC inventory'!$C$2:$C1000,"Retuned",'FC inventory'!$B$2:$B1000,$A6,'FC inventory'!$A$2:$A1000,Today()) - (SUMIFS('FC inventory'!I$2:I1000,'FC inventory'!$C$2:$C1000,"Spoilage",'FC inventory'!$B$2:$B1000,$A6,'FC inventory'!$A$2:$A1000,Today())))) -> 0 | H6: =(SUMIFS('FC inventory'!J$2:J1000,'FC inventory'!$C$2:$C1000,"In",'FC inventory'!$B$2:$B1000,$A6,'FC inventory'!$A$2:$A1000,"<"&Today())-SUMIFS('FC inventory'!J$2:J1000,'FC inventory'!$C$2:$C1000,"Out",'FC inventory'!$B$2:$B1000,$A6,'FC inventory'!$A$2:$A1000,"<"&Today())+SUMIFS('FC inventory'!J$2:J1000,'FC inventory'!$C$2:$C1000,"Return",'FC inventory'!$B$2:$B1000,$A6,'FC inventory'!$A$2:$A1000,"<"&Today())-SUMIFS('FC inventory'!J$2:J1000,'FC inventory'!$C$2:$C1000,"Spoilage",'FC inventory'!$B$2:$B1000,$A6,'FC inventory'!$A$2:$A1000,"<"&today()))+ (SUMIFS('FC inventory'!J$2:J1000,'FC inventory'!$C$2:$C1000,"In",'FC inventory'!$B$2:$B1000,$A6,'FC inventory'!$A$2:$A1000,Today()))-(SUMIFS('FC inventory'!J$2:J1000,'FC inventory'!$C$2:$C1000,"Out",'FC inventory'!$B$2:$B1000,$A6,'FC inventory'!$A$2:$A1000,Today()) - (SUMIFS('FC inventory'!J$2:J1000,'FC inventory'!$C$2:$C1000,"Retuned",'FC inventory'!$B$2:$B1000,$A6,'FC inventory'!$A$2:$A1000,Today()) - (SUMIFS('FC inventory'!J$2:J1000,'FC inventory'!$C$2:$C1000,"Spoilage",'FC inventory'!$B$2:$B1000,$A6,'FC inventory'!$A$2:$A1000,Today())))) -> 0 | I6: =(SUMIFS('FC inventory'!K$2:K1000,'FC inventory'!$C$2:$C1000,"In",'FC inventory'!$B$2:$B1000,$A6,'FC inventory'!$A$2:$A1000,"<"&Today())-SUMIFS('FC inventory'!K$2:K1000,'FC inventory'!$C$2:$C1000,"Out",'FC inventory'!$B$2:$B1000,$A6,'FC inventory'!$A$2:$A1000,"<"&Today())+SUMIFS('FC inventory'!K$2:K1000,'FC inventory'!$C$2:$C1000,"Return",'FC inventory'!$B$2:$B1000,$A6,'FC inventory'!$A$2:$A1000,"<"&Today())-SUMIFS('FC inventory'!K$2:K1000,'FC inventory'!$C$2:$C1000,"Spoilage",'FC inventory'!$B$2:$B1000,$A6,'FC inventory'!$A$2:$A1000,"<"&today()))+ (SUMIFS('FC inventory'!K$2:K1000,'FC inventory'!$C$2:$C1000,"In",'FC inventory'!$B$2:$B1000,$A6,'FC inventory'!$A$2:$A1000,Today()))-(SUMIFS('FC inventory'!K$2:K1000,'FC inventory'!$C$2:$C1000,"Out",'FC inventory'!$B$2:$B1000,$A6,'FC inventory'!$A$2:$A1000,Today()) - (SUMIFS('FC inventory'!K$2:K1000,'FC inventory'!$C$2:$C1000,"Retuned",'FC inventory'!$B$2:$B1000,$A6,'FC inventory'!$A$2:$A1000,Today()) - (SUMIFS('FC inventory'!K$2:K1000,'FC inventory'!$C$2:$C1000,"Spoilage",'FC inventory'!$B$2:$B1000,$A6,'FC inventory'!$A$2:$A1000,Today())))) -> 0 | ... AF6: =(SUMIFS('FC inventory'!AH$2:AH1000,'FC inventory'!$C$2:$C1000,"In",'FC inventory'!$B$2:$B1000,$A6,'FC inventory'!$A$2:$A1000,"<"&Today())-SUMIFS('FC inventory'!AH$2:AH1000,'FC inventory'!$C$2:$C1000,"Out",'FC inventory'!$B$2:$B1000,$A6,'FC inventory'!$A$2:$A1000,"<"&Today())+SUMIFS('FC inventory'!AH$2:AH1000,'FC inventory'!$C$2:$C1000,"Return",'FC inventory'!$B$2:$B1000,$A6,'FC inventory'!$A$2:$A1000,"<"&Today())-SUMIFS('FC inventory'!AH$2:AH1000,'FC inventory'!$C$2:$C1000,"Spoilage",'FC inventory'!$B$2:$B1000,$A6,'FC inventory'!$A$2:$A1000,"<"&today()))+ (SUMIFS('FC inventory'!AH$2:AH1000,'FC inventory'!$C$2:$C1000,"In",'FC inventory'!$B$2:$B1000,$A6,'FC inventory'!$A$2:$A1000,Today()))-(SUMIFS('FC inventory'!AH$2:AH1000,'FC inventory'!$C$2:$C1000,"Out",'FC inventory'!$B$2:$B1000,$A6,'FC inventory'!$A$2:$A1000,Today()) - (SUMIFS('FC inventory'!AH$2:AH1000,'FC inventory'!$C$2:$C1000,"Retuned",'FC inventory'!$B$2:$B1000,$A6,'FC inventory'!$A$2:$A1000,Today()) - (SUMIFS('FC inventory'!AH$2:AH1000,'FC inventory'!$C$2:$C1000,"Spoilage",'FC inventory'!$B$2:$B1000,$A6,'FC inventory'!$A$2:$A1000,Today())))) -> 0
A7: Apata | B7: =(SUMIFS('FC inventory'!D$2:D1000,'FC inventory'!$C$2:$C1000,"In",'FC inventory'!$B$2:$B1000,$A7,'FC inventory'!$A$2:$A1000,"<"&Today())-SUMIFS('FC inventory'!D$2:D1000,'FC inventory'!$C$2:$C1000,"Out",'FC inventory'!$B$2:$B1000,$A7,'FC inventory'!$A$2:$A1000,"<"&Today())+SUMIFS('FC inventory'!D$2:D1000,'FC inventory'!$C$2:$C1000,"Return",'FC inventory'!$B$2:$B1000,$A7,'FC inventory'!$A$2:$A1000,"<"&Today())-SUMIFS('FC inventory'!D$2:D1000,'FC inventory'!$C$2:$C1000,"Spoilage",'FC inventory'!$B$2:$B1000,$A7,'FC inventory'!$A$2:$A1000,"<"&today()))+ (SUMIFS('FC inventory'!D$2:D1000,'FC inventory'!$C$2:$C1000,"In",'FC inventory'!$B$2:$B1000,$A7,'FC inventory'!$A$2:$A1000,Today()))-(SUMIFS('FC inventory'!D$2:D1000,'FC inventory'!$C$2:$C1000,"Out",'FC inventory'!$B$2:$B1000,$A7,'FC inventory'!$A$2:$A1000,Today()) - (SUMIFS('FC inventory'!D$2:D1000,'FC inventory'!$C$2:$C1000,"Retuned",'FC inventory'!$B$2:$B1000,$A7,'FC inventory'!$A$2:$A1000,Today()) - (SUMIFS('FC inventory'!D$2:D1000,'FC inventory'!$C$2:$C1000,"Spoilage",'FC inventory'!$B$2:$B1000,$A7,'FC inventory'!$A$2:$A1000,Today())))) -> 6 | C7: =(SUMIFS('FC inventory'!E$2:E1000,'FC inventory'!$C$2:$C1000,"In",'FC inventory'!$B$2:$B1000,$A7,'FC inventory'!$A$2:$A1000,"<"&Today())-SUMIFS('FC inventory'!E$2:E1000,'FC inventory'!$C$2:$C1000,"Out",'FC inventory'!$B$2:$B1000,$A7,'FC inventory'!$A$2:$A1000,"<"&Today())+SUMIFS('FC inventory'!E$2:E1000,'FC inventory'!$C$2:$C1000,"Return",'FC inventory'!$B$2:$B1000,$A7,'FC inventory'!$A$2:$A1000,"<"&Today())-SUMIFS('FC inventory'!E$2:E1000,'FC inventory'!$C$2:$C1000,"Spoilage",'FC inventory'!$B$2:$B1000,$A7,'FC inventory'!$A$2:$A1000,"<"&today()))+ (SUMIFS('FC inventory'!E$2:E1000,'FC inventory'!$C$2:$C1000,"In",'FC inventory'!$B$2:$B1000,$A7,'FC inventory'!$A$2:$A1000,Today()))-(SUMIFS('FC inventory'!E$2:E1000,'FC inventory'!$C$2:$C1000,"Out",'FC inventory'!$B$2:$B1000,$A7,'FC inventory'!$A$2:$A1000,Today()) - (SUMIFS('FC inventory'!E$2:E1000,'FC inventory'!$C$2:$C1000,"Retuned",'FC inventory'!$B$2:$B1000,$A7,'FC inventory'!$A$2:$A1000,Today()) - (SUMIFS('FC inventory'!E$2:E1000,'FC inventory'!$C$2:$C1000,"Spoilage",'FC inventory'!$B$2:$B1000,$A7,'FC inventory'!$A$2:$A1000,Today())))) -> 0 | D7: =(SUMIFS('FC inventory'!F$2:F1000,'FC inventory'!$C$2:$C1000,"In",'FC inventory'!$B$2:$B1000,$A7,'FC inventory'!$A$2:$A1000,"<"&Today())-SUMIFS('FC inventory'!F$2:F1000,'FC inventory'!$C$2:$C1000,"Out",'FC inventory'!$B$2:$B1000,$A7,'FC inventory'!$A$2:$A1000,"<"&Today())+SUMIFS('FC inventory'!F$2:F1000,'FC inventory'!$C$2:$C1000,"Return",'FC inventory'!$B$2:$B1000,$A7,'FC inventory'!$A$2:$A1000,"<"&Today())-SUMIFS('FC inventory'!F$2:F1000,'FC inventory'!$C$2:$C1000,"Spoilage",'FC inventory'!$B$2:$B1000,$A7,'FC inventory'!$A$2:$A1000,"<"&today()))+ (SUMIFS('FC inventory'!F$2:F1000,'FC inventory'!$C$2:$C1000,"In",'FC inventory'!$B$2:$B1000,$A7,'FC inventory'!$A$2:$A1000,Today()))-(SUMIFS('FC inventory'!F$2:F1000,'FC inventory'!$C$2:$C1000,"Out",'FC inventory'!$B$2:$B1000,$A7,'FC inventory'!$A$2:$A1000,Today()) - (SUMIFS('FC inventory'!F$2:F1000,'FC inventory'!$C$2:$C1000,"Retuned",'FC inventory'!$B$2:$B1000,$A7,'FC inventory'!$A$2:$A1000,Today()) - (SUMIFS('FC inventory'!F$2:F1000,'FC inventory'!$C$2:$C1000,"Spoilage",'FC inventory'!$B$2:$B1000,$A7,'FC inventory'!$A$2:$A1000,Today())))) -> 1 | E7: =(SUMIFS('FC inventory'!G$2:G1000,'FC inventory'!$C$2:$C1000,"In",'FC inventory'!$B$2:$B1000,$A7,'FC inventory'!$A$2:$A1000,"<"&Today())-SUMIFS('FC inventory'!G$2:G1000,'FC inventory'!$C$2:$C1000,"Out",'FC inventory'!$B$2:$B1000,$A7,'FC inventory'!$A$2:$A1000,"<"&Today())+SUMIFS('FC inventory'!G$2:G1000,'FC inventory'!$C$2:$C1000,"Return",'FC inventory'!$B$2:$B1000,$A7,'FC inventory'!$A$2:$A1000,"<"&Today())-SUMIFS('FC inventory'!G$2:G1000,'FC inventory'!$C$2:$C1000,"Spoilage",'FC inventory'!$B$2:$B1000,$A7,'FC inventory'!$A$2:$A1000,"<"&today()))+ (SUMIFS('FC inventory'!G$2:G1000,'FC inventory'!$C$2:$C1000,"In",'FC inventory'!$B$2:$B1000,$A7,'FC inventory'!$A$2:$A1000,Today()))-(SUMIFS('FC inventory'!G$2:G1000,'FC inventory'!$C$2:$C1000,"Out",'FC inventory'!$B$2:$B1000,$A7,'FC inventory'!$A$2:$A1000,Today()) - (SUMIFS('FC inventory'!G$2:G1000,'FC inventory'!$C$2:$C1000,"Retuned",'FC inventory'!$B$2:$B1000,$A7,'FC inventory'!$A$2:$A1000,Today()) - (SUMIFS('FC inventory'!G$2:G1000,'FC inventory'!$C$2:$C1000,"Spoilage",'FC inventory'!$B$2:$B1000,$A7,'FC inventory'!$A$2:$A1000,Today())))) -> 3 | F7: =(SUMIFS('FC inventory'!H$2:H1000,'FC inventory'!$C$2:$C1000,"In",'FC inventory'!$B$2:$B1000,$A7,'FC inventory'!$A$2:$A1000,"<"&Today())-SUMIFS('FC inventory'!H$2:H1000,'FC inventory'!$C$2:$C1000,"Out",'FC inventory'!$B$2:$B1000,$A7,'FC inventory'!$A$2:$A1000,"<"&Today())+SUMIFS('FC inventory'!H$2:H1000,'FC inventory'!$C$2:$C1000,"Return",'FC inventory'!$B$2:$B1000,$A7,'FC inventory'!$A$2:$A1000,"<"&Today())-SUMIFS('FC inventory'!H$2:H1000,'FC inventory'!$C$2:$C1000,"Spoilage",'FC inventory'!$B$2:$B1000,$A7,'FC inventory'!$A$2:$A1000,"<"&today()))+ (SUMIFS('FC inventory'!H$2:H1000,'FC inventory'!$C$2:$C1000,"In",'FC inventory'!$B$2:$B1000,$A7,'FC inventory'!$A$2:$A1000,Today()))-(SUMIFS('FC inventory'!H$2:H1000,'FC inventory'!$C$2:$C1000,"Out",'FC inventory'!$B$2:$B1000,$A7,'FC inventory'!$A$2:$A1000,Today()) - (SUMIFS('FC inventory'!H$2:H1000,'FC inventory'!$C$2:$C1000,"Retuned",'FC inventory'!$B$2:$B1000,$A7,'FC inventory'!$A$2:$A1000,Today()) - (SUMIFS('FC inventory'!H$2:H1000,'FC inventory'!$C$2:$C1000,"Spoilage",'FC inventory'!$B$2:$B1000,$A7,'FC inventory'!$A$2:$A1000,Today())))) -> 0 | G7: =(SUMIFS('FC inventory'!I$2:I1000,'FC inventory'!$C$2:$C1000,"In",'FC inventory'!$B$2:$B1000,$A7,'FC inventory'!$A$2:$A1000,"<"&Today())-SUMIFS('FC inventory'!I$2:I1000,'FC inventory'!$C$2:$C1000,"Out",'FC inventory'!$B$2:$B1000,$A7,'FC inventory'!$A$2:$A1000,"<"&Today())+SUMIFS('FC inventory'!I$2:I1000,'FC inventory'!$C$2:$C1000,"Return",'FC inventory'!$B$2:$B1000,$A7,'FC inventory'!$A$2:$A1000,"<"&Today())-SUMIFS('FC inventory'!I$2:I1000,'FC inventory'!$C$2:$C1000,"Spoilage",'FC inventory'!$B$2:$B1000,$A7,'FC inventory'!$A$2:$A1000,"<"&today()))+ (SUMIFS('FC inventory'!I$2:I1000,'FC inventory'!$C$2:$C1000,"In",'FC inventory'!$B$2:$B1000,$A7,'FC inventory'!$A$2:$A1000,Today()))-(SUMIFS('FC inventory'!I$2:I1000,'FC inventory'!$C$2:$C1000,"Out",'FC inventory'!$B$2:$B1000,$A7,'FC inventory'!$A$2:$A1000,Today()) - (SUMIFS('FC inventory'!I$2:I1000,'FC inventory'!$C$2:$C1000,"Retuned",'FC inventory'!$B$2:$B1000,$A7,'FC inventory'!$A$2:$A1000,Today()) - (SUMIFS('FC inventory'!I$2:I1000,'FC inventory'!$C$2:$C1000,"Spoilage",'FC inventory'!$B$2:$B1000,$A7,'FC inventory'!$A$2:$A1000,Today())))) -> 56 | H7: =(SUMIFS('FC inventory'!J$2:J1000,'FC inventory'!$C$2:$C1000,"In",'FC inventory'!$B$2:$B1000,$A7,'FC inventory'!$A$2:$A1000,"<"&Today())-SUMIFS('FC inventory'!J$2:J1000,'FC inventory'!$C$2:$C1000,"Out",'FC inventory'!$B$2:$B1000,$A7,'FC inventory'!$A$2:$A1000,"<"&Today())+SUMIFS('FC inventory'!J$2:J1000,'FC inventory'!$C$2:$C1000,"Return",'FC inventory'!$B$2:$B1000,$A7,'FC inventory'!$A$2:$A1000,"<"&Today())-SUMIFS('FC inventory'!J$2:J1000,'FC inventory'!$C$2:$C1000,"Spoilage",'FC inventory'!$B$2:$B1000,$A7,'FC inventory'!$A$2:$A1000,"<"&today()))+ (SUMIFS('FC inventory'!J$2:J1000,'FC inventory'!$C$2:$C1000,"In",'FC inventory'!$B$2:$B1000,$A7,'FC inventory'!$A$2:$A1000,Today()))-(SUMIFS('FC inventory'!J$2:J1000,'FC inventory'!$C$2:$C1000,"Out",'FC inventory'!$B$2:$B1000,$A7,'FC inventory'!$A$2:$A1000,Today()) - (SUMIFS('FC inventory'!J$2:J1000,'FC inventory'!$C$2:$C1000,"Retuned",'FC inventory'!$B$2:$B1000,$A7,'FC inventory'!$A$2:$A1000,Today()) - (SUMIFS('FC inventory'!J$2:J1000,'FC inventory'!$C$2:$C1000,"Spoilage",'FC inventory'!$B$2:$B1000,$A7,'FC inventory'!$A$2:$A1000,Today())))) -> 0 | I7: =(SUMIFS('FC inventory'!K$2:K1000,'FC inventory'!$C$2:$C1000,"In",'FC inventory'!$B$2:$B1000,$A7,'FC inventory'!$A$2:$A1000,"<"&Today())-SUMIFS('FC inventory'!K$2:K1000,'FC inventory'!$C$2:$C1000,"Out",'FC inventory'!$B$2:$B1000,$A7,'FC inventory'!$A$2:$A1000,"<"&Today())+SUMIFS('FC inventory'!K$2:K1000,'FC inventory'!$C$2:$C1000,"Return",'FC inventory'!$B$2:$B1000,$A7,'FC inventory'!$A$2:$A1000,"<"&Today())-SUMIFS('FC inventory'!K$2:K1000,'FC inventory'!$C$2:$C1000,"Spoilage",'FC inventory'!$B$2:$B1000,$A7,'FC inventory'!$A$2:$A1000,"<"&today()))+ (SUMIFS('FC inventory'!K$2:K1000,'FC inventory'!$C$2:$C1000,"In",'FC inventory'!$B$2:$B1000,$A7,'FC inventory'!$A$2:$A1000,Today()))-(SUMIFS('FC inventory'!K$2:K1000,'FC inventory'!$C$2:$C1000,"Out",'FC inventory'!$B$2:$B1000,$A7,'FC inventory'!$A$2:$A1000,Today()) - (SUMIFS('FC inventory'!K$2:K1000,'FC inventory'!$C$2:$C1000,"Retuned",'FC inventory'!$B$2:$B1000,$A7,'FC inventory'!$A$2:$A1000,Today()) - (SUMIFS('FC inventory'!K$2:K1000,'FC inventory'!$C$2:$C1000,"Spoilage",'FC inventory'!$B$2:$B1000,$A7,'FC inventory'!$A$2:$A1000,Today())))) -> 0 | ... AF7: =(SUMIFS('FC inventory'!AH$2:AH1000,'FC inventory'!$C$2:$C1000,"In",'FC inventory'!$B$2:$B1000,$A7,'FC inventory'!$A$2:$A1000,"<"&Today())-SUMIFS('FC inventory'!AH$2:AH1000,'FC inventory'!$C$2:$C1000,"Out",'FC inventory'!$B$2:$B1000,$A7,'FC inventory'!$A$2:$A1000,"<"&Today())+SUMIFS('FC inventory'!AH$2:AH1000,'FC inventory'!$C$2:$C1000,"Return",'FC inventory'!$B$2:$B1000,$A7,'FC inventory'!$A$2:$A1000,"<"&Today())-SUMIFS('FC inventory'!AH$2:AH1000,'FC inventory'!$C$2:$C1000,"Spoilage",'FC inventory'!$B$2:$B1000,$A7,'FC inventory'!$A$2:$A1000,"<"&today()))+ (SUMIFS('FC inventory'!AH$2:AH1000,'FC inventory'!$C$2:$C1000,"In",'FC inventory'!$B$2:$B1000,$A7,'FC inventory'!$A$2:$A1000,Today()))-(SUMIFS('FC inventory'!AH$2:AH1000,'FC inventory'!$C$2:$C1000,"Out",'FC inventory'!$B$2:$B1000,$A7,'FC inventory'!$A$2:$A1000,Today()) - (SUMIFS('FC inventory'!AH$2:AH1000,'FC inventory'!$C$2:$C1000,"Retuned",'FC inventory'!$B$2:$B1000,$A7,'FC inventory'!$A$2:$A1000,Today()) - (SUMIFS('FC inventory'!AH$2:AH1000,'FC inventory'!$C$2:$C1000,"Spoilage",'FC inventory'!$B$2:$B1000,$A7,'FC inventory'!$A$2:$A1000,Today())))) -> 0
A8: TOTAL | B8: =SUM(B2:B7) -> 4 | C8: =SUM(C2:C7) -> 3 | D8: =SUM(D2:D7) -> 2 | E8: =SUM(E2:E7) -> 2 | F8: =SUM(F2:F7) -> 0 | G8: =SUM(G2:G7) -> 184 | H8: =SUM(H2:H7) -> 0 | I8: =SUM(I2:I7) -> 0 | ... AF8: =SUM(AF2:AF7) -> 0
A9: PRICE PER SKU | B9: ='Daily sales'!$C2 | C9: ='Daily sales'!$C3 | D9: ='Daily sales'!$C4 | E9: ='Daily sales'!$C5 | F9: ='Daily sales'!$C6 | G9: ='Daily sales'!$C7 | H9: ='Daily sales'!$C8 | I9: ='Daily sales'!$C9 | J9: ='Daily sales'!$C10 | K9: ='Daily sales'!$C11 | L9: ='Daily sales'!$C12 | M9: ='Daily sales'!$C13 | N9: ='Daily sales'!$C14 | O9: ='Daily sales'!$C15 | P9: ='Daily sales'!$C16 | Q9: ='Daily sales'!$C17 | R9: ='Daily sales'!$C18 | S9: ='Daily sales'!$C19 | T9: ='Daily sales'!$C20 | U9: ='Daily sales'!$C21 | V9: ='Daily sales'!$C22 | W9: ='Daily sales'!$C23 | X9: ='Daily sales'!$C24 | Y9: ='Daily sales'!$C25 | Z9: ='Daily sales'!$C26 | AA9: ='Daily sales'!$C27 | AB9: ='Daily sales'!$C28 | AC9: ='Daily sales'!$C29 | AD9: ='Daily sales'!$C30 | AE9: ='Daily sales'!$C31 | AF9: ='Daily sales'!$C32
A10: TOTAL COST PER SKU | B10: =B9*B8 -> 0 | C10: =C9*C8 -> 0 | D10: =D9*D8 -> 0 | E10: =E9*E8 -> 0 | F10: =F9*F8 -> 0 | G10: =G9*G8 -> 0 | H10: =H9*H8 -> 0 | I10: =I9*I8 -> 0 | ... AF10: =AF9*AF8 -> 0
A11: SUM TOTAL OF STOCK LEFT | B11: =SUM(B10:AF10) -> 0

Sheet Total Sales
A1: =IFERROR(__xludf.DUMMYFUNCTION("IMPORTRANGE(""https://docs.google.com/spreadsheets/d/1Lf9s7nk0Dnc6-C4BZ2nQSf_Pa6iyo3cNO7WJlMPJFhY/edit#gid=114137067"",""Total Sales!A1:AA150"")"),45889.0) -> 45889 | B1: =IFERROR(__xludf.DUMMYFUNCTION("""COMPUTED_VALUE"""),"Token Agemawo") -> Token Agemawo | C1: =IFERROR(__xludf.DUMMYFUNCTION("""COMPUTED_VALUE"""),"Token Boneless") -> Token Boneless | D1: =IFERROR(__xludf.DUMMYFUNCTION("""COMPUTED_VALUE"""),"Token Cow H&N") -> Token Cow H&N | E1: =IFERROR(__xludf.DUMMYFUNCTION("""COMPUTED_VALUE"""),"Token Cow Hump") -> Token Cow Hump | F1: =IFERROR(__xludf.DUMMYFUNCTION("""COMPUTED_VALUE"""),"Token Cow Tail") -> Token Cow Tail | G1: =IFERROR(__xludf.DUMMYFUNCTION("""COMPUTED_VALUE"""),"Token Ponmo") -> Token Ponmo | H1: =IFERROR(__xludf.DUMMYFUNCTION("""COMPUTED_VALUE"""),"Token Cow Asso.") -> Token Cow Asso. | I1: =IFERROR(__xludf.DUMMYFUNCTION("""COMPUTED_VALUE"""),"Token Minced Meat") -> Token Minced Meat | J1: =IFERROR(__xludf.DUMMYFUNCTION("""COMPUTED_VALUE"""),"Token Cow leg") -> Token Cow leg | K1: =IFERROR(__xludf.DUMMYFUNCTION("""COMPUTED_VALUE"""),"Token Goat Head and Leg") -> Token Goat Head and Leg | L1: =IFERROR(__xludf.DUMMYFUNCTION("""COMPUTED_VALUE"""),"Token Goat Assort.") -> Token Goat Assort. | M1: =IFERROR(__xludf.DUMMYFUNCTION("""COMPUTED_VALUE"""),"Token Chicken") -> Token Chicken | N1: =IFERROR(__xludf.DUMMYFUNCTION("""COMPUTED_VALUE"""),"Token Gizzard") -> Token Gizzard | O1: =IFERROR(__xludf.DUMMYFUNCTION("""COMPUTED_VALUE"""),"Token Hake") -> Token Hake | P1: =IFERROR(__xludf.DUMMYFUNCTION("""COMPUTED_VALUE"""),"Token Titus") -> Token Titus | Q1: =IFERROR(__xludf.DUMMYFUNCTION("""COMPUTED_VALUE"""),"Value Cow Assorted") -> Value Cow Assorted | R1: =IFERROR(__xludf.DUMMYFUNCTION("""COMPUTED_VALUE"""),"KG Agemawo") -> KG Agemawo | S1: =IFERROR(__xludf.DUMMYFUNCTION("""COMPUTED_VALUE"""),"KG Boneless") -> KG Boneless | T1: =IFERROR(__xludf.DUMMYFUNCTION("""COMPUTED_VALUE"""),"KG Cow H&N") -> KG Cow H&N | U1: =IFERROR(__xludf.DUMMYFUNCTION("""COMPUTED_VALUE"""),"KG Cow Hump") -> KG Cow Hump | V1: =IFERROR(__xludf.DUMMYFUNCTION("""COMPUTED_VALUE"""),"KG Cow Tongue") -> KG Cow Tongue | W1: =IFERROR(__xludf.DUMMYFUNCTION("""COMPUTED_VALUE"""),"KG Goat Meat") -> KG Goat Meat | X1: =IFERROR(__xludf.DUMMYFUNCTION("""COMPUTED_VALUE"""),"KG Chicken") -> KG Chicken | Y1: =IFERROR(__xludf.DUMMYFUNCTION("""COMPUTED_VALUE"""),"KG Hake") -> KG Hake | Z1: =IFERROR(__xludf.DUMMYFUNCTION("""COMPUTED_VALUE"""),"Kg Titus") -> Kg Titus
A2: =IFERROR(__xludf.DUMMYFUNCTION("""COMPUTED_VALUE"""),"ALAKIA") -> ALAKIA | B2: =IFERROR(__xludf.DUMMYFUNCTION("""COMPUTED_VALUE"""),0.0) -> 0 | C2: =IFERROR(__xludf.DUMMYFUNCTION("""COMPUTED_VALUE"""),0.0) -> 0 | D2: =IFERROR(__xludf.DUMMYFUNCTION("""COMPUTED_VALUE"""),0.0) -> 0 | E2: =IFERROR(__xludf.DUMMYFUNCTION("""COMPUTED_VALUE"""),0.0) -> 0 | F2: =IFERROR(__xludf.DUMMYFUNCTION("""COMPUTED_VALUE"""),0.0) -> 0 | G2: =IFERROR(__xludf.DUMMYFUNCTION("""COMPUTED_VALUE"""),0.0) -> 0 | H2: =IFERROR(__xludf.DUMMYFUNCTION("""COMPUTED_VALUE"""),0.0) -> 0 | I2: =IFERROR(__xludf.DUMMYFUNCTION("""COMPUTED_VALUE"""),0.0) -> 0 | ... Z2: =IFERROR(__xludf.DUMMYFUNCTION("""COMPUTED_VALUE"""),0.0) -> 0
A3: =IFERROR(__xludf.DUMMYFUNCTION("""COMPUTED_VALUE"""),"BASHORUN") -> BASHORUN | B3: =IFERROR(__xludf.DUMMYFUNCTION("""COMPUTED_VALUE"""),0.0) -> 0 | C3: =IFERROR(__xludf.DUMMYFUNCTION("""COMPUTED_VALUE"""),0.0) -> 0 | D3: =IFERROR(__xludf.DUMMYFUNCTION("""COMPUTED_VALUE"""),0.0) -> 0 | E3: =IFERROR(__xludf.DUMMYFUNCTION("""COMPUTED_VALUE"""),0.0) -> 0 | F3: =IFERROR(__xludf.DUMMYFUNCTION("""COMPUTED_VALUE"""),0.0) -> 0 | G3: =IFERROR(__xludf.DUMMYFUNCTION("""COMPUTED_VALUE"""),0.0) -> 0 | H3: =IFERROR(__xludf.DUMMYFUNCTION("""COMPUTED_VALUE"""),0.0) -> 0 | I3: =IFERROR(__xludf.DUMMYFUNCTION("""COMPUTED_VALUE"""),0.0) -> 0 | ... Z3: =IFERROR(__xludf.DUMMYFUNCTION("""COMPUTED_VALUE"""),0.0) -> 0
A4: =IFERROR(__xludf.DUMMYFUNCTION("""COMPUTED_VALUE"""),"APATA") -> APATA | B4: =IFERROR(__xludf.DUMMYFUNCTION("""COMPUTED_VALUE"""),0.0) -> 0 | C4: =IFERROR(__xludf.DUMMYFUNCTION("""COMPUTED_VALUE"""),0.0) -> 0 | D4: =IFERROR(__xludf.DUMMYFUNCTION("""COMPUTED_VALUE"""),0.0) -> 0 | E4: =IFERROR(__xludf.DUMMYFUNCTION("""COMPUTED_VALUE"""),0.0) -> 0 | F4: =IFERROR(__xludf.DUMMYFUNCTION("""COMPUTED_VALUE"""),0.0) -> 0 | G4: =IFERROR(__xludf.DUMMYFUNCTION("""COMPUTED_VALUE"""),0.0) -> 0 | H4: =IFERROR(__xludf.DUMMYFUNCTION("""COMPUTED_VALUE"""),0.0) -> 0 | I4: =IFERROR(__xludf.DUMMYFUNCTION("""COMPUTED_VALUE"""),0.0) -> 0 | ... Z4: =IFERROR(__xludf.DUMMYFUNCTION("""COMPUTED_VALUE"""),0.0) -> 0
A5: =IFERROR(__xludf.DUMMYFUNCTION("""COMPUTED_VALUE"""),"BCT") -> BCT | B5: =IFERROR(__xludf.DUMMYFUNCTION("""COMPUTED_VALUE"""),0.0) -> 0 | C5: =IFERROR(__xludf.DUMMYFUNCTION("""COMPUTED_VALUE"""),0.0) -> 0 | D5: =IFERROR(__xludf.DUMMYFUNCTION("""COMPUTED_VALUE"""),0.0) -> 0 | E5: =IFERROR(__xludf.DUMMYFUNCTION("""COMPUTED_VALUE"""),0.0) -> 0 | F5: =IFERROR(__xludf.DUMMYFUNCTION("""COMPUTED_VALUE"""),0.0) -> 0 | G5: =IFERROR(__xludf.DUMMYFUNCTION("""COMPUTED_VALUE"""),0.0) -> 0 | H5: =IFERROR(__xludf.DUMMYFUNCTION("""COMPUTED_VALUE"""),0.0) -> 0 | I5: =IFERROR(__xludf.DUMMYFUNCTION("""COMPUTED_VALUE"""),0.0) -> 0 | ... Z5: =IFERROR(__xludf.DUMMYFUNCTION("""COMPUTED_VALUE"""),0.0) -> 0
A6: =IFERROR(__xludf.DUMMYFUNCTION("""COMPUTED_VALUE"""),"ALESHINLOYE") -> ALESHINLOYE | B6: =IFERROR(__xludf.DUMMYFUNCTION("""COMPUTED_VALUE"""),0.0) -> 0 | C6: =IFERROR(__xludf.DUMMYFUNCTION("""COMPUTED_VALUE"""),0.0) -> 0 | D6: =IFERROR(__xludf.DUMMYFUNCTION("""COMPUTED_VALUE"""),0.0) -> 0 | E6: =IFERROR(__xludf.DUMMYFUNCTION("""COMPUTED_VALUE"""),0.0) -> 0 | F6: =IFERROR(__xludf.DUMMYFUNCTION("""COMPUTED_VALUE"""),0.0) -> 0 | G6: =IFERROR(__xludf.DUMMYFUNCTION("""COMPUTED_VALUE"""),0.0) -> 0 | H6: =IFERROR(__xludf.DUMMYFUNCTION("""COMPUTED_VALUE"""),0.0) -> 0 | I6: =IFERROR(__xludf.DUMMYFUNCTION("""COMPUTED_VALUE"""),0.0) -> 0 | ... Z6: =IFERROR(__xludf.DUMMYFUNCTION("""COMPUTED_VALUE"""),0.0) -> 0
A7: =IFERROR(__xludf.DUMMYFUNCTION("""COMPUTED_VALUE"""),"FELELE") -> FELELE | B7: =IFERROR(__xludf.DUMMYFUNCTION("""COMPUTED_VALUE"""),0.0) -> 0 | C7: =IFERROR(__xludf.DUMMYFUNCTION("""COMPUTED_VALUE"""),0.0) -> 0 | D7: =IFERROR(__xludf.DUMMYFUNCTION("""COMPUTED_VALUE"""),0.0) -> 0 | E7: =IFERROR(__xludf.DUMMYFUNCTION("""COMPUTED_VALUE"""),0.0) -> 0 | F7: =IFERROR(__xludf.DUMMYFUNCTION("""COMPUTED_VALUE"""),0.0) -> 0 | G7: =IFERROR(__xludf.DUMMYFUNCTION("""COMPUTED_VALUE"""),0.0) -> 0 | H7: =IFERROR(__xludf.DUMMYFUNCTION("""COMPUTED_VALUE"""),0.0) -> 0 | I7: =IFERROR(__xludf.DUMMYFUNCTION("""COMPUTED_VALUE"""),0.0) -> 0 | ... Z7: =IFERROR(__xludf.DUMMYFUNCTION("""COMPUTED_VALUE"""),0.0) -> 0
A8: =IFERROR(__xludf.DUMMYFUNCTION("""COMPUTED_VALUE"""),"TOTAL SALES") -> TOTAL SALES | B8: =IFERROR(__xludf.DUMMYFUNCTION("""COMPUTED_VALUE"""),0.0) -> 0 | C8: =IFERROR(__xludf.DUMMYFUNCTION("""COMPUTED_VALUE"""),0.0) -> 0 | D8: =IFERROR(__xludf.DUMMYFUNCTION("""COMPUTED_VALUE"""),0.0) -> 0 | E8: =IFERROR(__xludf.DUMMYFUNCTION("""COMPUTED_VALUE"""),0.0) -> 0 | F8: =IFERROR(__xludf.DUMMYFUNCTION("""COMPUTED_VALUE"""),0.0) -> 0 | G8: =IFERROR(__xludf.DUMMYFUNCTION("""COMPUTED_VALUE"""),0.0) -> 0 | H8: =IFERROR(__xludf.DUMMYFUNCTION("""COMPUTED_VALUE"""),0.0) -> 0 | I8: =IFERROR(__xludf.DUMMYFUNCTION("""COMPUTED_VALUE"""),0.0) -> 0 | ... Z8: =IFERROR(__xludf.DUMMYFUNCTION("""COMPUTED_VALUE"""),0.0) -> 0
A9: =IFERROR(__xludf.DUMMYFUNCTION("""COMPUTED_VALUE"""),"PRICE PER SKU") -> PRICE PER SKU
A10: =IFERROR(__xludf.DUMMYFUNCTION("""COMPUTED_VALUE""")," AMOUNT SOLD PER SKU") -> AMOUNT SOLD PER SKU | B10: =IFERROR(__xludf.DUMMYFUNCTION("""COMPUTED_VALUE"""),0.0) -> 0 | C10: =IFERROR(__xludf.DUMMYFUNCTION("""COMPUTED_VALUE"""),0.0) -> 0 | D10: =IFERROR(__xludf.DUMMYFUNCTION("""COMPUTED_VALUE"""),0.0) -> 0 | E10: =IFERROR(__xludf.DUMMYFUNCTION("""COMPUTED_VALUE"""),0.0) -> 0 | F10: =IFERROR(__xludf.DUMMYFUNCTION("""COMPUTED_VALUE"""),0.0) -> 0 | G10: =IFERROR(__xludf.DUMMYFUNCTION("""COMPUTED_VALUE"""),0.0) -> 0 | H10: =IFERROR(__xludf.DUMMYFUNCTION("""COMPUTED_VALUE"""),0.0) -> 0 | I10: =IFERROR(__xludf.DUMMYFUNCTION("""COMPUTED_VALUE"""),0.0) -> 0 | ... AA10: =IFERROR(__xludf.DUMMYFUNCTION("""COMPUTED_VALUE"""),0.0) -> 0
A11: =IFERROR(__xludf.DUMMYFUNCTION("""COMPUTED_VALUE"""),"TOTAL AMOUNT SOLD") -> TOTAL AMOUNT SOLD | B11: =IFERROR(__xludf.DUMMYFUNCTION("""COMPUTED_VALUE"""),0.0) -> 0

Sheet Daily sales
A1: PRODUCT | B1: =TODAY() -> 45889 | C1: =IFERROR(__xludf.DUMMYFUNCTION("IMPORTRANGE(""https://docs.google.com/spreadsheets/d/1oBfDIwRefgDKmTMY5WskKiEbAKkDNkwzBkuwbN-8H_M/edit#gid=0"",""flat price!B1:B35"")"),"#REF!") -> #REF! | D1: Total price per sku sold daily
A2: ='FC inventory'!D1 -> Agemawo 1kg | B2: =SUM(Apata!B5,Alakia!B5,Bashorun!B5,BCT!B5,Eleyele!B5,Felele!B5) -> 0 | D2: =B2*C2 -> 0
A3: ='FC inventory'!E1 -> Boneless Beef 1kg | B3: =SUM(Apata!C5,Alakia!C5,Bashorun!C5,BCT!C5,Eleyele!C5,Felele!C5) -> 0 | D3: =B3*C3 -> 0
A4: ='FC inventory'!F1 -> Cow Hump 1kg | B4: =SUM(Apata!D$5,Alakia!D$5,Bashorun!D$5,BCT!D$5,Eleyele!D$5,Felele!D$5) -> 0 | D4: =B4*C4 -> 0
A5: ='FC inventory'!G1 -> Cow Head & Neck 1kg | B5: =SUM(Apata!E$5,Alakia!E$5,Bashorun!E$5,BCT!E$5,Eleyele!E$5,Felele!E$5) -> 0 | D5: =B5*C5 -> 0
A6: ='FC inventory'!H1 -> Goat Meat 1kg | B6: =SUM(Apata!F$5,Alakia!F$5,Bashorun!F$5,BCT!F$5,Eleyele!F$5,Felele!F$5) -> 0 | D6: =B6*C6 -> 0
A7: ='FC inventory'!I1 -> Chicken 1kg | B7: =SUM(Apata!G$5,Alakia!G$5,Bashorun!G$5,BCT!G$5,Eleyele!G$5,Felele!G$5) -> 0 | D7: =B7*C7 -> 0
A8: ='FC inventory'!J1 -> Titus 1kg (uncleaned) | B8: =SUM(Apata!H$5,Alakia!H$5,Bashorun!H$5,BCT!H$5,Eleyele!H$5,Felele!H$5) -> 0 | D8: =B8*C8 -> 0
A9: ='FC inventory'!K1 -> Titus 1kg (Cleaned) | B9: =SUM(Apata!I$5,Alakia!I$5,Bashorun!I$5,BCT!I$5,Eleyele!I$5,Felele!I$5) -> 0 | D9: =B9*C9 -> 0
A10: ='FC inventory'!L1 -> Hake 1kg (Cleaned) | B10: =SUM(Apata!J$5,Alakia!J$5,Bashorun!J$5,BCT!J$5,Eleyele!J$5,Felele!J$5) -> 0 | D10: =B10*C10 -> 0
A11: ='FC inventory'!M1 -> Hake 1kg (Uncleaned) | B11: =SUM(Apata!K$5,Alakia!K$5,Bashorun!K$5,BCT!K$5,Eleyele!K$5,Felele!K$5) -> 0 | D11: =B11*C11 -> 0
A12: ='FC inventory'!N1 -> Value Pack (Cow Tongue) | B12: =SUM(Apata!L$5,Alakia!L$5,Bashorun!L$5,BCT!L$5,Eleyele!L$5,Felele!L$5) -> 0 | D12: =B12*C12 -> 0
A13: ='FC inventory'!O1 -> Value Pack (Cow Assorted) | B13: =SUM(Apata!M$5,Alakia!M$5,Bashorun!M$5,BCT!M$5,Eleyele!M$5,Felele!M$5) -> 0 | D13: =B13*C13 -> 0
A14: ='FC inventory'!P1 -> Token Pack (Cow Minced Meat) | B14: =SUM(Apata!N$5,Alakia!N$5,Bashorun!N$5,BCT!N$5,Eleyele!N$5,Felele!N$5) -> 0 | D14: =B14*C14 -> 0
A15: ='FC inventory'!Q1 -> Token Pack (Agemawo) | B15: =SUM(Apata!O$5,Alakia!O$5,Bashorun!O$5,BCT!O$5,Eleyele!O$5,Felele!O$5) -> 0 | D15: =B15*C15 -> 0
A16: ='FC inventory'!R1 -> Token pack(boneless beef) | B16: =SUM(Apata!P$5,Alakia!P$5,Bashorun!P$5,BCT!P$5,Eleyele!P$5,Felele!P$5) -> 0 | D16: =B16*C16 -> 0
A17: ='FC inventory'!S1 -> Token Pack (Cow Tail) | B17: =SUM(Apata!Q$5,Alakia!Q$5,Bashorun!Q$5,BCT!Q$5,Eleyele!Q$5,Felele!Q$5) -> 0 | D17: =B17*C17 -> 0
A18: ='FC inventory'!T1 -> Token Pack (Cow Head & Neck) | B18: =SUM(Apata!R$5,Alakia!R$5,Bashorun!R$5,BCT!R$5,Eleyele!R$5,Felele!R$5) -> 0 | D18: =B18*C18 -> 0
A19: ='FC inventory'!U1 -> Token Pack (Cow Hump) | B19: =SUM(Apata!S$5,Alakia!S$5,Bashorun!S$5,BCT!S$5,Eleyele!S$5,Felele!S$5) -> 0 | D19: =B19*C19 -> 0
A20: ='FC inventory'!V1 -> Token Pack (Goat Meat) | B20: =SUM(Apata!T$5,Alakia!T$5,Bashorun!T$5,BCT!T$5,Eleyele!T$5,Felele!T$5) -> 0 | D20: =B20*C20 -> 0
A21: ='FC inventory'!W1 -> Token Pack (Chicken) | B21: =SUM(Apata!U$5,Alakia!U$5,Bashorun!U$5,BCT!U$5,Eleyele!U$5,Felele!U$5) -> 0 | D21: =B21*C21 -> 0
A22: ='FC inventory'!X1 -> Token Pack (Chicken Gizzard) | B22: =SUM(Apata!V$5,Alakia!V$5,Bashorun!V$5,BCT!V$5,Eleyele!V$5,Felele!V$5) -> 0 | D22: =B22*C22 -> 0
A23: ='FC inventory'!Y1 -> Token Pack (Pomo) | B23: =SUM(Apata!W$5,Alakia!W$5,Bashorun!W$5,BCT!W$5,Eleyele!W$5,Felele!W$5) -> 0 | D23: =B23*C23 -> 0
A24: ='FC inventory'!Z1 -> Token Pack (Shaki & Roundabout) | B24: =SUM(Apata!X$5,Alakia!X$5,Bashorun!X$5,BCT!X$5,Eleyele!X$5,Felele!X$5) -> 0 | D24: =B24*C24 -> 0
A25: ='FC inventory'!AA1 -> Token Pack (Cow Assorted) | B25: =SUM(Apata!Y$5,Alakia!Y$5,Bashorun!Y$5,BCT!Y$5,Eleyele!Y$5,Felele!Y$5) -> 0 | D25: =B25*C25 -> 0
A26: ='FC inventory'!AB1 -> Token Pack (Cow Leg) | B26: =SUM(Apata!Z$5,Alakia!Z$5,Bashorun!Z$5,BCT!Z$5,Eleyele!Z$5,Felele!Z$5) -> 0 | D26: =B26*C26 -> 0
A27: ='FC inventory'!AC1 -> Token Pack (Goat Assorted) | B27: =SUM(Apata!AA$5,Alakia!AA$5,Bashorun!AA$5,BCT!AA$5,Eleyele!AA$5,Felele!AA$5) -> 0 | D27: =B27*C27 -> 0
A28: ='FC inventory'!AD1 -> Token Pack (Titus) | B28: =SUM(Apata!AB$5,Alakia!AB$5,Bashorun!AB$5,BCT!AB$5,Eleyele!AB$5,Felele!AB$5) -> 0 | D28: =B28*C28 -> 0
A29: ='FC inventory'!AE1 -> Token Pack (Hake) | B29: =SUM(Apata!AC$5,Alakia!AC$5,Bashorun!AC$5,BCT!AC$5,Eleyele!AC$5,Felele!AC$5) -> 0 | D29: =B29*C29 -> 0
A30: ='FC inventory'!AF1 -> Token (small snail) | B30: =SUM(Apata!AD$5,Alakia!AD$5,Bashorun!AD$5,BCT!AD$5,Eleyele!AD$5,Felele!AD$5) -> 0 | D30: =B30*C30 -> 0
A31: ='FC inventory'!AG1 -> Token (big snail) | B31: =SUM(Apata!AE$5,Alakia!AE$5,Bashorun!AE$5,BCT!AE$5,Eleyele!AE$5,Felele!AE$5) -> 0 | D31: =B31*C31 -> 0
A32: ='FC inventory'!AH1 -> Token (Goat head & leg) | B32: =SUM(Apata!AF$5,Alakia!AF$5,Bashorun!AF$5,BCT!AF$5,Eleyele!AF$5,Felele!AF$5) -> 0 | D32: =B32*C32 -> 0
A33: TOTAL UNIT SOLD ACROSS ALL CENTRES | B33: =SUM(B2:B32) -> 0 | D33: =SUM(D2:D32) -> 0
A34: AVERAGE COST PER SKU SOLD | D34: =D33/B33 -> #DIV/0!
